Workbook
Name EAR_Machines: 'Rate-IndividualMachines'!$K$2:$K$109
Name EAR_01___Public_Utilities: 'Rate-SubGroup'!$A$2:$A$58
Name EAR_02___Industrial_Plant_Utilities: 'Rate-SubGroup'!$A$59:$A$70
Name EAR_03___Mining_Industry: 'Rate-SubGroup'!$A$71:$A$74
Name EAR_04___Chemical_Industry: 'Rate-SubGroup'!$A$75:$A$92
Name EAR_05___Metal_Industry: 'Rate-SubGroup'!$A$93:$A$99
Name EAR_06___Building_Industry: 'Rate-SubGroup'!$A$100:$A$104
Name EAR_07___Timber___Wood: 'Rate-SubGroup'!$A$105:$A$107
Name EAR_08___Pulp___Paper: 'Rate-SubGroup'!$A$108:$A$109
Name EAR_09___Printing___Packing: 'Rate-SubGroup'!$A$110:$A$111
Name EAR_10___Leather_Industry: 'Rate-SubGroup'!$A$112:$A$113
Name EAR_11___Textile_Industry: 'Rate-SubGroup'!$A$114:$A$120
Name EAR_12___Plastic___Rubber: 'Rate-SubGroup'!$A$121:$A$126
Name EAR_13___Food__Vegetable_: 'Rate-SubGroup'!$A$127:$A$135
Name EAR_14___Food__Animal_: 'Rate-SubGroup'!$A$136:$A$138
Name EAR_15___Food_Refrigeration: 'Rate-SubGroup'!$A$139:$A$140
Name EAR_16___Transport___Warehouses: 'Rate-SubGroup'!$A$141:$A$144
Name EAR_17___Public_Services: 'Rate-SubGroup'!$A$145:$A$147
Name EAR_18___Hospitals___Hotels: 'Rate-SubGroup'!$A$148:$A$149
Name EAR_19___Farming___Agriculture: 'Rate-SubGroup'!$A$150:$A$152
Name EAR_Clauses: 'Rate-Clauses'!$I$2:$I$27
Name EAR_Groups: 'Rate-SubGroup'!$N$2:$N$20
Name HZP_01: 'Hazard-Cities-2800'!$C$2:$C$22
Name HZP_02: 'Hazard-Cities-2800'!$C$23:$C$41
Name HZP_03: 'Hazard-Cities-2800'!$C$42:$C$56
Name HZP_04: 'Hazard-Cities-2800'!$C$57:$C$88
Name HZP_05: 'Hazard-Cities-2800'!$C$89:$C$96
Name HZP_06: 'Hazard-Cities-2800'!$C$97:$C$116
Name HZP_07: 'Hazard-Cities-2800'!$C$117:$C$142
Name HZP_08: 'Hazard-Cities-2800'!$C$143:$C$155
Name HZP_09: 'Hazard-Cities-2800'!$C$156:$C$181
Name HZP_10: 'Hazard-Cities-2800'!$C$182:$C$191
Name HZP_11: 'Hazard-Cities-2800'!$C$192:$C$221
Name HZP_12: 'Hazard-Cities-2800'!$C$222:$C$231
Name HZP_13: 'Hazard-Cities-2800'!$C$232:$C$252
Name HZP_14: 'Hazard-Cities-2800'!$C$253:$C$274
Name HZP_15: 'Hazard-Cities-2800'!$C$275:$C$304
Name HZP_16: 'Hazard-Cities-2800'!$C$305:$C$311
Name HZP_17: 'Hazard-Cities-2800'!$C$312:$C$316
Name HZP_18: 'Hazard-Cities-2800'!$C$317:$C$325
Name HZP_19: 'Hazard-Cities-2800'!$C$326:$C$347
Name HZP_20: 'Hazard-Cities-2800'!$C$348:$C$360
Name HZP_21: 'Hazard-Cities-2800'!$C$361:$C$373
Name HZP_22: 'Hazard-Cities-2800'!$C$374:$C$382
Name HZP_23: 'Hazard-Cities-2800'!$C$383:$C$394
Name HZP_24: 'Hazard-Cities-2800'!$C$395:$C$402
Name HZP_25: 'Hazard-Cities-2800'!$C$403:$C$423
Name HZP_26: 'Hazard-Cities-2800'!$C$424:$C$440
Name HZP_27: 'Hazard-Cities-2800'!$C$441:$C$444
Name HZP_28: 'Hazard-Cities-2800'!$C$445:$C$454
Name HZP_29: 'Hazard-Cities-2800'!$C$455:$C$472
Name HZP_30: 'Hazard-Cities-2800'!$C$473:$C$490

Sheet محاسبه-ساده
A1: 🧮 محاسبهٔ سریع حق‌بیمهٔ EAR
A3: =IF(AND(LEFT(Data!E75,1)="✓",LEFT(Data!E76,1)="✓",LEFT(Data!E77,1)="✓",LEFT(Data!E79,1)="✓",LEFT(Data!E80,1)="✓",LEFT(Data!E93,1)="✓"),"🟢 آماده محاسبه — همهٔ ورودی‌ها معتبرند","🔴 یکی از ورودی‌ها را بررسی کنید (شیت Data ردیف‌های K را ببینید)") -> 🟢 آماده محاسبه — همهٔ ورودی‌ها معتبرند
A4: نرخ فنی نهایی (بدون TPL) | C4: =Data!D60 -> 4.1
A5: حق‌بیمهٔ کل قابل‌پرداخت (﷼) | C5: =Data!E73 -> 165480129095
A8: ۱) مشخصات پروژه
B9: دامنهٔ پروژه (Project Scope) | C9: کل پروژه (Entire Project) | D9: کل پروژه = جداول سفید · ماشین‌آلات منفرد = جداول آبی (بند ۲.۵ سوییس‌ری)
B10: گروه صنعتی | C10: 05 — Metal Industry | D10: از فهرست انتخاب کنید
B11: زیرگروه پروژه ⟨فقط حالت کل پروژه⟩ | C11: 12.5 Paint factories and processing of comparable products | D11: بر اساس گروه بالا فیلتر می‌شود
B12: ماشین منفرد ⟨فقط حالت ماشین‌آلات منفرد⟩ | C12: 02.0.1 — Boiler feed pumps, incl. drive — turbine driven | D12: از جداول آبی — ۱۰۸ ماشین، با کد EAR برای جلوگیری از هم‌نامی
B13: مدت کل پروژه (ماه) ⟨فقط حالت کل پروژه⟩ | C13: 15 | D13: نصب + آزمایش، جمعاً
B14: ماه‌های نصب ⟨ماشین منفرد⟩ | C14: 3 | D14: نرخ پایه شامل ۳ ماه است · قابل تمدید تا حداکثر ۹ ماه (بند ۲.۵)
B15: ماه‌های آزمایش ⟨ماشین منفرد⟩ | C15: 1 | D15: نرخ پایه شامل ۱ ماه است · قابل تمدید تا حداکثر ۳ ماه (بند ۲.۵)
B16: استان | C16: قم | D16: از فهرست انتخاب کنید
B17: شهرستان | C17: قم | D17: ="بر اساس استان فیلتر می‌شود · سطح خطر زلزلهٔ شهر انتخابی: "&Data!E7 -> بر اساس استان فیلتر می‌شود · سطح خطر زلزلهٔ شهر انتخابی: زیاد
A19: ۲) مبلغ‌ها
B20: مبلغ بیمه — ارزش کل پروژه (﷼) | C20: 30638794500000 | D20: مبنای اصلی محاسبهٔ حق‌بیمه
B21: سقف مسئولیت شخص ثالث TPL (﷼) | C21: 6127758900000 | D21: سقف غرامت مسئولیت مدنی
B22: پوشش مسئولیت شخص ثالث (TPL) اصلاً وجود دارد؟ | C22: Yes | D22: اگر No باشد، کل حق‌بیمهٔ TPL (پایه + مسئولیت متقابل) صفر می‌شود و ردیف‌های ۲۶ تا ۲۸ نادیده گرفته می‌شوند
A23: ۳) گزینه‌های رایج (بیشتر پروژه‌ها این‌ها را دارند)
B24: آزمایش/راه‌اندازی (Testing) شامل شود؟ | C24: Yes | D24: اگر پروژه دورهٔ آزمایش دارد
B25: طبقهٔ نگهداری | C25: Heavy | D25: سبک (Light) یا سنگین/شیمیایی (Heavy)
B26: نگهداری ساده — مدت (ماه) | C26: 0 | D26: ۰ یعنی ندارد
B27: نگهداری گسترده — مدت (ماه) | C27: 0 | D27: ۰ یعنی ندارد
B28: کلاس حساسیت تجهیزات در برابر زلزله (۱ تا ۴) | C28: 2 | D28: ۱=غیرحساس … ۴=بسیار حساس
B29: کلاس مقاومت سازهٔ ساختمان (۱ تا ۶) | C29: 3 | D29: ۱=فولادی سبک … ۶=بنایی آجری
B30: ردهٔ ریسک فنی TPL | C30: III (Heavy) | D30: سبک / متوسط / سنگین
B31: ردهٔ محیط اطراف کارگاه (TPL) | C31: b — outer town (moderate density) | D31: سایت ایزوله / حومه / مرکز شهر
B32: مسئولیت متقابل (Cross Liability) شامل شود؟ | C32: Yes | D32: ٪۳۵ اضافه بر حق‌بیمهٔ TPL
A34: ۴) گزینه‌های تکمیلی (فقط اگر پروژه دارد وارد کنید)
B35: ریسک سازندهٔ تجهیزات — نقص مواد/کارگری (ماه) | C35: 0 | D35: ۰ = ندارد
B36: ریسک سازندهٔ تجهیزات — نقص طراحی (ماه) | C36: 0 | D36: ۰ = ندارد
B37: هزینهٔ تسریع — درصد از نرخ کار (اعشاری) | C37: 0 | D37: مثلاً ۰.۰۷۵ برای ۷.۵٪ · ۰ = ندارد
B38: شورش و اعتصاب — نرخ آتش‌نشانی (‰) | C38: 0 | D38: از بازار بیمهٔ آتش‌سوزی محلی بگیرید · ۰ = ندارد
B39: شورش و اعتصاب — دوره | C39: Testing/Commissioning period | D39: نصب یا آزمایش
B40: هوابرد — سقف تعهد (﷼) | C40: 0 | D40: ۰ = ندارد
B41: هوابرد — نرخ (‰) | C41: 0 | D41: ۵‰ زیر ۲۰۰۰ مایل، تا ۲۰‰ فاصلهٔ بیشتر
B42: انبارداری پیش از نصب — ارزش کالا (﷼) | C42: 0 | D42: ۰ = ندارد
B43: انبارداری پیش از نصب — مدت (ماه) | C43: 0 | D43: ۰ = ندارد
B44: ترانزیت زمینی — ارزش کالای در حال حمل (﷼) | C44: 0 | D44: ۰ = ندارد
B45: رفع نخاله — سقف هر رویداد (﷼) | C45: 0 | D45: ۰ = ندارد
B46: اموال مجاور — نوع پوشش | C46: Not included — existing property not covered | D46: پوشش اموال موجود در محل کارگاه
B47: اموال مجاور — سقف هر رویداد (﷼) | C47: 0 | D47: ۰ = ندارد
B48: معافیت زلزله (Earthquake Exclusion) اعمال شود؟ | C48: No | D48: در صورت Yes، بارگذاری زلزله صفر می‌شود
A50: ۵) تنظیمات مالی
B51: تعدیل نرخ‌گذار (اعشاری؛ منفی=تخفیف) | C51: 0 | D51: مثلاً ‎-0.1 برای ۱۰٪ تخفیف
B52: کارمزد نمایندگی (اعشاری) | C52: 0 | D52: مثلاً ۰.۱ برای ۱۰٪
B53: مالیات/عوارض بیمه (اعشاری) | C53: 0.1 | D53: نرخ فعلی ایران: ۰.۰۹
A55: ۶) تنظیم بلایای طبیعی برای حالت ماشین‌آلات منفرد
B56: بارگذاری بلایای طبیعی برای ماشین منفرد؟ | C56: No | D56: طبق بند ۲.۵ پیش‌فرض No · فقط اگر دورهٔ بازگشت رویداد فاجعه‌بار کمتر از ۱۰ سال باشد Yes کنید

Sheet Data
A1: EAR (Erection All Risks) — Premium Rating Engine · Swiss Re EAR methodology
A2: # | B2: Input / Parameter | C2: Selected Value | E2: Computed | F2: Notes / Swiss Re guidance
A3: A RISK CLASSIFICATION
A4: A1 | B4: Industry Group | C4: ='محاسبه-ساده'!C10 -> 05 — Metal Industry | F4: Select industry group. Drives the sub-group list.
A5: A2 | B5: Project Sub-Group | C5: ='محاسبه-ساده'!C11 -> 12.5 Paint factories and processing of comparable products | F5: Auto-filtered by group. Full EAR name incl. size band — this drives all base rates. | I5: =SUBSTITUTE(SUBSTITUTE(SUBSTITUTE(SUBSTITUTE(SUBSTITUTE(SUBSTITUTE(SUBSTITUTE(C4," ","_"),"-","_"),"—","_"),"(","_"),")","_"),"&","_"),"/","_") -> 05___Metal_Industry | J5: ="EAR_"&I5 -> EAR_05___Metal_Industry
A6: A3 | B6: Project Duration (months) | C6: ='محاسبه-ساده'!C13 -> 15 | F6: Total erection + testing period. Drives month-band rate build-up.
A7: A4 | B7: Province (Iran) — Standard 2800 | C7: ='محاسبه-ساده'!C16 -> قم | E7: =IFERROR(INDEX('Hazard-Cities-2800'!$E:$E,MATCH($C$8&" — "&$C$7,'Hazard-Cities-2800'!$B:$B,0)),"#not found") -> زیاد | F7: Select Province here; City/Town auto-filters in the row below (C8). Hazard level (E7) is read from the Standard 2800 (4th ed.) Appendix 1 classification, 489 county-seat points — sheet 'Hazard-Cities-2800'.
A8: A5 | B8: City/Town (auto-filtered by Province) | C8: ='محاسبه-ساده'!C17 -> قم | F8: City/town auto-filtered to the Province selected in C7 (Standard 2800 Appendix 1 classification, 489 county-seat points — sheet 'Hazard-Cities-2800'). Hazard level result shown in E7. | H8: =IFERROR(INDEX('Hazard-Province-Index'!$C:$C,MATCH($C$7,'Hazard-Province-Index'!$B:$B,0)),"#unknown province") -> HZP_17 | I8: Safe defined-name code driving the C8 dropdown (INDIRECT target) — same pattern as I5/J5 for Group→Sub-group.
A9: B BASE ERECTION RATE (from Rate-SubGroup, by month-band)
A10: B1 | B10: Base Erection Rate (banded, ‰) | E10: =IFERROR(IF($C$6<=1,INDEX('Rate-SubGroup'!$B$2:$B$152,MATCH($C$5,'Rate-SubGroup'!$A$2:$A$152,0)),IF($C$6<=12,INDEX('Rate-SubGroup'!$B$2:$B$152,MATCH($C$5,'Rate-SubGroup'!$A$2:$A$152,0))+($C$6-1)*INDEX('Rate-SubGroup'!$C$2:$C$152,MATCH($C$5,'Rate-SubGroup'!$A$2:$A$152,0)),IF($C$6<=24,INDEX('Rate-SubGroup'!$B$2:$B$152,MATCH($C$5,'Rate-SubGroup'!$A$2:$A$152,0))+11*INDEX('Rate-SubGroup'!$C$2:$C$152,MATCH($C$5,'Rate-SubGroup'!$A$2:$A$152,0))+($C$6-12)*INDEX('Rate-SubGroup'!$D$2:$D$152,MATCH($C$5,'Rate-SubGroup'!$A$2:$A$152,0)),INDEX('Rate-SubGroup'!$B$2:$B$152,MATCH($C$5,'Rate-SubGroup'!$A$2:$A$152,0))+11*INDEX('Rate-SubGroup'!$C$2:$C$152,MATCH($C$5,'Rate-SubGroup'!$A$2:$A$152,0))+12*INDEX('Rate-SubGroup'!$D$2:$D$152,MATCH($C$5,'Rate-SubGroup'!$A$2:$A$152,0))+($C$6-24)*INDEX('Rate-SubGroup'!$E$2:$E$152,MATCH($C$5,'Rate-SubGroup'!$A$2:$A$152,0))))),"#sub-group not found") -> 3.025 | F10: 1st-month Code1 + 0.10/0.05/0.025 bands per Swiss Re month structure.
A11: B2 | B11: Minimum Rate (floor, ‰) | E11: =IFERROR(INDEX('Rate-SubGroup'!$H$2:$H$152,MATCH($C$5,'Rate-SubGroup'!$A$2:$A$152,0)),"") -> 3.65 | F11: Erection rate cannot fall below this Swiss Re floor.
A12: B3 | B12: Hot Testing / Commissioning included? | C12: ='محاسبه-ساده'!C24 -> Yes | E12: =IF($I$86="M",0,IF($C$12="Yes",IFERROR(INDEX('Rate-SubGroup'!$F$2:$F$152,MATCH($C$5,'Rate-SubGroup'!$A$2:$A$152,0)),0),0)) -> 0.45 | F12: First-month testing rate (Rate-SubGroup col F) if Yes.
A13: B4 | B13: Effective Erection Rate (‰) | E13: =IF($I$86="M",$E$91,IFERROR(MAX(E10,E11),0)) -> 3.65 | F13: MAX(banded base, minimum-rate floor).
A14: B5 | B14: Reference Rate (‰) | E14: =IF($I$86="M",$E$92,IFERROR(INDEX('Rate-SubGroup'!$G$2:$G$152,MATCH($C$5,'Rate-SubGroup'!$A$2:$A$152,0)),0)) -> 3 | F14: Basis for Manufacturer's-Risk & maintenance loadings (col G).
A15: C EARTHQUAKE LOADING (Swiss Re real method: E = E1 × E2, Table E monthly rate × project duration) | G15: Helper calculations (not part of visible rate build-up):
A16: EQ1 | B16: Plant Sensitivity Class (Table E1, 1–4) | C16: ='محاسبه-ساده'!C28 -> 2 | E16: =IFERROR(INDEX('Rate-EQ-SwissRe'!$D$5:$D$8,MATCH($C$16,'Rate-EQ-SwissRe'!$A$5:$A$8,0)),"#invalid class") -> 2 | F16: Select 1-4 per Rate-EQ-SwissRe sheet Table E1 (equipment sensitivity). Returns factor E1.
A17: EQ2 | B17: Structure Factor Class (Table E2, 1–6) | C17: ='محاسبه-ساده'!C29 -> 3 | E17: =IFERROR(INDEX('Rate-EQ-SwissRe'!$D$12:$D$17,MATCH($C$17,'Rate-EQ-SwissRe'!$A$12:$A$17,0)),"#invalid class") -> 2 | F17: Select 1-6 per Rate-EQ-SwissRe sheet Table E2 (building/structure resistance). Returns factor E2.
A18: EQ3 | B18: Combined Sensitivity Factor E = E1 × E2 | E18: =E16*E17 -> 4 | F18: Real Swiss Re combined factor (was hardcoded/deprecated before this revision). | G18: =IF(E18<=1,1,IF(E18<=1.5,1.5,IF(E18<=2,2,IF(E18<=2.5,2.5,IF(E18<=3,3,IF(E18<=4,4,IF(E18<=5,5,IF(E18<=6,6,IF(E18<=8,8,IF(E18<=10,10,IF(E18<=12.5,12.5,IF(E18<=15,15,20)))))))))))) -> 4 | H18: E rounded UP to nearest Table E value (conservative assumption — see Rate-EQ-SwissRe notes)
A19: EQ4 | B19: Swiss Re Zone (derived from city hazard level, Standard 2800) | E19: =IFERROR(INDEX('Rate-EQ-SwissRe'!$B$21:$B$24,MATCH($E$7,'Rate-EQ-SwissRe'!$A$21:$A$24,0)),"#level not mapped") -> C | F19: Maps the city's Standard 2800 hazard level (E7) to a Swiss Re zone per the user-approved table in 'Rate-EQ-SwissRe' (خیلی‌زیاد→B, زیاد→C, متوسط→D, کم→E). Replaces the old 1.00/1.15 provincial multiplier entirely. | G19: =IFERROR(INDEX('Rate-EQ-SwissRe'!$B$29:$F$41,MATCH($G$18,'Rate-EQ-SwissRe'!$A$29:$A$41,0),MATCH($E$19,{"A","B","C","D","E"},0)),0) -> 0 | H19: Monthly earthquake rate (‰) from Table E, for rounded E and derived Zone
A20: EQ5 | B20: Earthquake Exclusion clause? | C20: ='محاسبه-ساده'!C48 -> No | F20: If Yes, EQ loading is forced to 0 (and must be excluded from TPL too).
A21: EQ6 | B21: Earthquake Loading (‰) | E21: =IF($C$20="Yes",0,ROUND($G$19*$C$6,4)) -> 0 | F21: Loading = monthly rate from Table E (G19) x project duration in months (C6, erection+testing). Real Swiss Re monthly-accrual method - replaces the old flat (rate x (loading factor - 1)) formula. Section I rate-summary structure (D59:D63) is unchanged.
A22: D EXISTING PROPERTY (premium on its own limit per event)
A23: D1 | B23: نگهداری گسترده — مدت (ماه) | C23: ='محاسبه-ساده'!C46 -> Not included — existing property not covered | D23: ='محاسبه-ساده'!C47 -> 0 | E23: =IFERROR(VLOOKUP($C$23,'Rate-Asset'!$A:$B,2,0),0) -> 0 | F23: Rate ‰ per event (Rate-Asset, ﷼ column). Premium applies to the limit, not the SI.
A24: D2 | B24: Existing Property — Limit per event (﷼) → Premium | E24: =ROUND(E23*D23/1000,0) -> 0 | F24: Enter limit per event in D23. Premium = rate × limit / 1000.
A25: E EXTENSIONS — RATE LOADINGS (‰ added to the MD rate, on contract value)
A26: ▸ | B26: Enter 0 (or “No”) to exclude an item. Loadings here are ‰ on the Sum Insured.
A27: E1 | B27: Manufacturer's Risk — Material/Workmanship (6.1.1): test/maint months | C27: ='محاسبه-ساده'!C35 -> 0 | D27: سایت ایزوله / حومه / مرکز شهر | E27: =IF(C27<=0,0,IF(C27<=3,0.05,IF(C27<=6,0.075,0.1))*E14) -> 0 | F27: 5% (1–3 mo) / 7.5% (4–6) / 10% (7+) of Ref.Rate.
A28: E2 | B28: Manufacturer's Risk — Defective Design (6.1.2): test/maint months | C28: ='محاسبه-ساده'!C36 -> 0 | E28: =IF(C28<=0,0,IF(C28<=3,0.05,IF(C28<=6,0.075,0.1))*E14) -> 0 | F28: Same scale as 6.1.1, on Ref.Rate.
A29: E3 | B29: Maintenance industry class | C29: ='محاسبه-ساده'!C25 -> Heavy | F29: Light vs power/chemical/heavy — sets maintenance % scale.
A30: E4 | B30: Visits Maintenance (6.2.1): maintenance months | C30: ='محاسبه-ساده'!C26 -> 0 | E30: =IF(C30<=0,0,IF(C29="Heavy",0.075,0.05)*E14*(C30/12)) -> 0 | F30: 5% light / 7.5% heavy of Ref.Rate per 12-mo period (pro-rata).
A31: E5 | B31: Extended Maintenance (6.2.2): maintenance months | C31: ='محاسبه-ساده'!C27 -> 0 | E31: =IF(C31<=0,0,IF(C29="Heavy",0.125,0.075)*E14*(C31/12)) -> 0 | F31: 7.5% light / 12.5% heavy of Ref.Rate per 12-mo period (pro-rata).
A32: E6 | B32: Expediting Costs (5.3): % of works rate | C32: ='محاسبه-ساده'!C37 -> 0 | E32: =IF(C32<=0,0,C32*E13) -> 0 | F32: 5–10% of the erection (works) rate. Enter as decimal, e.g. 0.075.
A33: E7 | B33: Riot and Strike (6.4): Fire Dept / FOC riot-and-strike rate (‰) | C33: ='محاسبه-ساده'!C38 -> 0 | F33: This is an EXTERNAL rate — Swiss Re does not tabulate it. Obtain the local Fire Department's (or FOC London-style) riot-and-strike rate for the property/plant, then enter it here as a ‰ figure. Excludes civil commotion unless separately agreed with the Reinsurer.
A34: E8 | B34: Riot and Strike — period basis | C34: ='محاسبه-ساده'!C39 -> Testing/Commissioning period | E34: =IF(C33<=0,0,C33*IF(C34="Testing/Commissioning period",1,0.5)) -> 0 | F34: Testing/Commissioning period = 100% of the rate above (confirmed, EAR Rating Guide Sec.9 item 6.4). Erection period = 50% shown here, but this figure could NOT be verified in the uploaded Swiss Re source after two independent searches — flagged as insufficient evidence; confirm with reinsurer before relying on it.
A35: E9 | B35: Rate-loadings sub-total (‰) | E35: =E27+E28+E30+E31+E32+E34 -> 0 | F35: Sum of the loadings above.
A36: F EXTENSIONS — PREMIUM ADD-ONS (c-units, each on its own basis)
A37: ▸ | B37: These apply to a separate limit/value, NOT the SI, so they are priced as premiums (﷼), not ‰.
A38: F1 | B38: Air Freight (5.4): aggregate limit (C, ﷼) · rate ‰ (D) | C38: ='محاسبه-ساده'!C40 -> 0 | D38: ='محاسبه-ساده'!C41 -> 0 | E38: =ROUND(D38*C38/1000,0) -> 0 | F38: 5‰ <2000 mi, up to 20‰ longer. Premium = rate × limit / 1000.
A39: F2 | B39: Storage Pre-Erection (5.5): value stored (C, ﷼) · months (D) | C39: ='محاسبه-ساده'!C42 -> 0 | D39: ='محاسبه-ساده'!C43 -> 0 | E39: =ROUND(0.1*C39*D39/1000,0) -> 0 | F39: Min 0.1‰/month on value stored.
A40: F3 | B40: Inland Transit (6.5): value transported (C, ﷼) | C40: ='محاسبه-ساده'!C44 -> 0 | E40: =ROUND(1*C40/1000,0) -> 0 | F40: Min 1‰ on total value transported (marine specialist rate).
A41: F4 | B41: Clearance of Debris >threshold (5.2): limit per event (﷼) | C41: ='محاسبه-ساده'!C45 -> 0 | E41: =IF($C$41>'Currency-Conversion'!$C$14,ROUND($E$13*$C$41/1000,0),0) -> 0 | F41: Threshold and rate both in ﷼ now — see 'Currency-Conversion' sheet row 14 for the converted threshold (was 100,000 c-units).
A42: F5 | B42: Premium add-ons sub-total (﷼) | E42: =E24+E38+E39+E40+E41 -> 0 | F42: Existing property + air freight + storage + transit + debris.
A43: G THIRD PARTY LIABILITY (calculated once, from Rate-TPL)
A44: G1 | B44: TPL — Technical Risk Category | C44: ='محاسبه-ساده'!C30 -> III (Heavy) | F44: I Light / II Medium / III Heavy (Rate-TPL B.1). | H44: TPL Included? | I44: ='محاسبه-ساده'!C22 -> Yes
A45: G2 | B45: TPL — Surroundings Category | C45: ='محاسبه-ساده'!C31 -> b — outer town (moderate density) | F45: a isolated / b outer town / c dense-urban.
A46: G3 | B46: TPL — Total Limit (﷼) | C46: ='محاسبه-ساده'!C21 -> 6127758900000 | F46: Limit of indemnity in ﷼; sets the adaptation factor via 'Currency-Conversion' sheet rows 18-24 (Rial-equivalent of the original 0.5-10 million c-unit bands).
A47: G4 | B47: TPL — Base Rate (‰) | E47: =IFERROR(INDEX('Rate-TPL'!$C$4:$E$6,MATCH($C$44,{"I (Light)","II (Medium)","III (Heavy)"},0),MATCH($C$45,{"a — isolated site","b — outer town (moderate density)","c — central/urban"},0)),0) -> 0.6 | F47: Rate at 2-mio base, by category × surroundings.
A48: G5 | B48: TPL — Limit Adaptation Factor | C48: 0 | E48: =IFERROR(INDEX('Rate-TPL'!$B$9:$B$15,MATCH($C$46,'Currency-Conversion'!$C$18:$C$24,1)),1) -> 1 | F48: Factor for the chosen total limit (Rate-TPL B.2).
A49: G6 | B49: TPL — Effective Rate (‰) | C49: 0.1 | E49: =E47*E48 -> 0.6 | F49: Base rate × limit factor.
A50: G7 | B50: Cross Liability (6.3) included? | C50: ='محاسبه-ساده'!C32 -> Yes | F50: 35% surcharge on TPL premium if Yes.
A51: G8 | B51: TPL Premium (﷼) | E51: =IF($I$44="No",0,IFERROR(ROUND($C$62*E49/1000,0),0)) -> 0 | F51: TPL rate × contract value (SI). Minimum-premium floor (Rate-TPL F:K) removed per user instruction — see Changelog v14–v15. Base TPL rate table itself is unchanged. Zeroed entirely if TPL Included (کش‌ساده!C18) = No.
A52: G9 | B52: Cross Liability surcharge (﷼) | E52: =IF($C$50="Yes",ROUND(0.35*E51,0),0) -> 6434146845 | F52: 35% of TPL premium, only if selected (G7).
A53: G10 | B53: TPL Total (﷼) | E53: =E51+E52 -> 24817423545 | F53: TPL premium + cross-liability.
A54: I RATE SUMMARY (MD technical rate, ‰)
A55: # | B55: Component | D55: Rate (‰) | E55: Notes
A56: S1 | B56: Effective Erection Rate | D56: =E13 -> 3.65 | E56: Base or floor, whichever higher
A57: S2 | B57: Hot Testing / Commissioning | D57: =E12 -> 0.45 | E57: First-month testing rate
A58: S3 | B58: Earthquake Loading | D58: =IF(AND($I$86="M",$C$90="No"),0,E21) -> 0 | E58: E1×E2 method
A59: S4 | B59: Extension Rate-Loadings | D59: =E35 -> 0 | E59: MR + maintenance + expediting
A60: S5 | B60: MD TECHNICAL RATE (‰) | D60: =D56+D57+D58+D59 -> 4.1 | E60: TPL is NOT in this rate — it is a separate premium (section J).
A61: J PREMIUM CALCULATION (c-units; 1 c-unit ≈ 1 USD @1997)
A62: P1 | B62: Sum Insured — Material Damage (﷼) | C62: ='محاسبه-ساده'!C20 -> 30638794500000 | F62: Total contract / erection value.
A63: P2 | B63: Underwriting Adjustment (decimal; − = discount) | C63: ='محاسبه-ساده'!C51 -> 0 | F63: e.g. -0.10 = 10% discount, +0.05 = 5% loading.
A64: P3 | B64: MD Office Rate (‰) | E64: =ROUND(D60*(1+C63),4) -> 4.1 | F64: MD technical rate × (1 + UW adjustment).
A65: P4 | B65: Indicative Minimum Premium (﷼) | E65: =IFERROR(INDEX('Rate-SubGroup'!$K$2:$K$152,MATCH($C$5,'Rate-SubGroup'!$A$2:$A$152,0)),'Currency-Conversion'!$C$15) -> 3.0638794e+09 | F65: INFORMATIONAL ONLY — no longer applied to the premium calc (was General Excess mis-mapped as a minimum premium; removed in v15). Kept here for audit-trail visibility only.
A66: P5 | B66: Gross MD Premium (﷼) | E66: =ROUND(C62*E64/1000,0) -> 0 | F66: SI × office rate / 1000. Minimum-premium floor removed per user instruction — see Changelog v14–v15. (Rate floor E11/E13 unaffected.)
A67: P6 | B67: Premium Add-ons (﷼) | E67: =E42 -> 0 | F67: From section F (separate-basis covers).
A68: P7 | B68: TPL Total (﷼) | E68: =E53 -> 24817423545 | F68: From section G (incl. cross-liability).
A69: P8 | B69: GROSS PREMIUM (﷼) | E69: =E66+E67+E68 -> 150436480995 | F69: MD + add-ons + TPL — the office premium before tax.
A70: P9 | B70: Brokerage / Commission (decimal) | C70: ='محاسبه-ساده'!C52 -> 0 | F70: Paid out of gross; insurer receives the remainder.
A71: P10 | B71: Net Premium to Insurer (﷼) | E71: =ROUND(E69*(1-C70),0) -> 150436480995 | F71: Gross × (1 − brokerage).
A72: P11 | B72: Insurance Tax / Stamp Duty (decimal) | C72: ='محاسبه-ساده'!C53 -> 0.1 | F72: Iran premium tax (currently 9%).
A73: P12 | B73: TOTAL PREMIUM PAYABLE BY INSURED (﷼) | E73: =ROUND(E69*(1+C72),0) -> 165480129095 | F73: Gross × (1 + tax). Convert to local currency at current FX.
A74: K VALIDATION CHECKS
A75: V1 | B75: Sub-group resolved to a real rate | E75: =IF(AND(ISNUMBER(E10),ISNUMBER(E11),E11>0),"✓ rate found","⚠ check sub-group C5") -> ✓ rate found
A76: V2 | B76: Effective rate ≥ minimum floor | E76: =IF($I$86="M","✓ OK (blue table — basic rate is the minimum)",IF(E13>=E11,"✓ OK","⚠ below floor")) -> ✓ OK
A77: V3 | B77: Duration within 1–120 months | E77: =IF(AND(C6>=1,C6<=120),"✓ OK","⚠ duration 1-120") -> ✓ OK
A78: V4 | B78: EQ exclusion zeroes EQ loading | E78: =IF(OR(C20<>"Yes",E21=0),"✓ OK","⚠ EQ loading not zeroed") -> ✓ OK
A79: V5 | B79: TPL inputs valid | E79: =IF($I$44="No","✓ OK (TPL excluded)",IF(AND(ISNUMBER(E47),E47>0),"✓ OK","⚠ check TPL category/surroundings")) -> ✓ OK
A80: V6 | B80: Sum Insured entered | E80: =IF(C62>0,"✓ OK","⚠ enter Sum Insured P1") -> ✓ OK
A85: L INDIVIDUAL MACHINES (Blue Tables — Swiss Re Rating Guide 2.5)
A86: M1 | B86: Rating Basis (Entire Project / Individual Machines) | C86: ='محاسبه-ساده'!C9 -> کل پروژه (Entire Project) | F86: Set on محاسبه-ساده!C52. Default = Entire Project, which leaves every downstream formula behaving exactly as before. | H86: Mode flag: M = individual machine (blue), P = entire project (white). Drives the switch in E12/E13/E14/D58. | I86: =IF(ISNUMBER(SEARCH("Individual Machines",$C$86)),"M","P") -> P
A87: M2 | B87: Machine (blue table) | C87: ='محاسبه-ساده'!C12
A88: M3 | B88: Erection months (machine) | C88: ='محاسبه-ساده'!C14 -> 3
A89: M4 | B89: Testing months (machine) | C89: ='محاسبه-ساده'!C15 -> 1
A90: M5 | B90: Nature-perils loading for individual machine? | C90: ='محاسبه-ساده'!C56 -> No
A91: M6 | B91: Blue-table Erection Rate (‰) | E91: =IF($I$86<>"M",0,IFERROR(INDEX('Rate-IndividualMachines'!$L$2:$L$109,MATCH($C$87,'Rate-IndividualMachines'!$K$2:$K$109,0))+MAX(0,MIN($C$88,9)-3)*INDEX('Rate-IndividualMachines'!$M$2:$M$109,MATCH($C$87,'Rate-IndividualMachines'!$K$2:$K$109,0))+MAX(0,MIN($C$89,3)-1)*INDEX('Rate-IndividualMachines'!$N$2:$N$109,MATCH($C$87,'Rate-IndividualMachines'!$K$2:$K$109,0)),0)) -> 0 | F91: Basic Rate + MAX(0,MIN(erect,9)-3)×Add.Erect + MAX(0,MIN(test,3)-1)×Add.Test. Source: Swiss Re 2.5 / 10.1 — basic rate covers 3 months erection + 1 month testing; erection extendable to 9, testing to 3.
A92: M7 | B92: Blue-table Reference Rate (‰) | E92: =IF($I$86<>"M",0,IFERROR(INDEX('Rate-IndividualMachines'!$O$2:$O$109,MATCH($C$87,'Rate-IndividualMachines'!$K$2:$K$109,0)),0)) -> 0 | F92: Reference Rate from the blue table (col F), used by the Manufacturer-Risk / maintenance loadings when in machine mode.
A93: V7 | B93: Individual-machine periods within Swiss Re caps | E93: =IF($I$86<>"M","✓ n/a",IF(AND($C$88>=0,$C$88<=9,$C$89>=0,$C$89<=3),"✓ OK","⚠ machine period exceeds Swiss Re caps (erect ≤9, test ≤3)")) -> ✓ n/a

Sheet Rate-SubGroup
A1: Project Sub-Group | B1: Code1 | C1: Code2 | D1: Code3 | E1: Code4 | F1: Hot_test | G1: Ref_Rate | H1: Min. Rate | I1: Gen. Excess (c-units) All Events | J1: AoG / Test / Maint. Excess (c-units) | K1: Gen. Excess (﷼) | L1: AoG/Test/Maint Excess (﷼) | N1: _groups
A2: 01.1.1 Boilerhouse installations — natural circulation, ≤250 t/h (boiler + superheaters, fans, water treatment, feed pumps) | B2: 1.55 | C2: 0.1 | D2: 0.075 | E2: 0.05 | F2: 0.45 | G2: 3 | H2: 3.55 | I2: 5000 | J2: 150/MW (min 10,000) | K2: =I2*'Currency-Conversion'!$C$10 -> 1.5319397e+10 | L2: =J2&" — تبدیل خودکار به ریال ممکن نشد (نرخ به‌ازای واحد ظرفیت است، نه عدد ساده). برای تبدیل دستی، اعداد را در ضریب "&TEXT('Currency-Conversion'!$C$10,"#,##0")&" ضرب کنید." -> 150/MW (min 10,000) — تبدیل خودکار به ریال ممکن نشد (نرخ به‌ازای واحد ظرفیت است، نه عدد ساده). برای تبدیل دستی، اعداد را در ضریب 3,063,879 ضرب کنید. | N2: 01 — Public Utilities
A3: 01.1.1 Boilerhouse installations comprising boiler with all auxiliaries (superheaters, fans, feed pumps, water treatment) - natural circulat | B3: 1.6 | C3: 0.1 | D3: 0.075 | E3: 0.05 | F3: 0.45 | G3: 3.5 | H3: 3.75 | I3: 5000 | J3: 150/MW | K3: =I3*'Currency-Conversion'!$C$10 -> 1.5319397e+10 | L3: =J3&" — تبدیل خودکار به ریال ممکن نشد (نرخ به‌ازای واحد ظرفیت است، نه عدد ساده). برای تبدیل دستی، اعداد را در ضریب "&TEXT('Currency-Conversion'!$C$10,"#,##0")&" ضرب کنید." -> 150/MW — تبدیل خودکار به ریال ممکن نشد (نرخ به‌ازای واحد ظرفیت است، نه عدد ساده). برای تبدیل دستی، اعداد را در ضریب 3,063,879 ضرب کنید. | N3: 02 — Industrial Plant Utilities
A4: 01.1.2 Turbogenerating sets — turbine, generator, cooling system, governor, directly connected auxiliaries — up to 50 MW | B4: 1.65 | C4: 0.1 | D4: 0.05 | E4: 0.025 | F4: 1 | G4: 10 | H4: 4.4 | I4: 5000 | J4: 25000 | K4: =I4*'Currency-Conversion'!$C$10 -> 1.5319397e+10 | L4: =J4*'Currency-Conversion'!$C$10 -> 76596986250 | N4: 03 — Mining Industry
A5: 01.1.2 Turbogenerating sets (turbine, generator, cooling system, governor, directly connected auxiliaries) — 50 to 125 MW | B5: 1.75 | C5: 0.1 | D5: 0.05 | E5: 0.025 | F5: 1.1 | G5: 10 | H5: 4.75 | I5: 5000 | J5: 250/MW (min 25,000) | K5: =I5*'Currency-Conversion'!$C$10 -> 1.5319397e+10 | L5: =J5&" — تبدیل خودکار به ریال ممکن نشد (نرخ به‌ازای واحد ظرفیت است، نه عدد ساده). برای تبدیل دستی، اعداد را در ضریب "&TEXT('Currency-Conversion'!$C$10,"#,##0")&" ضرب کنید." -> 250/MW (min 25,000) — تبدیل خودکار به ریال ممکن نشد (نرخ به‌ازای واحد ظرفیت است، نه عدد ساده). برای تبدیل دستی، اعداد را در ضریب 3,063,879 ضرب کنید. | N5: 04 — Chemical Industry
A6: 01.1.2 Turbogenerating sets (turbine, generator, cooling system, governor, directly connected auxiliaries) — 125 to 250 MW | B6: 1.75 | C6: 0.1 | D6: 0.05 | E6: 0.025 | F6: 1.3 | G6: 12 | H6: 4.95 | I6: 5000 | J6: 250/MW | K6: =I6*'Currency-Conversion'!$C$10 -> 1.5319397e+10 | L6: =J6&" — تبدیل خودکار به ریال ممکن نشد (نرخ به‌ازای واحد ظرفیت است، نه عدد ساده). برای تبدیل دستی، اعداد را در ضریب "&TEXT('Currency-Conversion'!$C$10,"#,##0")&" ضرب کنید." -> 250/MW — تبدیل خودکار به ریال ممکن نشد (نرخ به‌ازای واحد ظرفیت است، نه عدد ساده). برای تبدیل دستی، اعداد را در ضریب 3,063,879 ضرب کنید. | N6: 05 — Metal Industry
A7: 01.1.2 Turbogenerating sets (turbine, generator, cooling system, governor, directly connected auxiliaries) — 250 to 450 MW | B7: 1.75 | C7: 0.1 | D7: 0.05 | E7: 0.025 | F7: 1.55 | G7: 14 | H7: 5.4 | I7: 7500 | J7: 250/MW | K7: =I7*'Currency-Conversion'!$C$10 -> 2.2979096e+10 | L7: =J7&" — تبدیل خودکار به ریال ممکن نشد (نرخ به‌ازای واحد ظرفیت است، نه عدد ساده). برای تبدیل دستی، اعداد را در ضریب "&TEXT('Currency-Conversion'!$C$10,"#,##0")&" ضرب کنید." -> 250/MW — تبدیل خودکار به ریال ممکن نشد (نرخ به‌ازای واحد ظرفیت است، نه عدد ساده). برای تبدیل دستی، اعداد را در ضریب 3,063,879 ضرب کنید. | N7: 06 — Building Industry
A8: 01.1.3 Water-systems cycle comprising condenser, feed heater piping, pumps etc. | B8: 1.55 | C8: 0.05 | D8: 0.05 | E8: 0.025 | F8: 0.55 | G8: 3 | H8: 3.1 | I8: 2500 | J8: 5000 | K8: =I8*'Currency-Conversion'!$C$10 -> 7.6596986e+09 | L8: =J8*'Currency-Conversion'!$C$10 -> 1.5319397e+10 | N8: 07 — Timber & Wood
A9: 01.1.4 Electric equipment, control and measuring installations incl. station transformers | B9: 1.55 | C9: 0.075 | D9: 0.075 | E9: 0.05 | F9: 0.65 | G9: 3.5 | H9: 3.3 | I9: 2500 | J9: 5000 | K9: =I9*'Currency-Conversion'!$C$10 -> 7.6596986e+09 | L9: =J9*'Currency-Conversion'!$C$10 -> 1.5319397e+10 | N9: 08 — Pulp & Paper
A10: 01.1.5 Balance of plant comprising: ash-handling, off-site tanks | B10: 1.55 | C10: 0.05 | D10: 0.075 | E10: 0.025 | F10: 0.55 | G10: 2 | H10: 3.1 | I10: 2500 | J10: 5000 | K10: =I10*'Currency-Conversion'!$C$10 -> 7.6596986e+09 | L10: =J10*'Currency-Conversion'!$C$10 -> 1.5319397e+10 | N10: 09 — Printing & Packing
A11: 01.2.1 Gas turbine power plants — Gasturbo generating sets (turbine, compressor, generator, starting device, all auxiliaries) — up to 10 MW | B11: 1.65 | C11: 0.15 | D11: 0.075 | E11: 0.05 | F11: 1.1 | G11: 10 | H11: 4.2 | I11: 5000 | J11: 10000 | K11: =I11*'Currency-Conversion'!$C$10 -> 1.5319397e+10 | L11: =J11*'Currency-Conversion'!$C$10 -> 3.0638794e+10 | N11: 10 — Leather Industry
A12: 01.2.1 Gasturbo generating sets (turbine, compressor, generator, starting device, all auxiliaries connected to foundation block) — 10 to 20 | B12: 1.75 | C12: 0.15 | D12: 0.075 | E12: 0.075 | F12: 1.2 | G12: 10 | H12: 4.7 | I12: 5000 | J12: 750/MW (min 10,000) | K12: =I12*'Currency-Conversion'!$C$10 -> 1.5319397e+10 | L12: =J12&" — تبدیل خودکار به ریال ممکن نشد (نرخ به‌ازای واحد ظرفیت است، نه عدد ساده). برای تبدیل دستی، اعداد را در ضریب "&TEXT('Currency-Conversion'!$C$10,"#,##0")&" ضرب کنید." -> 750/MW (min 10,000) — تبدیل خودکار به ریال ممکن نشد (نرخ به‌ازای واحد ظرفیت است، نه عدد ساده). برای تبدیل دستی، اعداد را در ضریب 3,063,879 ضرب کنید. | N12: 11 — Textile Industry
A13: 01.2.1 Gasturbo generating sets (turbine, compressor, generator, starting device, all auxiliaries connected to foundation block) — 20 to 40 | B13: 1.9 | C13: 0.15 | D13: 0.075 | E13: 0.075 | F13: 1.45 | G13: 12 | H13: 5.5 | I13: 5000 | J13: 750/MW | K13: =I13*'Currency-Conversion'!$C$10 -> 1.5319397e+10 | L13: =J13&" — تبدیل خودکار به ریال ممکن نشد (نرخ به‌ازای واحد ظرفیت است، نه عدد ساده). برای تبدیل دستی، اعداد را در ضریب "&TEXT('Currency-Conversion'!$C$10,"#,##0")&" ضرب کنید." -> 750/MW — تبدیل خودکار به ریال ممکن نشد (نرخ به‌ازای واحد ظرفیت است، نه عدد ساده). برای تبدیل دستی، اعداد را در ضریب 3,063,879 ضرب کنید. | N13: 12 — Plastic & Rubber
A14: 01.2.2 Electrical equipment control/measuring: air inlet/outlet, filters, piping, pumps incl. station transformers | B14: 1.55 | C14: 0.075 | D14: 0.075 | E14: 0.075 | F14: 0.65 | G14: 3 | H14: 3.3 | I14: 1000 | J14: 2000 | K14: =I14*'Currency-Conversion'!$C$10 -> 3.0638794e+09 | L14: =J14*'Currency-Conversion'!$C$10 -> 6.1277589e+09 | N14: 13 — Food (Vegetable)
A15: 01.2.3 Balance of plant off-site installations: tanks, gas receiving and/or pressure reducing plant etc. | B15: 1.55 | C15: 0.075 | D15: 0.075 | E15: 0.075 | F15: 0.55 | G15: 2.5 | H15: 3.1 | I15: 1000 | J15: 2000 | K15: =I15*'Currency-Conversion'!$C$10 -> 3.0638794e+09 | L15: =J15*'Currency-Conversion'!$C$10 -> 6.1277589e+09 | N15: 14 — Food (Animal)
A16: 01.3.1 Diesel generator sets — diesel engine, starting device, generator and all auxiliaries attached — engines with speed above 500 rpm | B16: 2.05 | C16: 0.15 | D16: 0.1 | E16: 0.1 | F16: 1.1 | G16: 12 | H16: 4.95 | I16: 2000 | J16: 1000/MW (min 5,000) | K16: =I16*'Currency-Conversion'!$C$10 -> 6.1277589e+09 | L16: =J16&" — تبدیل خودکار به ریال ممکن نشد (نرخ به‌ازای واحد ظرفیت است، نه عدد ساده). برای تبدیل دستی، اعداد را در ضریب "&TEXT('Currency-Conversion'!$C$10,"#,##0")&" ضرب کنید." -> 1000/MW (min 5,000) — تبدیل خودکار به ریال ممکن نشد (نرخ به‌ازای واحد ظرفیت است، نه عدد ساده). برای تبدیل دستی، اعداد را در ضریب 3,063,879 ضرب کنید. | N16: 15 — Food Refrigeration
A17: 01.3.1 Diesel Generator sets (diesel engine, starting device, generator, all attached auxiliaries) - engines with speed above 500 rpm — engi | B17: 1.75 | C17: 0.1 | D17: 0.1 | E17: 0.1 | F17: 0.9 | G17: 10 | H17: 4.2 | I17: 2000 | J17: 1000/MW | K17: =I17*'Currency-Conversion'!$C$10 -> 6.1277589e+09 | L17: =J17&" — تبدیل خودکار به ریال ممکن نشد (نرخ به‌ازای واحد ظرفیت است، نه عدد ساده). برای تبدیل دستی، اعداد را در ضریب "&TEXT('Currency-Conversion'!$C$10,"#,##0")&" ضرب کنید." -> 1000/MW — تبدیل خودکار به ریال ممکن نشد (نرخ به‌ازای واحد ظرفیت است، نه عدد ساده). برای تبدیل دستی، اعداد را در ضریب 3,063,879 ضرب کنید. | N17: 16 — Transport & Warehouses
A18: 01.3.2 Electrical equipment control/measuring; air inlet/outlet, filters, piping, pumps | B18: 1.65 | C18: 0.1 | D18: 0.075 | E18: 0.075 | F18: 0.65 | G18: 3 | H18: 3.4 | I18: 1000 | J18: 2000 | K18: =I18*'Currency-Conversion'!$C$10 -> 3.0638794e+09 | L18: =J18*'Currency-Conversion'!$C$10 -> 6.1277589e+09 | N18: 17 — Public Services
A19: 01.3.3 Balance of plant comprising off-site installations, tanks, etc. | B19: 1.5 | C19: 0.1 | D19: 0.075 | E19: 0.075 | F19: 0.55 | G19: 2.5 | H19: 3 | I19: 1000 | J19: 2000 | K19: =I19*'Currency-Conversion'!$C$10 -> 3.0638794e+09 | L19: =J19*'Currency-Conversion'!$C$10 -> 6.1277589e+09 | N19: 18 — Hospitals & Hotels
A20: 01.4.1 Turbinehouse installations - Pelton turbine, up to 100 MW | B20: 1.55 | C20: 0.075 | D20: 0.05 | E20: 0.025 | F20: 0.65 | G20: 3 | H20: 2.95 | I20: 2500 | J20: 10000 | K20: =I20*'Currency-Conversion'!$C$10 -> 7.6596986e+09 | L20: =J20*'Currency-Conversion'!$C$10 -> 3.0638794e+10 | N20: 19 — Farming & Agriculture
A21: 01.4.1 Turbinehouse installations - Pelton turbine — Pelton, 100 to 200 MW | B21: 1.55 | C21: 0.075 | D21: 0.05 | E21: 0.025 | F21: 0.65 | G21: 4 | H21: 3.3 | I21: 2500 | J21: 100/MW | K21: =I21*'Currency-Conversion'!$C$10 -> 7.6596986e+09 | L21: =J21&" — تبدیل خودکار به ریال ممکن نشد (نرخ به‌ازای واحد ظرفیت است، نه عدد ساده). برای تبدیل دستی، اعداد را در ضریب "&TEXT('Currency-Conversion'!$C$10,"#,##0")&" ضرب کنید." -> 100/MW — تبدیل خودکار به ریال ممکن نشد (نرخ به‌ازای واحد ظرفیت است، نه عدد ساده). برای تبدیل دستی، اعداد را در ضریب 3,063,879 ضرب کنید.
A22: 01.4.1 Turbinehouse installations - Pelton turbine — Francis turbine, up to 100 MW | B22: 1.7 | C22: 0.075 | D22: 0.05 | E22: 0.025 | F22: 0.8 | G22: 3 | H22: 3.3 | I22: 2500 | J22: 10000 | K22: =I22*'Currency-Conversion'!$C$10 -> 7.6596986e+09 | L22: =J22*'Currency-Conversion'!$C$10 -> 3.0638794e+10
A23: 01.4.1 Turbinehouse installations - Pelton turbine — Francis, 100 to 200 MW | B23: 1.8 | C23: 0.075 | D23: 0.05 | E23: 0.025 | F23: 0.8 | G23: 4 | H23: 3.6 | I23: 2500 | J23: 100/MW | K23: =I23*'Currency-Conversion'!$C$10 -> 7.6596986e+09 | L23: =J23&" — تبدیل خودکار به ریال ممکن نشد (نرخ به‌ازای واحد ظرفیت است، نه عدد ساده). برای تبدیل دستی، اعداد را در ضریب "&TEXT('Currency-Conversion'!$C$10,"#,##0")&" ضرب کنید." -> 100/MW — تبدیل خودکار به ریال ممکن نشد (نرخ به‌ازای واحد ظرفیت است، نه عدد ساده). برای تبدیل دستی، اعداد را در ضریب 3,063,879 ضرب کنید.
A24: 01.4.1 Turbinehouse installations - Pelton turbine — Kaplan turbine, up to 100 MW | B24: 1.7 | C24: 0.075 | D24: 0.05 | E24: 0.025 | F24: 0.8 | G24: 4 | H24: 3.3 | I24: 2500 | J24: 10000 | K24: =I24*'Currency-Conversion'!$C$10 -> 7.6596986e+09 | L24: =J24*'Currency-Conversion'!$C$10 -> 3.0638794e+10
A25: 01.4.1 Turbinehouse installations - Pelton turbine — Kaplan, 100 to 200 MW | B25: 1.8 | C25: 0.075 | D25: 0.05 | E25: 0.025 | F25: 0.8 | G25: 4 | H25: 3.65 | I25: 2500 | J25: 100/MW | K25: =I25*'Currency-Conversion'!$C$10 -> 7.6596986e+09 | L25: =J25&" — تبدیل خودکار به ریال ممکن نشد (نرخ به‌ازای واحد ظرفیت است، نه عدد ساده). برای تبدیل دستی، اعداد را در ضریب "&TEXT('Currency-Conversion'!$C$10,"#,##0")&" ضرب کنید." -> 100/MW — تبدیل خودکار به ریال ممکن نشد (نرخ به‌ازای واحد ظرفیت است، نه عدد ساده). برای تبدیل دستی، اعداد را در ضریب 3,063,879 ضرب کنید.
A26: 01.4.1 Turbinehouse installations - Pelton turbine — Other types (tubular/axial flow reaction turbines), up to 25 MW | B26: 1.6 | C26: 0.075 | D26: 0.05 | E26: 0.025 | F26: 0.9 | G26: 4 | H26: 3.3 | I26: 2500 | J26: 5000 | K26: =I26*'Currency-Conversion'!$C$10 -> 7.6596986e+09 | L26: =J26*'Currency-Conversion'!$C$10 -> 1.5319397e+10
A27: 01.4.1 Turbinehouse installations - Pelton turbine — Other types, 25 to 50 MW | B27: 1.7 | C27: 0.075 | D27: 0.05 | E27: 0.025 | F27: 0.9 | G27: 4 | H27: 3.75 | I27: 2500 | J27: 100/MW | K27: =I27*'Currency-Conversion'!$C$10 -> 7.6596986e+09 | L27: =J27&" — تبدیل خودکار به ریال ممکن نشد (نرخ به‌ازای واحد ظرفیت است، نه عدد ساده). برای تبدیل دستی، اعداد را در ضریب "&TEXT('Currency-Conversion'!$C$10,"#,##0")&" ضرب کنید." -> 100/MW — تبدیل خودکار به ریال ممکن نشد (نرخ به‌ازای واحد ظرفیت است، نه عدد ساده). برای تبدیل دستی، اعداد را در ضریب 3,063,879 ضرب کنید.
A28: 01.4.2 Pumping house installations - Horizontal pumping sets, up to 25 MW | B28: 1.75 | C28: 0.1 | D28: 0.075 | E28: 0.05 | F28: 0.8 | G28: 5 | H28: 3.6 | I28: 2500 | J28: 5000 | K28: =I28*'Currency-Conversion'!$C$10 -> 7.6596986e+09 | L28: =J28*'Currency-Conversion'!$C$10 -> 1.5319397e+10
A29: 01.4.2 Pumping house installations - Horizontal pumping sets — Horizontal, 25 to 50 MW | B29: 1.75 | C29: 0.1 | D29: 0.075 | E29: 0.05 | F29: 0.8 | G29: 5 | H29: 4.1 | I29: 2500 | J29: 10000 | K29: =I29*'Currency-Conversion'!$C$10 -> 7.6596986e+09 | L29: =J29*'Currency-Conversion'!$C$10 -> 3.0638794e+10
A30: 01.4.2 Pumping house installations - Horizontal pumping sets — Vertical pumping sets, up to 25 MW | B30: 1.65 | C30: 0.1 | D30: 0.075 | E30: 0.05 | F30: 0.9 | G30: 5 | H30: 3.85 | I30: 2500 | J30: 5000 | K30: =I30*'Currency-Conversion'!$C$10 -> 7.6596986e+09 | L30: =J30*'Currency-Conversion'!$C$10 -> 1.5319397e+10
A31: 01.4.2 Pumping house installations - Horizontal pumping sets — Vertical, 25 to 50 MW | B31: 1.75 | C31: 0.1 | D31: 0.075 | E31: 0.05 | F31: 0.9 | G31: 5 | H31: 4.25 | I31: 2500 | J31: 10000 | K31: =I31*'Currency-Conversion'!$C$10 -> 7.6596986e+09 | L31: =J31*'Currency-Conversion'!$C$10 -> 3.0638794e+10
A32: 01.4.3 Electrical equipment and measuring installations, station transformers, pressurised air control systems, etc. | B32: 1.5 | C32: 0.075 | D32: 0.05 | E32: 0.025 | F32: 0.55 | G32: 3.5 | H32: 3.3 | I32: 2500 | J32: 5000 | K32: =I32*'Currency-Conversion'!$C$10 -> 7.6596986e+09 | L32: =J32*'Currency-Conversion'!$C$10 -> 1.5319397e+10
A33: 01.4.4 Water intake and off-site installations: penstocks, gates, trash racks, weir installations and the like | B33: 1.5 | C33: 0.075 | D33: 0.05 | E33: 0.025 | F33: 0.65 | G33: 3 | H33: 3.3 | I33: 2500 | J33: 5000 | K33: =I33*'Currency-Conversion'!$C$10 -> 7.6596986e+09 | L33: =J33*'Currency-Conversion'!$C$10 -> 1.5319397e+10
A34: 01.5.1 Transformer stations — power transformer, phase compensators, cooling control, capacitors, rectifier banks — 30 to 150 MVA | B34: 1.7 | C34: 0.075 | D34: 0.05 | E34: 0.05 | F34: 0.75 | G34: 5 | H34: 3.15 | I34: 2500 | J34: 5000 | K34: =I34*'Currency-Conversion'!$C$10 -> 7.6596986e+09 | L34: =J34*'Currency-Conversion'!$C$10 -> 1.5319397e+10
A35: 01.5.1 Transformer stations — power transformer, phase compensators, cooling control, capacitors, rectifier banks — 150 to 300 MVA | B35: 1.7 | C35: 0.075 | D35: 0.05 | E35: 0.05 | F35: 0.9 | G35: 6 | H35: 3.4 | I35: 2500 | J35: 5000 | K35: =I35*'Currency-Conversion'!$C$10 -> 7.6596986e+09 | L35: =J35*'Currency-Conversion'!$C$10 -> 1.5319397e+10
A36: 01.5.1 Transformer stations — power transformer, phase compensators, cooling control, capacitors, rectifier banks — above 300 MVA | B36: 1.7 | C36: 0.075 | D36: 0.05 | E36: 0.05 | F36: 1.1 | G36: 7 | H36: 3.65 | I36: 5000 | J36: 10000 | K36: =I36*'Currency-Conversion'!$C$10 -> 1.5319397e+10 | L36: =J36*'Currency-Conversion'!$C$10 -> 3.0638794e+10
A37: 01.5.1 Transformer Stations (power transformer, phase compensators, cooling/control/protection auxiliaries, capacitors, rectifier banks) - P | B37: 1.6 | C37: 0.075 | D37: 0.05 | E37: 0.05 | F37: 0.65 | G37: 5 | H37: 2.9 | I37: 1000 | J37: 2500 | K37: =I37*'Currency-Conversion'!$C$10 -> 3.0638794e+09 | L37: =J37*'Currency-Conversion'!$C$10 -> 7.6596986e+09
A38: 01.5.2 Switchgear installations (circuit breakers, control/protection equipment, line feeders) up to 60 kV | B38: 1.55 | C38: 0.075 | D38: 0.05 | E38: 0.05 | F38: 0.55 | G38: 2 | H38: 2.7 | I38: 1000 | J38: 2500 | K38: =I38*'Currency-Conversion'!$C$10 -> 3.0638794e+09 | L38: =J38*'Currency-Conversion'!$C$10 -> 7.6596986e+09
A39: 01.5.2 Switchgear installations (circuit breakers, control/protection equipment, line feeders) — 60 kV to 500 kV | B39: 1.7 | C39: 0.075 | D39: 0.05 | E39: 0.05 | F39: 0.55 | G39: 2.5 | H39: 2.85 | I39: 1000 | J39: 2500 | K39: =I39*'Currency-Conversion'!$C$10 -> 3.0638794e+09 | L39: =J39*'Currency-Conversion'!$C$10 -> 7.6596986e+09
... A152: 19.3 Poultry farms (rearing hatcheries) and similar installations | B152: 1.55 | C152: 0.125 | D152: 0.075 | E152: 0.05 | F152: 0.55 | G152: 3 | H152: 3.3 | I152: 1000 | J152: 2500 | K152: =I152*'Currency-Conversion'!$C$10 -> 3.0638794e+09 | L152: =J152*'Currency-Conversion'!$C$10 -> 7.6596986e+09
K153: EAR 19.3 · p.184 | L153: 19.3 Poultry farms (rearing hatcheries) and similar installations | Section value %=NS | Min.Rate=3.30 | Erection: 1st month=1.55, 2-12=0.125, 13-24=0.075, 25-=0.05 | Testing: 1st month=0.55, fol.=0.425 | Ref.Rate=3 | XS general=1,000, AOG/Test/Maint=2,500

Sheet Rate-Clauses
A1: Clause No. | B1: Clause / Endorsement Name | C1: Type | D1: Rate Impact | E1: Basis of Impact | F1: EAR Ref. (Page) | G1: Description & Notes | I1: _clause_list
A2: 1.21.01 | B2: Expediting Costs | C2: Extension | D2: 5-10% of works rate | E2: On total SI | F2: p.35/109 | G2: Covers extra charges for overtime, night-work, public holidays, express freight (excl. airfreight). Limit per event ≈ 20% of expected average claim. | I2: Expediting Costs
A3: 1.21.02 | B3: Cross Liability | C3: Extension | D3: 35% of total TPL prem | E3: On TPL prem | F3: p.42/47 | G3: Allows sub-contractors to claim against each other under same policy. Min 15% if no plant/storage exposure covered separately. | I3: Cross Liability
A4: 1.21.03 | B4: Riot and Strike | C4: Extension | D4: 50% of fire R&S rate | E4: Erection period | F4: p.42/50 | G4: 100% during commissioning/testing period (confirmed, EAR Rating Guide Sec.9 item 6.4). Erection-period % ("50%" previously shown here) could NOT be verified against the uploaded source after two independent searches — flagged as insufficient evidence; use with caution / confirm with reinsurer guideline before relying on it. | I4: Riot and Strike
A5: 1.21.04 | B5: Visits Maintenance | C5: Extension | D5: 5-7.5% of Ref.Rate | E5: Per month | F5: p.41/52 | G5: 5% light industries; 7.5% power plants/chemical/heavy. Cover restricted to damage occurring during contractor site visits. | I5: Visits Maintenance
A6: 1.21.05 | B6: Extended Maintenance | C6: Extension | D6: 7.5-12.5% of Ref.Rate | E6: Per month | F6: p.41/53 | G6: 7.5% light; 12.5% heavy. Full maintenance cover but period usually ≤12 months; loading required for extensions >12 months. | I6: Extended Maintenance
A7: 1.21.06 | B7: [Reserved / Not printed] | C7: N/A | D7: — | E7: — | F7: p.45 | G7: Not printed in the guide copy available. | I7: Contractors' Plant & Equipment
A8: 1.21.07 | B8: [Reserved / Not printed] | C8: N/A | D8: — | E8: — | F8: p.45 | G8: Not printed in the guide copy available. | I8: Airfreight Costs
A9: 1.21.08 | B9: Contractors' Plant & Equipment | C9: Extension | D9: 8-10‰ p.a. (plant) 6-7‰ p.a. (equipment) | E9: Annual rate on SI | F9: p.36/54-55 | G9: Covers mobile/stationary erection plant and scaffolding/hutments. Applies only to smaller, light-type plant. Min excess: 1,000 c-units. If period <1 yr: monthly rate = 1/10 annual rate. | I9: Reassessment Clause — Steam & Gas Turbine Generator Sets
A10: 1.21.09 | B10: Airfreight Costs | C10: Extension | D10: 5-20‰ | E10: On aggregate limit | F10: p.35/56 | G10: 5‰ for distances <2,000 miles; proportional increase to 20‰ for longer. Max aggregate limit ≈ 1% of SI. | I10: Special Conditions — Hydrocarbon Processing Industry
A11: 1.21.10 | B11: [Reserved / Not printed] | C11: N/A | D11: — | E11: — | F11: p.45 | G11: Not printed in available copy. | I11: Faulty Design (Defective Design)
A12: 1.21.11 | B12: [Reserved / Not printed] | C12: N/A | D12: — | E12: — | F12: p.45 | G12: Not printed in available copy. | I12: Existing Property
... A27: — | B27: Contract Works Time Schedule | C27: Special Condition | D27: Condition only | E27: N/A | F27: p.71 | G27: Requires insured to maintain and submit project time schedule. Material deviations may require re-rating. | I27: Third Party Liability (TPL)
A28: — | B28: Debris, Silt, Erosion, Landslip | C28: Extension/Restriction | D28: Per underwriter | E28: On affected SI | F28: p.72 | G28: Adds or restricts cover for debris removal/silt/erosion damage. Terms depend on project type and location.
A29: 6.1.1 | B29: Manufacturer's Risk — Defective Material/Workmanship | C29: Extension | D29: 5/7.5/10% of Ref.Rate | E29: Per test/maint month | F29: Sec 6.1.1 | G29: Additional rate calculated as % of Ref.Rate per testing/maintenance month. Defective part itself always excluded.
A30: 6.1.2 | B30: Manufacturer's Risk — Defective Design | C30: Extension | D30: 5/7.5/10% of Ref.Rate | E30: Per test/maint month | F30: Sec 6.1.2 | G30: Same rate scale as 6.1.1. Only additional repair costs covered (not cost of rectifying the design defect itself).
A31: Table 20 | B31: Third Party Liability (TPL) | C31: Standard Section | D31: 0.20 to 0.80‰ | E31: On contract value | F31: p.186-193 | G31: Rate depends on Technical Risk Category (I/II/III) and Surroundings Category (a/b/c). See Rate-TPL sheet for full rate table.

Sheet Rate-IndividualMachines
A1: EAR Rating — Individual Machines (Blue Tables) | Basic Rate = for up to 3 months erection + 1 month testing | K1: Machine (picker label) | L1: Basic Rate ‰ | M1: Add. Erect ‰/mo | N1: Add. Test ‰/mo | O1: Ref. Rate ‰
A2: EAR Code | B2: Description | C2: Basic Rate (≤3m erection +1m testing) | D2: Add. Rate Erection (per month) | E2: Add. Rate Testing (per month) | F2: Ref. Rate | G2: General Excess (c-units) | H2: AoG/Test/ Maint. XS (c-units) | I2: Gen. Excess (﷼) | J2: Maint. Excess (﷼) | K2: 02.0.1 — Boiler feed pumps, incl. drive — turbine driven | L2: 4 | M2: 0.25 | N2: 1 | O2: 12
A3: 01.0 | B3: PUBLIC UTILITIES — Individual machines: use min rate from white Rating Table 01 (Public Utilities) or white Table 16 (Transport) | K3: 02.0.1 — Boiler feed pumps, incl. drive — motor driven | L3: 3.5 | M3: 0.2 | N3: 0.8 | O3: 8
A4: 02.0 | B4: UTILITIES IN INDUSTRIAL PLANTS — Individual Machines | K4: 02.0.2 — Heat exchangers, condensers | L4: 2.5 | M4: 0.1 | N4: 0.3 | O4: 4
A5: 02.0.1 | B5: Boiler feed pumps, incl. drive — turbine driven | C5: 4 | D5: 0.25 | E5: 1 | F5: 12 | G5: 2500 | H5: 10000 | I5: =G5*'Currency-Conversion'!$C$10 -> 7.6596986e+09 | J5: =H5*'Currency-Conversion'!$C$10 -> 3.0638794e+10 | K5: 02.0.3 — Electrical motors — asynchronous squirrel cage, up to 1 MW | L5: 2.5 | M5: 0.1 | N5: 0.6 | O5: 5
A6: 02.0.1 | B6: Boiler feed pumps, incl. drive — motor driven | C6: 3.5 | D6: 0.2 | E6: 0.8 | F6: 8 | G6: 1250 | H6: 2500 | I6: =G6*'Currency-Conversion'!$C$10 -> 3.8298493e+09 | J6: =H6*'Currency-Conversion'!$C$10 -> 7.6596986e+09 | K6: 02.0.3 — Electrical motors — asynchronous slip ring, up to 25 MW | L6: 2.7 | M6: 0.1 | N6: 0.8 | O6: 6
A7: 02.0.2 | B7: Heat exchangers, condensers | C7: 2.5 | D7: 0.1 | E7: 0.3 | F7: 4 | G7: 500 | H7: 1000 | I7: =G7*'Currency-Conversion'!$C$10 -> 1.5319397e+09 | J7: =H7*'Currency-Conversion'!$C$10 -> 3.0638794e+09 | K7: 02.0.3 — Electrical motors — synchronous, up to 25 MW | L7: 3 | M7: 0.15 | N7: 0.9 | O7: 6
A8: 02.0.3 | B8: Electrical motors — asynchronous squirrel cage, up to 1 MW | C8: 2.5 | D8: 0.1 | E8: 0.6 | F8: 5 | G8: 500 | H8: 1000 | I8: =G8*'Currency-Conversion'!$C$10 -> 1.5319397e+09 | J8: =H8*'Currency-Conversion'!$C$10 -> 3.0638794e+09 | K8: 02.0.3 — Electrical motors — direct current, up to 10 MW | L8: 3.5 | M8: 0.15 | N8: 1 | O8: 8
A9: 02.0.3 | B9: Electrical motors — asynchronous slip ring, up to 25 MW | C9: 2.7 | D9: 0.1 | E9: 0.8 | F9: 6 | G9: 500 | H9: 1000 | I9: =G9*'Currency-Conversion'!$C$10 -> 1.5319397e+09 | J9: =H9*'Currency-Conversion'!$C$10 -> 3.0638794e+09 | K9: 02.0.3 — Electrical motors — special design (e.g. ring motor), up to 25 MW | L9: 4 | M9: 0.2 | N9: 1 | O9: 8
A10: 02.0.3 | B10: Electrical motors — synchronous, up to 25 MW | C10: 3 | D10: 0.15 | E10: 0.9 | F10: 6 | G10: 500 | H10: 1000 | I10: =G10*'Currency-Conversion'!$C$10 -> 1.5319397e+09 | J10: =H10*'Currency-Conversion'!$C$10 -> 3.0638794e+09 | K10: 02.0.4 — Transformers — single/three phase, up to 100 MW; 30 kV | L10: 3 | M10: 0.2 | N10: 0.7 | O10: 6
A11: 02.0.3 | B11: Electrical motors — direct current, up to 10 MW | C11: 3.5 | D11: 0.15 | E11: 1 | F11: 8 | G11: 1000 | H11: 2000 | I11: =G11*'Currency-Conversion'!$C$10 -> 3.0638794e+09 | J11: =H11*'Currency-Conversion'!$C$10 -> 6.1277589e+09 | K11: 02.0.4 — Transformers — special design (rectifier/furnace transformers), up to 50 MW | L11: 3.5 | M11: 0.25 | N11: 1 | O11: 6
A12: 02.0.3 | B12: Electrical motors — special design (e.g. ring motor), up to 25 MW | C12: 4 | D12: 0.2 | E12: 1 | F12: 8 | G12: 2500 | H12: 5000 | I12: =G12*'Currency-Conversion'!$C$10 -> 7.6596986e+09 | J12: =H12*'Currency-Conversion'!$C$10 -> 1.5319397e+10 | K12: 02.0.5 — Pumps incl. motor drive — reciprocating type, up to 5 MW; 50 bar | L12: 3 | M12: 0.25 | N12: 0.8 | O12: 10
A13: 02.0.4 | B13: Transformers — single/three phase, up to 100 MW; 30 kV | C13: 3 | D13: 0.2 | E13: 0.7 | F13: 6 | G13: 1000 | H13: 2000 | I13: =G13*'Currency-Conversion'!$C$10 -> 3.0638794e+09 | J13: =H13*'Currency-Conversion'!$C$10 -> 6.1277589e+09 | K13: 02.0.5 — Pumps incl. motor drive — centrifugal type, up to 5 MW; 50 bar | L13: 3.3 | M13: 0.25 | N13: 0.7 | O13: 6
A14: 02.0.4 | B14: Transformers — special design (rectifier/furnace transformers), up to 50 MW | C14: 3.5 | D14: 0.25 | E14: 1 | F14: 6 | G14: 2000 | H14: 4000 | I14: =G14*'Currency-Conversion'!$C$10 -> 6.1277589e+09 | J14: =H14*'Currency-Conversion'!$C$10 -> 1.2255518e+10 | K14: 02.0.5 — Pumps incl. motor drive — special design (submerged, deepwell) | L14: 3.5 | M14: 0.3 | N14: 1 | O14: 8
A15: 02.0.5 | B15: Pumps incl. motor drive — reciprocating type, up to 5 MW; 50 bar | C15: 3 | D15: 0.25 | E15: 0.8 | F15: 10 | G15: 1000 | H15: 2000 | I15: =G15*'Currency-Conversion'!$C$10 -> 3.0638794e+09 | J15: =H15*'Currency-Conversion'!$C$10 -> 6.1277589e+09 | K15: 02.0.6 — Compressors incl. drive — reciprocating, up to 10 MW; 100 bar | L15: 3.7 | M15: 0.2 | N15: 0.75 | O15: 10
A16: 02.0.5 | B16: Pumps incl. motor drive — centrifugal type, up to 5 MW; 50 bar | C16: 3.3 | D16: 0.25 | E16: 0.7 | F16: 6 | G16: 1000 | H16: 2000 | I16: =G16*'Currency-Conversion'!$C$10 -> 3.0638794e+09 | J16: =H16*'Currency-Conversion'!$C$10 -> 6.1277589e+09 | K16: 02.0.6 — Compressors — turbo (axial/radial), turbine driven, up to 10 MW; 50 bar | L16: 4 | M16: 0.25 | N16: 1 | O16: 15
... A22: 02.0.8 | B22: Other individual machines, not specified elsewhere | C22: 2.5 | D22: 0.2 | E22: 0.4 | F22: 5 | G22: 500 | H22: 1000 | I22: =G22*'Currency-Conversion'!$C$10 -> 1.5319397e+09 | J22: =H22*'Currency-Conversion'!$C$10 -> 3.0638794e+09 | K22: 03.0.3 — Hoists, shaft lifts | L22: 2.5 | M22: 0.2 | N22: 0.6 | O22: 6
A23: 03.0 | B23: MINING INDUSTRY — Individual Machines | K23: 03.0.4 — Compressors/ventilators incl. drive — turbine driven, up to 10 000 kW; 50 bar | L23: 3 | M23: 0.3 | N23: 1 | O23: 10
A24: 03.0.1 | B24: Dredgers, excavators, draglines and other exploitation machines | C24: 4 | D24: 0.3 | E24: 1 | F24: 15 | G24: 5000 | H24: 10000 | I24: =G24*'Currency-Conversion'!$C$10 -> 1.5319397e+10 | J24: =H24*'Currency-Conversion'!$C$10 -> 3.0638794e+10 | K24: 03.0.4 — Compressors/ventilators incl. drive — motor driven, up to 10 000 kW; 50 bar | L24: 3.5 | M24: 0.2 | N24: 1.25 | O24: 15
A25: 03.0.2 | B25: Breakers, crushers | C25: 3.5 | D25: 0.25 | E25: 1.5 | F25: 25 | G25: 2500 | H25: 5000 | I25: =G25*'Currency-Conversion'!$C$10 -> 7.6596986e+09 | J25: =H25*'Currency-Conversion'!$C$10 -> 1.5319397e+10 | K25: 03.0.5 — Kilns, reverberatory furnaces, pelletizers | L25: 3 | M25: 0.15 | N25: 0.5 | O25: 6
A26: 03.0.3 | B26: Hoists, shaft lifts | C26: 2.5 | D26: 0.2 | E26: 0.6 | F26: 6 | G26: 1000 | H26: 2000 | I26: =G26*'Currency-Conversion'!$C$10 -> 3.0638794e+09 | J26: =H26*'Currency-Conversion'!$C$10 -> 6.1277589e+09 | K26: 03.0.6 — Other individual machines, not specified elsewhere | L26: 2.5 | M26: 0.1 | N26: 0.5 | O26: 5
A27: 03.0.4 | B27: Compressors/ventilators incl. drive — turbine driven, up to 10 000 kW; 50 bar | C27: 3 | D27: 0.3 | E27: 1 | F27: 10 | G27: 5000 | H27: 10000 | I27: =G27*'Currency-Conversion'!$C$10 -> 1.5319397e+10 | J27: =H27*'Currency-Conversion'!$C$10 -> 3.0638794e+10 | K27: 04.0.1 — Vessels, pressure vessels, distallation columns, crackers, reactors, furnaces | L27: 3.2 | M27: 0.25 | N27: 0.6 | O27: 6
A28: 03.0.4 | B28: Compressors/ventilators incl. drive — motor driven, up to 10 000 kW; 50 bar | C28: 3.5 | D28: 0.2 | E28: 1.25 | F28: 15 | G28: 2500 | H28: 5000 | I28: =G28*'Currency-Conversion'!$C$10 -> 7.6596986e+09 | J28: =H28*'Currency-Conversion'!$C$10 -> 1.5319397e+10 | K28: 04.0.2 — Turbo-compressors/pumps — turbine driven, ≤100 MW; ≤100 bar | L28: 5.5 | M28: 0.3 | N28: 1.5 | O28: 18
A29: 03.0.5 | B29: Kilns, reverberatory furnaces, pelletizers | C29: 3 | D29: 0.15 | E29: 0.5 | F29: 6 | G29: 2500 | H29: 5000 | I29: =G29*'Currency-Conversion'!$C$10 -> 7.6596986e+09 | J29: =H29*'Currency-Conversion'!$C$10 -> 1.5319397e+10 | K29: 04.0.2 — Turbo-compressors/pumps — motor driven, ≤100 MW; ≤100 bar | L29: 4.25 | M29: 0.25 | N29: 0.9 | O29: 12
A30: 03.0.6 | B30: Other individual machines, not specified elsewhere | C30: 2.5 | D30: 0.1 | E30: 0.5 | F30: 5 | G30: 1000 | H30: 2000 | I30: =G30*'Currency-Conversion'!$C$10 -> 3.0638794e+09 | J30: =H30*'Currency-Conversion'!$C$10 -> 6.1277589e+09 | K30: 04.0.3 — Reciprocating type compressors and pumps — motor driven, ≤20 MW; ≤250 bar | L30: 3.85 | M30: 0.25 | N30: 0.75 | O30: 10
A31: 04.0 | B31: CHEMICAL INDUSTRY — Individual Machines | K31: 04.0.4 — Centrifuges | L31: 3.2 | M31: 0.2 | N31: 0.45 | O31: 5
A32: 04.0.1 | B32: Vessels, pressure vessels, distallation columns, crackers, reactors, furnaces | C32: 3.2 | D32: 0.25 | E32: 0.6 | F32: 6 | G32: 2500 | H32: 5000 | I32: =G32*'Currency-Conversion'!$C$10 -> 7.6596986e+09 | J32: =H32*'Currency-Conversion'!$C$10 -> 1.5319397e+10 | K32: 04.0.5 — Filters, cyclones, electrostatic precipitators | L32: 3.2 | M32: 0.15 | N32: 0.8 | O32: 6
A33: 04.0.2 | B33: Turbo-compressors/pumps — turbine driven, ≤100 MW; ≤100 bar | C33: 5.5 | D33: 0.3 | E33: 1.5 | F33: 18 | G33: 2500 | H33: 10000 | I33: =G33*'Currency-Conversion'!$C$10 -> 7.6596986e+09 | J33: =H33*'Currency-Conversion'!$C$10 -> 3.0638794e+10 | K33: 04.0.6 — Other individual machines, not specified elsewhere | L33: 2.75 | M33: 0.15 | N33: 0.4 | O33: 4
A34: 04.0.2 | B34: Turbo-compressors/pumps — motor driven, ≤100 MW; ≤100 bar | C34: 4.25 | D34: 0.25 | E34: 0.9 | F34: 12 | G34: 2500 | H34: 5000 | I34: =G34*'Currency-Conversion'!$C$10 -> 7.6596986e+09 | J34: =H34*'Currency-Conversion'!$C$10 -> 1.5319397e+10 | K34: 05.0.1 — Steel furnaces (Bessemer and Thomas converters, Siemens Martin furnaces) | L34: 2.7 | M34: 0.2 | N34: 0.4 | O34: 5
A35: 04.0.3 | B35: Reciprocating type compressors and pumps — motor driven, ≤20 MW; ≤250 bar | C35: 3.85 | D35: 0.25 | E35: 0.75 | F35: 10 | G35: 2000 | H35: 2000 | I35: =G35*'Currency-Conversion'!$C$10 -> 6.1277589e+09 | J35: =H35*'Currency-Conversion'!$C$10 -> 6.1277589e+09 | K35: 05.0.2 — Electrical arc furnaces | L35: 2.85 | M35: 0.25 | N35: 0.5 | O35: 6
A36: 04.0.4 | B36: Centrifuges | C36: 3.2 | D36: 0.2 | E36: 0.45 | F36: 5 | G36: 500 | H36: 1000 | I36: =G36*'Currency-Conversion'!$C$10 -> 1.5319397e+09 | J36: =H36*'Currency-Conversion'!$C$10 -> 3.0638794e+09 | K36: 05.0.3 — Other furnaces | L36: 2.5 | M36: 0.2 | N36: 0.4 | O36: 5
A37: 04.0.5 | B37: Filters, cyclones, electrostatic precipitators | C37: 3.2 | D37: 0.15 | E37: 0.8 | F37: 6 | G37: 2500 | H37: 5000 | I37: =G37*'Currency-Conversion'!$C$10 -> 7.6596986e+09 | J37: =H37*'Currency-Conversion'!$C$10 -> 1.5319397e+10 | K37: 05.0.4 — Hot rolling mills, continuous casting machines | L37: 3 | M37: 0.2 | N37: 0.5 | O37: 6
A38: 04.0.6 | B38: Other individual machines, not specified elsewhere | C38: 2.75 | D38: 0.15 | E38: 0.4 | F38: 4 | G38: 500 | H38: 1000 | I38: =G38*'Currency-Conversion'!$C$10 -> 1.5319397e+09 | J38: =H38*'Currency-Conversion'!$C$10 -> 3.0638794e+09 | K38: 05.0.5 — Extrusion presses, forging hammers, forging presses, shears and punching machines, presses, cutters | L38: 3.1 | M38: 0.2 | N38: 0.6 | O38: 8
A39: 05.0 | B39: METAL INDUSTRY — Individual Machines | K39: 05.0.6 — Cold rolling mills | L39: 2.85 | M39: 0.2 | N39: 0.5 | O39: 5
A40: 05.0.1 | B40: Steel furnaces (Bessemer and Thomas converters, Siemens Martin furnaces) | C40: 2.7 | D40: 0.2 | E40: 0.4 | F40: 5 | G40: 2500 | H40: 5000 | I40: =G40*'Currency-Conversion'!$C$10 -> 7.6596986e+09 | J40: =H40*'Currency-Conversion'!$C$10 -> 1.5319397e+10 | K40: 05.0.7 — Machine tools, incl. NC equipment, lathes, planing etc. | L40: 2.2 | M40: 0.15 | N40: 0.35 | O40: 4
A41: 05.0.2 | B41: Electrical arc furnaces | C41: 2.85 | D41: 0.25 | E41: 0.5 | F41: 6 | G41: 2500 | H41: 5000 | I41: =G41*'Currency-Conversion'!$C$10 -> 7.6596986e+09 | J41: =H41*'Currency-Conversion'!$C$10 -> 1.5319397e+10 | K41: 05.0.8 — Scrap shearing machines, shredders | L41: 2.5 | M41: 0.25 | N41: 0.5 | O41: 5
A42: 05.0.3 | B42: Other furnaces | C42: 2.5 | D42: 0.2 | E42: 0.4 | F42: 5 | G42: 2500 | H42: 5000 | I42: =G42*'Currency-Conversion'!$C$10 -> 7.6596986e+09 | J42: =H42*'Currency-Conversion'!$C$10 -> 1.5319397e+10 | K42: 05.0.9 — Other individual machines, not specified elsewhere | L42: 2.3 | M42: 0.15 | N42: 0.4 | O42: 4
A43: 05.0.4 | B43: Hot rolling mills, continuous casting machines | C43: 3 | D43: 0.2 | E43: 0.5 | F43: 6 | G43: 2500 | H43: 5000 | I43: =G43*'Currency-Conversion'!$C$10 -> 7.6596986e+09 | J43: =H43*'Currency-Conversion'!$C$10 -> 1.5319397e+10 | K43: 06.0.1 — Crushers (hammer, jaw) | L43: 4.5 | M43: 0.1 | N43: 1.5 | O43: 20
A44: 05.0.5 | B44: Extrusion presses, forging hammers, forging presses, shears and punching machines, presses, cutters | C44: 3.1 | D44: 0.2 | E44: 0.6 | F44: 8 | G44: 2500 | H44: 5000 | I44: =G44*'Currency-Conversion'!$C$10 -> 7.6596986e+09 | J44: =H44*'Currency-Conversion'!$C$10 -> 1.5319397e+10 | K44: 06.0.2 — Transport systems: conveyor belts, bucket elevators, air slides, air lifts | L44: 2.8 | M44: 0.15 | N44: 0.4 | O44: 5
A45: 05.0.6 | B45: Cold rolling mills | C45: 2.85 | D45: 0.2 | E45: 0.5 | F45: 5 | G45: 1250 | H45: 2500 | I45: =G45*'Currency-Conversion'!$C$10 -> 3.8298493e+09 | J45: =H45*'Currency-Conversion'!$C$10 -> 7.6596986e+09 | K45: 06.0.3 — Mills: raw material grinding, clinker grinding, coal grinding, mixers | L45: 3.4 | M45: 0.15 | N45: 0.5 | O45: 6
A46: 05.0.7 | B46: Machine tools, incl. NC equipment, lathes, planing etc. | C46: 2.2 | D46: 0.15 | E46: 0.35 | F46: 4 | G46: 500 | H46: 1000 | I46: =G46*'Currency-Conversion'!$C$10 -> 1.5319397e+09 | J46: =H46*'Currency-Conversion'!$C$10 -> 3.0638794e+09 | K46: 06.0.4 — Filters: cyclones, separators, bag filters, electrostatic precipitators (mills, coolers) | L46: 3.2 | M46: 0.15 | N46: 0.8 | O46: 6
A47: 05.0.8 | B47: Scrap shearing machines, shredders | C47: 2.5 | D47: 0.25 | E47: 0.5 | F47: 5 | G47: 2500 | H47: 5000 | I47: =G47*'Currency-Conversion'!$C$10 -> 7.6596986e+09 | J47: =H47*'Currency-Conversion'!$C$10 -> 1.5319397e+10 | K47: 06.0.5 — Kilns, precalcining and drying furnaces, reheating and melting furnaces | L47: 3.4 | M47: 0.2 | N47: 0.6 | O47: 7
A48: 05.0.9 | B48: Other individual machines, not specified elsewhere | C48: 2.3 | D48: 0.15 | E48: 0.4 | F48: 4 | G48: 500 | H48: 1000 | I48: =G48*'Currency-Conversion'!$C$10 -> 1.5319397e+09 | J48: =H48*'Currency-Conversion'!$C$10 -> 3.0638794e+09 | K48: 06.0.6 — Coolers: rotary, planetary, grate type | L48: 3.2 | M48: 0.15 | N48: 0.5 | O48: 5
A49: 06.0 | B49: BUILDING INDUSTRY — Individual Machines | K49: 06.0.7 — Material storage: stackers and reclaimers, weighing devices | L49: 3.2 | M49: 0.1 | N49: 0.75 | O49: 10
A50: 06.0.1 | B50: Crushers (hammer, jaw) | C50: 4.5 | D50: 0.1 | E50: 1.5 | F50: 20 | G50: 2500 | H50: 5000 | I50: =G50*'Currency-Conversion'!$C$10 -> 7.6596986e+09 | J50: =H50*'Currency-Conversion'!$C$10 -> 1.5319397e+10 | K50: 06.0.8 — Bagging machines, bulk loading | L50: 2.7 | M50: 0.15 | N50: 0.4 | O50: 6
A51: 06.0.2 | B51: Transport systems: conveyor belts, bucket elevators, air slides, air lifts | C51: 2.8 | D51: 0.15 | E51: 0.4 | F51: 5 | G51: 500 | H51: 1000 | I51: =G51*'Currency-Conversion'!$C$10 -> 1.5319397e+09 | J51: =H51*'Currency-Conversion'!$C$10 -> 3.0638794e+09 | K51: 06.0.9 — Glass manufacturing lines | L51: 3.1 | M51: 0.15 | N51: 0.45 | O51: 5
A52: 06.0.3 | B52: Mills: raw material grinding, clinker grinding, coal grinding, mixers | C52: 3.4 | D52: 0.15 | E52: 0.5 | F52: 6 | G52: 2500 | H52: 5000 | I52: =G52*'Currency-Conversion'!$C$10 -> 7.6596986e+09 | J52: =H52*'Currency-Conversion'!$C$10 -> 1.5319397e+10 | K52: 06.0.10 — Other individual machines, not specified elsewhere | L52: 2.8 | M52: 0.1 | N52: 0.4 | O52: 4
A53: 06.0.4 | B53: Filters: cyclones, separators, bag filters, electrostatic precipitators (mills, coolers) | C53: 3.2 | D53: 0.15 | E53: 0.8 | F53: 6 | G53: 1250 | H53: 2500 | I53: =G53*'Currency-Conversion'!$C$10 -> 3.8298493e+09 | J53: =H53*'Currency-Conversion'!$C$10 -> 7.6596986e+09 | K53: 07.0.1 — Frame saws | L53: 4.5 | M53: 0.1 | N53: 1.2 | O53: 15
A54: 06.0.5 | B54: Kilns, precalcining and drying furnaces, reheating and melting furnaces | C54: 3.4 | D54: 0.2 | E54: 0.6 | F54: 7 | G54: 2500 | H54: 5000 | I54: =G54*'Currency-Conversion'!$C$10 -> 7.6596986e+09 | J54: =H54*'Currency-Conversion'!$C$10 -> 1.5319397e+10 | K54: 07.0.2 — Wood chippers, veneering machines, peelers, chippers etc. | L54: 3.6 | M54: 0.15 | N54: 0.75 | O54: 8
A55: 06.0.6 | B55: Coolers: rotary, planetary, grate type | C55: 3.2 | D55: 0.15 | E55: 0.5 | F55: 5 | G55: 2500 | H55: 5000 | I55: =G55*'Currency-Conversion'!$C$10 -> 7.6596986e+09 | J55: =H55*'Currency-Conversion'!$C$10 -> 1.5319397e+10 | K55: 07.0.3 — Single and multi-stage presses | L55: 3.75 | M55: 0.2 | N55: 0.65 | O55: 7
A56: 06.0.7 | B56: Material storage: stackers and reclaimers, weighing devices | C56: 3.2 | D56: 0.1 | E56: 0.75 | F56: 10 | G56: 1000 | H56: 2000 | I56: =G56*'Currency-Conversion'!$C$10 -> 3.0638794e+09 | J56: =H56*'Currency-Conversion'!$C$10 -> 6.1277589e+09 | K56: 07.0.4 — Other individual machines, not specified elsewhere | L56: 2.2 | M56: 0.1 | N56: 0.4 | O56: 4
A57: 06.0.8 | B57: Bagging machines, bulk loading | C57: 2.7 | D57: 0.15 | E57: 0.4 | F57: 6 | G57: 1000 | H57: 2000 | I57: =G57*'Currency-Conversion'!$C$10 -> 3.0638794e+09 | J57: =H57*'Currency-Conversion'!$C$10 -> 6.1277589e+09 | K57: 08.0.1 — Bark removing (decorticating) machines, wood chippers, wood grinders | L57: 3.6 | M57: 0.15 | N57: 0.75 | O57: 8
A58: 06.0.9 | B58: Glass manufacturing lines | C58: 3.1 | D58: 0.15 | E58: 0.45 | F58: 5 | G58: 1000 | H58: 2000 | I58: =G58*'Currency-Conversion'!$C$10 -> 3.0638794e+09 | J58: =H58*'Currency-Conversion'!$C$10 -> 6.1277589e+09 | K58: 08.0.2 — Beating mills, finishers, Jordan mills, Dolly tubs | L58: 2.9 | M58: 0.2 | N58: 0.45 | O58: 5
A59: 06.0.10 | B59: Other individual machines, not specified elsewhere | C59: 2.8 | D59: 0.1 | E59: 0.4 | F59: 4 | G59: 1000 | H59: 2000 | I59: =G59*'Currency-Conversion'!$C$10 -> 3.0638794e+09 | J59: =H59*'Currency-Conversion'!$C$10 -> 6.1277589e+09 | K59: 08.0.3 — Pulp sheet or paper making machines | L59: 3 | M59: 0.1 | N59: 0.45 | O59: 5
A60: 07.0 | B60: TIMBER & WOOD INDUSTRY — Individual Machines | K60: 08.0.4 — Black liquor boilers | L60: 3 | M60: 0.1 | N60: 0.55 | O60: 6
A61: 07.0.1 | B61: Frame saws | C61: 4.5 | D61: 0.1 | E61: 1.2 | F61: 15 | G61: 1000 | H61: 2000 | I61: =G61*'Currency-Conversion'!$C$10 -> 3.0638794e+09 | J61: =H61*'Currency-Conversion'!$C$10 -> 6.1277589e+09 | K61: 08.0.5 — Other individual machines, not specified elsewhere | L61: 2.5 | M61: 0.15 | N61: 0.4 | O61: 4
A62: 07.0.2 | B62: Wood chippers, veneering machines, peelers, chippers etc. | C62: 3.6 | D62: 0.15 | E62: 0.75 | F62: 8 | G62: 1000 | H62: 2000 | I62: =G62*'Currency-Conversion'!$C$10 -> 3.0638794e+09 | J62: =H62*'Currency-Conversion'!$C$10 -> 6.1277589e+09 | K62: 09.0.1 — Rotary printing machines | L62: 2.2 | M62: 0.2 | N62: 0.4 | O62: 4
A63: 07.0.3 | B63: Single and multi-stage presses | C63: 3.75 | D63: 0.2 | E63: 0.65 | F63: 7 | G63: 1000 | H63: 2000 | I63: =G63*'Currency-Conversion'!$C$10 -> 3.0638794e+09 | J63: =H63*'Currency-Conversion'!$C$10 -> 6.1277589e+09 | K63: 09.0.2 — Other printing machines | L63: 2.5 | M63: 0.2 | N63: 1.45 | O63: 5
A64: 07.0.4 | B64: Other individual machines, not specified elsewhere | C64: 2.2 | D64: 0.1 | E64: 0.4 | F64: 4 | G64: 1500 | H64: 1000 | I64: =G64*'Currency-Conversion'!$C$10 -> 4595819175 | J64: =H64*'Currency-Conversion'!$C$10 -> 3.0638794e+09 | K64: 09.0.3 — Type setting machines | L64: 2 | M64: 0.15 | N64: 0.5 | O64: 3
A65: 08.0 | B65: PULP AND PAPER INDUSTRY — Individual Machines | K65: 09.0.4 — Electronic scanning machines | L65: 2.5 | M65: 0.2 | N65: 0.6 | O65: 6
A66: 08.0.1 | B66: Bark removing (decorticating) machines, wood chippers, wood grinders | C66: 3.6 | D66: 0.15 | E66: 0.75 | F66: 8 | G66: 1000 | H66: 2000 | I66: =G66*'Currency-Conversion'!$C$10 -> 3.0638794e+09 | J66: =H66*'Currency-Conversion'!$C$10 -> 6.1277589e+09 | K66: 09.0.5 — Presses, cutters, punchers | L66: 2.4 | M66: 0.2 | N66: 0.5 | O66: 5
A67: 08.0.2 | B67: Beating mills, finishers, Jordan mills, Dolly tubs | C67: 2.9 | D67: 0.2 | E67: 0.45 | F67: 5 | G67: 500 | H67: 1000 | I67: =G67*'Currency-Conversion'!$C$10 -> 1.5319397e+09 | J67: =H67*'Currency-Conversion'!$C$10 -> 3.0638794e+09 | K67: 09.0.6 — Other individual machines, not specified elsewhere | L67: 2 | M67: 0.15 | N67: 0.4 | O67: 3
A68: 08.0.3 | B68: Pulp sheet or paper making machines | C68: 3 | D68: 0.1 | E68: 0.45 | F68: 5 | G68: 2500 | H68: 5000 | I68: =G68*'Currency-Conversion'!$C$10 -> 7.6596986e+09 | J68: =H68*'Currency-Conversion'!$C$10 -> 1.5319397e+10 | K68: 10.0.1 — All individual machines, not specified elsewhere | L68: 2.5 | M68: 0.15 | N68: 0.4 | O68: 4
A69: 08.0.4 | B69: Black liquor boilers | C69: 3 | D69: 0.1 | E69: 0.55 | F69: 6 | G69: 2500 | H69: 5000 | I69: =G69*'Currency-Conversion'!$C$10 -> 7.6596986e+09 | J69: =H69*'Currency-Conversion'!$C$10 -> 1.5319397e+10 | K69: 11.0.1 — Bale breakers, openers, carding machines | L69: 2 | M69: 0.2 | N69: 0.4 | O69: 5
A70: 08.0.5 | B70: Other individual machines, not specified elsewhere | C70: 2.5 | D70: 0.15 | E70: 0.4 | F70: 4 | G70: 500 | H70: 1000 | I70: =G70*'Currency-Conversion'!$C$10 -> 1.5319397e+09 | J70: =H70*'Currency-Conversion'!$C$10 -> 3.0638794e+09 | K70: 11.0.2 — Spinning, roving, twisting machines | L70: 1.8 | M70: 0.1 | N70: 0.3 | O70: 2
A71: 09.0 | B71: PRINTING & PACKING MATERIAL INDUSTRIES — Individual Machines | K71: 11.0.3 — Weaving machines, knitting machines | L71: 2 | M71: 0.15 | N71: 0.35 | O71: 3
A72: 09.0.1 | B72: Rotary printing machines | C72: 2.2 | D72: 0.2 | E72: 0.4 | F72: 4 | G72: 1000 | H72: 2000 | I72: =G72*'Currency-Conversion'!$C$10 -> 3.0638794e+09 | J72: =H72*'Currency-Conversion'!$C$10 -> 6.1277589e+09 | K72: 11.0.4 — Printing machines | L72: 1.8 | M72: 0.2 | N72: 0.4 | O72: 4
A73: 09.0.2 | B73: Other printing machines | C73: 2.5 | D73: 0.2 | E73: 1.45 | F73: 5 | G73: 1000 | H73: 2000 | I73: =G73*'Currency-Conversion'!$C$10 -> 3.0638794e+09 | J73: =H73*'Currency-Conversion'!$C$10 -> 6.1277589e+09 | K73: 11.0.5 — Washing machines (dry cleaners) | L73: 2 | M73: 0.2 | N73: 0.5 | O73: 5
A74: 09.0.3 | B74: Type setting machines | C74: 2 | D74: 0.15 | E74: 0.5 | F74: 3 | G74: 500 | H74: 1000 | I74: =G74*'Currency-Conversion'!$C$10 -> 1.5319397e+09 | J74: =H74*'Currency-Conversion'!$C$10 -> 3.0638794e+09 | K74: 11.0.6 — Other individual machines, not specified elsewhere | L74: 1.8 | M74: 0.1 | N74: 0.3 | O74: 3
A75: 09.0.4 | B75: Electronic scanning machines | C75: 2.5 | D75: 0.2 | E75: 0.6 | F75: 6 | G75: 500 | H75: 1000 | I75: =G75*'Currency-Conversion'!$C$10 -> 1.5319397e+09 | J75: =H75*'Currency-Conversion'!$C$10 -> 3.0638794e+09 | K75: 12.0.1 — Extruders, injection moulding machines, plastic-blowing machines, vulcanizing presses | L75: 3.5 | M75: 0.2 | N75: 0.9 | O75: 10
A76: 09.0.5 | B76: Presses, cutters, punchers | C76: 2.4 | D76: 0.2 | E76: 0.5 | F76: 5 | G76: 500 | H76: 1000 | I76: =G76*'Currency-Conversion'!$C$10 -> 1.5319397e+09 | J76: =H76*'Currency-Conversion'!$C$10 -> 3.0638794e+09 | K76: 12.0.2 — Cutters, mills, mixers, calanders | L76: 3.2 | M76: 0.2 | N76: 0.65 | O76: 7
A77: 09.0.6 | B77: Other individual machines, not specified elsewhere | C77: 2 | D77: 0.15 | E77: 0.4 | F77: 3 | G77: 500 | H77: 1000 | I77: =G77*'Currency-Conversion'!$C$10 -> 1.5319397e+09 | J77: =H77*'Currency-Conversion'!$C$10 -> 3.0638794e+09 | K77: 12.0.3 — Strand-bead forming machines | L77: 3 | M77: 0.2 | N77: 0.5 | O77: 5
A78: 10.0 | B78: LEATHER INDUSTRY — Individual Machines | K78: 12.0.4 — Vacuum impregnation machines | L78: 3.2 | M78: 0.2 | N78: 0.65 | O78: 8
A79: 10.0.1 | B79: All individual machines, not specified elsewhere | C79: 2.5 | D79: 0.15 | E79: 0.4 | F79: 4 | G79: 500 | H79: 1000 | I79: =G79*'Currency-Conversion'!$C$10 -> 1.5319397e+09 | J79: =H79*'Currency-Conversion'!$C$10 -> 3.0638794e+09 | K79: 12.0.5 — Other individual machines, not specified elsewhere | L79: 2.5 | M79: 0.15 | N79: 0.45 | O79: 5
A80: 11.0 | B80: TEXTILE INDUSTRY — Individual Machines | K80: 13.0.1 — Aspirators, cleaning, screening, brushing, shelling, winnowing machines | L80: 2.6 | M80: 0.2 | N80: 0.4 | O80: 4
A81: 11.0.1 | B81: Bale breakers, openers, carding machines | C81: 2 | D81: 0.2 | E81: 0.4 | F81: 5 | G81: 1000 | H81: 2000 | I81: =G81*'Currency-Conversion'!$C$10 -> 3.0638794e+09 | J81: =H81*'Currency-Conversion'!$C$10 -> 6.1277589e+09 | K81: 13.0.2 — Cyclones, filters, dust collectors, bag filters etc. | L81: 2.8 | M81: 0.2 | N81: 0.45 | O81: 5
A82: 11.0.2 | B82: Spinning, roving, twisting machines | C82: 1.8 | D82: 0.1 | E82: 0.3 | F82: 2 | G82: 500 | H82: 1000 | I82: =G82*'Currency-Conversion'!$C$10 -> 1.5319397e+09 | J82: =H82*'Currency-Conversion'!$C$10 -> 3.0638794e+09 | K82: 13.0.3 — Ball mills, grinders, crushing mills | L82: 2.6 | M82: 0.2 | N82: 0.5 | O82: 5
A83: 11.0.3 | B83: Weaving machines, knitting machines | C83: 2 | D83: 0.15 | E83: 0.35 | F83: 3 | G83: 500 | H83: 1000 | I83: =G83*'Currency-Conversion'!$C$10 -> 1.5319397e+09 | J83: =H83*'Currency-Conversion'!$C$10 -> 3.0638794e+09 | K83: 13.0.4 — Oil presses, cocoa butter presses, other presses, beet slicers, cutters, extractors, pelletizers | L83: 3.1 | M83: 0.2 | N83: 0.55 | O83: 6
A84: 11.0.4 | B84: Printing machines | C84: 1.8 | D84: 0.2 | E84: 0.4 | F84: 4 | G84: 500 | H84: 1000 | I84: =G84*'Currency-Conversion'!$C$10 -> 1.5319397e+09 | J84: =H84*'Currency-Conversion'!$C$10 -> 3.0638794e+09 | K84: 13.0.5 — Sugar cane crusher mills (roller mills) incl. drive — turbine driven, up to 5 MW | L84: 4.25 | M84: 0.25 | N84: 1 | O84: 12
A85: 11.0.5 | B85: Washing machines (dry cleaners) | C85: 2 | D85: 0.2 | E85: 0.5 | F85: 5 | G85: 1000 | H85: 2000 | I85: =G85*'Currency-Conversion'!$C$10 -> 3.0638794e+09 | J85: =H85*'Currency-Conversion'!$C$10 -> 6.1277589e+09 | K85: 13.0.5 — Sugar cane crusher mills (roller mills) incl. drive — motor driven, up to 5 MW | L85: 3.8 | M85: 0.2 | N85: 0.75 | O85: 10
A86: 11.0.6 | B86: Other individual machines, not specified elsewhere | C86: 1.8 | D86: 0.1 | E86: 0.3 | F86: 3 | G86: 500 | H86: 1000 | I86: =G86*'Currency-Conversion'!$C$10 -> 1.5319397e+09 | J86: =H86*'Currency-Conversion'!$C$10 -> 3.0638794e+09 | K86: 13.0.6 — Ovens, roasting plants, dryers | L86: 2.1 | M86: 0.25 | N86: 0.4 | O86: 3
A87: 12.0 | B87: PLASTIC & RUBBER PRODUCTS INDUSTRIES — Individual Machines | K87: 13.0.7 — Bottle cleaning and filling machines, packing machines | L87: 2.9 | M87: 0.15 | N87: 0.5 | O87: 5
A88: 12.0.1 | B88: Extruders, injection moulding machines, plastic-blowing machines, vulcanizing presses | C88: 3.5 | D88: 0.2 | E88: 0.9 | F88: 10 | G88: 1250 | H88: 2500 | I88: =G88*'Currency-Conversion'!$C$10 -> 3.8298493e+09 | J88: =H88*'Currency-Conversion'!$C$10 -> 7.6596986e+09 | K88: 13.0.8 — Centrifuges, separators | L88: 3.2 | M88: 0.15 | N88: 0.5 | O88: 5
A89: 12.0.2 | B89: Cutters, mills, mixers, calanders | C89: 3.2 | D89: 0.2 | E89: 0.65 | F89: 7 | G89: 500 | H89: 1000 | I89: =G89*'Currency-Conversion'!$C$10 -> 1.5319397e+09 | J89: =H89*'Currency-Conversion'!$C$10 -> 3.0638794e+09 | K89: 13.0.9 — Automatic cigar and cigarette production machines | L89: 3.4 | M89: 0.15 | N89: 0.75 | O89: 8
A90: 12.0.3 | B90: Strand-bead forming machines | C90: 3 | D90: 0.2 | E90: 0.5 | F90: 5 | G90: 2500 | H90: 5000 | I90: =G90*'Currency-Conversion'!$C$10 -> 7.6596986e+09 | J90: =H90*'Currency-Conversion'!$C$10 -> 1.5319397e+10 | K90: 13.0.10 — Vacuum dryers, pulverizer installations for instant pulverized food production | L90: 3.3 | M90: 0.2 | N90: 0.6 | O90: 6
A91: 12.0.4 | B91: Vacuum impregnation machines | C91: 3.2 | D91: 0.2 | E91: 0.65 | F91: 8 | G91: 1000 | H91: 2000 | I91: =G91*'Currency-Conversion'!$C$10 -> 3.0638794e+09 | J91: =H91*'Currency-Conversion'!$C$10 -> 6.1277589e+09 | K91: 13.0.11 — Other individual machines, not specified elsewhere | L91: 2.5 | M91: 0.1 | N91: 0.4 | O91: 4
A92: 12.0.5 | B92: Other individual machines, not specified elsewhere | C92: 2.5 | D92: 0.15 | E92: 0.45 | F92: 5 | G92: 500 | H92: 1000 | I92: =G92*'Currency-Conversion'!$C$10 -> 1.5319397e+09 | J92: =H92*'Currency-Conversion'!$C$10 -> 3.0638794e+09 | K92: 14.0.1 — Heaters, pasteurizers, homogenizers, coolers | L92: 2.4 | M92: 0.15 | N92: 0.3 | O92: 3
A93: 13.0 | B93: FOOD INDUSTRY (VEGETABLE ORIGIN) — Individual Machines | K93: 14.0.2 — Cooling compressors incl. motor drive | L93: 3.6 | M93: 0.2 | N93: 0.75 | O93: 8
A94: 13.0.1 | B94: Aspirators, cleaning, screening, brushing, shelling, winnowing machines | C94: 2.6 | D94: 0.2 | E94: 0.4 | F94: 4 | G94: 500 | H94: 1000 | I94: =G94*'Currency-Conversion'!$C$10 -> 1.5319397e+09 | J94: =H94*'Currency-Conversion'!$C$10 -> 3.0638794e+09 | K94: 14.0.3 — Centrifuges, separators | L94: 3.2 | M94: 0.15 | N94: 0.5 | O94: 5
A95: 13.0.2 | B95: Cyclones, filters, dust collectors, bag filters etc. | C95: 2.8 | D95: 0.2 | E95: 0.45 | F95: 5 | G95: 500 | H95: 1000 | I95: =G95*'Currency-Conversion'!$C$10 -> 1.5319397e+09 | J95: =H95*'Currency-Conversion'!$C$10 -> 3.0638794e+09 | K95: 14.0.4 — Meat saws, cutters, choppers, mincing machines, mixers | L95: 2.5 | M95: 0.25 | N95: 0.35 | O95: 4
A96: 13.0.3 | B96: Ball mills, grinders, crushing mills | C96: 2.6 | D96: 0.2 | E96: 0.5 | F96: 5 | G96: 500 | H96: 1000 | I96: =G96*'Currency-Conversion'!$C$10 -> 1.5319397e+09 | J96: =H96*'Currency-Conversion'!$C$10 -> 3.0638794e+09 | K96: 14.0.5 — Vacuum dryers, pulverizers | L96: 3.3 | M96: 0.2 | N96: 0.6 | O96: 6
A97: 13.0.4 | B97: Oil presses, cocoa butter presses, other presses, beet slicers, cutters, extractors, pelletizers | C97: 3.1 | D97: 0.2 | E97: 0.55 | F97: 6 | G97: 1000 | H97: 2000 | I97: =G97*'Currency-Conversion'!$C$10 -> 3.0638794e+09 | J97: =H97*'Currency-Conversion'!$C$10 -> 6.1277589e+09 | K97: 14.0.6 — Bottle cleaning and filling machines, packing machines | L97: 2.9 | M97: 0.15 | N97: 0.5 | O97: 5
A98: 13.0.5 | B98: Sugar cane crusher mills (roller mills) incl. drive — turbine driven, up to 5 MW | C98: 4.25 | D98: 0.25 | E98: 1 | F98: 12 | G98: 2500 | H98: 5000 | I98: =G98*'Currency-Conversion'!$C$10 -> 7.6596986e+09 | J98: =H98*'Currency-Conversion'!$C$10 -> 1.5319397e+10 | K98: 14.0.7 — Other individual machines, not specified elsewhere | L98: 2.2 | M98: 0.1 | N98: 0.4 | O98: 5
A99: 13.0.5 | B99: Sugar cane crusher mills (roller mills) incl. drive — motor driven, up to 5 MW | C99: 3.8 | D99: 0.2 | E99: 0.75 | F99: 10 | G99: 1250 | H99: 2500 | I99: =G99*'Currency-Conversion'!$C$10 -> 3.8298493e+09 | J99: =H99*'Currency-Conversion'!$C$10 -> 7.6596986e+09 | K99: 15.0.1 — Cooling compressors incl. motor drive | L99: 3.6 | M99: 0.2 | N99: 0.75 | O99: 8
A100: 13.0.6 | B100: Ovens, roasting plants, dryers | C100: 2.1 | D100: 0.25 | E100: 0.4 | F100: 3 | G100: 500 | H100: 1000 | I100: =G100*'Currency-Conversion'!$C$10 -> 1.5319397e+09 | J100: =H100*'Currency-Conversion'!$C$10 -> 3.0638794e+09 | K100: 15.0.2 — Fans, blowers | L100: 3.2 | M100: 0.2 | N100: 0.5 | O100: 5
A101: 13.0.7 | B101: Bottle cleaning and filling machines, packing machines | C101: 2.9 | D101: 0.15 | E101: 0.5 | F101: 5 | G101: 500 | H101: 1000 | I101: =G101*'Currency-Conversion'!$C$10 -> 1.5319397e+09 | J101: =H101*'Currency-Conversion'!$C$10 -> 3.0638794e+09 | K101: 15.0.3 — Evaporators, coolers, heat exchangers | L101: 2.8 | M101: 0.1 | N101: 0.4 | O101: 4
A102: 13.0.8 | B102: Centrifuges, separators | C102: 3.2 | D102: 0.15 | E102: 0.5 | F102: 5 | G102: 500 | H102: 1000 | I102: =G102*'Currency-Conversion'!$C$10 -> 1.5319397e+09 | J102: =H102*'Currency-Conversion'!$C$10 -> 3.0638794e+09 | K102: 15.0.4 — Autoclaves, sterilizers | L102: 2.5 | M102: 0.15 | N102: 0.4 | O102: 5
A103: 13.0.9 | B103: Automatic cigar and cigarette production machines | C103: 3.4 | D103: 0.15 | E103: 0.75 | F103: 8 | G103: 1000 | H103: 2000 | I103: =G103*'Currency-Conversion'!$C$10 -> 3.0638794e+09 | J103: =H103*'Currency-Conversion'!$C$10 -> 6.1277589e+09 | K103: 15.0.5 — Can manufacturing machines, filling, sealing, labelling machines | L103: 3.1 | M103: 0.1 | N103: 0.55 | O103: 6
A104: 13.0.10 | B104: Vacuum dryers, pulverizer installations for instant pulverized food production | C104: 3.3 | D104: 0.2 | E104: 0.6 | F104: 6 | G104: 1000 | H104: 2000 | I104: =G104*'Currency-Conversion'!$C$10 -> 3.0638794e+09 | J104: =H104*'Currency-Conversion'!$C$10 -> 6.1277589e+09 | K104: 15.0.6 — Other individual machines, not specified elsewhere | L104: 2.2 | M104: 0.15 | N104: 0.4 | O104: 3.5
A105: 13.0.11 | B105: Other individual machines, not specified elsewhere | C105: 2.5 | D105: 0.1 | E105: 0.4 | F105: 4 | G105: 500 | H105: 1000 | I105: =G105*'Currency-Conversion'!$C$10 -> 1.5319397e+09 | J105: =H105*'Currency-Conversion'!$C$10 -> 3.0638794e+09 | K105: 18.0.1 — Air conditioning devices — window units | L105: 4.5 | M105: 0.2 | N105: 1 | O105: 15
...

Sheet Rate-TPL
A1: EAR Rating — Third Party Liability (TPL) Section | Rating Guidelines Swiss Re EAR-Policy | Base: 2 million c-units limit, excess 2,000 c-units
A2: B.1 TABLE OF RATES FOR BASIC LIMIT (2 mio c-units, excess 2,000 c-units)
A3: Tech. Risk Cat. | B3: Industry Examples | C3: Surroundings Category a (isolated site) | D3: Surroundings Category b (outer town) | E3: Surroundings Category c (dense/urban) | F3: Min.Prem. a (c-units) | G3: Min.Prem. b (c-units) | H3: Min.Prem. c (c-units) | I3: Min.Prem. a (﷼) | J3: Min.Prem. b (﷼) | K3: Min.Prem. c (﷼)
A4: I (Light) | B4: 09 Printing, 10 Leather, 11 Textile, 13 Food (veg), 14 Food (anim) | C4: 0.2 | D4: 0.3 | E4: 0.4 | F4: 500 | G4: 800 | H4: 1500 | I4: =F4*'Currency-Conversion'!$C$10 -> 1.5319397e+09 | J4: =G4*'Currency-Conversion'!$C$10 -> 2451103560 | K4: =H4*'Currency-Conversion'!$C$10 -> 4595819175
A5: II (Medium) | B5: 01.5 Electricity dist., 01.6 Waterworks, 01.8 Telecom, 07 Timber, 08 Paper, 12 Plastic, 15 Cold stores, 17 Public svcs, 18 Hospitals, 19 Farming | C5: 0.3 | D5: 0.45 | E5: 0.6 | F5: 1300 | G5: 1800 | H5: 2500 | I5: =F5*'Currency-Conversion'!$C$10 -> 3.9830433e+09 | J5: =G5*'Currency-Conversion'!$C$10 -> 5.514983e+09 | K5: =H5*'Currency-Conversion'!$C$10 -> 7.6596986e+09
A6: III (Heavy) | B6: 01.1-.4 Power plants, 01.7 Garbage, 02 Indust. utilities, 03 Mining, 04 Chemical, 05 Metal, 06 Building, 12 Plastic, 16 Transport/ports | C6: 0.4 | D6: 0.6 | E6: 0.8 | F6: 2300 | G6: 2900 | H6: 4000 | I6: =F6*'Currency-Conversion'!$C$10 -> 7.0469227e+09 | J6: =G6*'Currency-Conversion'!$C$10 -> 8885250405 | K6: =H6*'Currency-Conversion'!$C$10 -> 1.2255518e+10
A7: B.2 FACTORS FOR ADAPTING RATES TO OTHER LIMITS (minimum excess = 1 ‰ of total limit)
A8: Total Limit (c-units mio) | B8: Factor | I8: Notes
A9: ≤ 0.5 mio | B9: 0.65
A10: 1 mio | B10: 0.8
A11: 2 mio (base) | B11: 1
A12: 4 mio | B12: 1.2
A13: 6 mio | B13: 1.4
A14: 8 mio | B14: 1.56
A15: 10 mio | B15: 1.67
A16: B.3 REBATES FOR INCREASED EXCESSES (excess in ‰ of total limit insured)
A17: Excess (‰ of total limit insured) | B17: Deduction (% of total premium) | I17: Notes
A18: 1 ‰ (min) | B18: 0% (no rebate)
A19: 2 ‰ | B19: 10%
A20: 3 ‰ | B20: 15%
A21: 5 ‰ | B21: 20%
A22: B.4 ADDITIONAL PREMIUM FOR TPL COVER DURING MAINTENANCE PERIOD
A23: Maintenance Type | B23: Additional Premium | I23: Notes
A24: Visits maintenance (12-month period) | B24: 20% of TPL rate for erection/testing (pro rata for longer periods)
A25: Extended maintenance (12-month period) | B25: 40% of TPL rate for erection/testing (pro rata for longer periods)
A26: B.5 ADDITIONAL PREMIUM FOR CROSS LIABILITY
A27: Surcharge: 35% of total TPL premium (minimum 15% if no plant/equipment/storage exposure or these are covered under MD section)
A28: B.6 DEDUCTIONS OF PREMIUM RATES FOR HIGH CONTRACT (PROJECT) VALUES
A29: Contract Value | B29: Rebate on TPL Rate | I29: Notes
A30: Up to c-units 50 mio | B30: None
A31: 50 mio to 150 mio | B31: 0 – 15%
A32: 150 mio to 350 mio | B32: 15 – 40%
A33: Above 350 mio | B33: Case by case

Sheet Rate-Deductibles
A1: EAR — Excess / Deductible Reference Tables (Swiss Re EAR Rating Guide — Section 9)
A2: D.1 REBATE FACTORS — MULTIPLES OF MINIMUM EXCESS (applied to individual item rate)
A3: Multiple of Min. Excess | B3: Rebate Factor (× basic rate) | C3: Effective Rate = | G3: Notes
A4: 2 | B4: 0.9 | C4: basic rate × 0.9
A5: 3 | B5: 0.85 | C5: basic rate × 0.85
A6: 5 | B6: 0.8 | C6: basic rate × 0.8
A7: 7.5 | B7: 0.75 | C7: basic rate × 0.75
A8: 10 | B8: 0.7 | C8: basic rate × 0.7
A9: 20 | B9: 0.65 | C9: basic rate × 0.65
A10: 30 | B10: 0.6 | C10: basic rate × 0.6
A11: 40 | B11: 0.55 | C11: basic rate × 0.55
A12: 60 | B12: 0.5 | C12: basic rate × 0.5
A13: 100 | B13: 0.45 | C13: basic rate × 0.45
A14: > 100 | B14: Consult Reinsurer
A15: D.2 PROPORTIONAL EXCESS (% of each claim)
A16: Proportional Excess (% of each claim) | B16: Rebate Factor | G16: Notes
A17: 10% | B17: 0.9
A18: 20% | B18: 0.8
A19: D.3 MINIMUM EXCESSES BY SUB-GROUP (from white Rating Tables — Source: Rate-SubGroup col G = Ref.Rate, col H = EAR source)
A20: Row | B20: Sub-Group Name (EAR Standard) | C20: Min. Rate | D20: Gen. Excess (c-units) All Events | E20: AoG/Test/Maint. Excess (c-units) | F20: EAR Table Source | G20: Notes | H20: Gen. Excess (﷼) | I20: AoG Excess (﷼)
A21: 1 | B21: 01.1.1 Boilerhouse installations — natural circulation, ≤250 t/h (boiler + superheaters, fans, water treatment, feed pumps) | C21: 3.55 | D21: 5000 | E21: 150/MW (min 10,000) | F21: Rate-SubGroup row 2 | H21: =D21*'Currency-Conversion'!$C$10 -> 1.5319397e+10 | I21: =E21&" — تبدیل خودکار ممکن نشد (نرخ به‌ازای واحد ظرفیت)." -> 150/MW (min 10,000) — تبدیل خودکار ممکن نشد (نرخ به‌ازای واحد ظرفیت).
A22: 2 | B22: 01.1.1 Boilerhouse installations comprising boiler with all auxiliaries (superheaters, fans, feed pumps, water treatment) - natural circulat | C22: 3.75 | D22: 5000 | E22: 150/MW | F22: Rate-SubGroup row 3 | H22: =D22*'Currency-Conversion'!$C$10 -> 1.5319397e+10 | I22: =E22&" — تبدیل خودکار ممکن نشد (نرخ به‌ازای واحد ظرفیت)." -> 150/MW — تبدیل خودکار ممکن نشد (نرخ به‌ازای واحد ظرفیت).
A23: 3 | B23: 01.1.2 Turbogenerating sets — turbine, generator, cooling system, governor, directly connected auxiliaries — up to 50 MW | C23: 4.4 | D23: 5000 | E23: 25000 | F23: Rate-SubGroup row 4 | H23: =D23*'Currency-Conversion'!$C$10 -> 1.5319397e+10 | I23: =E23*'Currency-Conversion'!$C$10 -> 76596986250
A24: 4 | B24: 01.1.2 Turbogenerating sets (turbine, generator, cooling system, governor, directly connected auxiliaries) — 50 to 125 MW | C24: 4.75 | D24: 5000 | E24: 250/MW (min 25,000) | F24: Rate-SubGroup row 5 | H24: =D24*'Currency-Conversion'!$C$10 -> 1.5319397e+10 | I24: =E24&" — تبدیل خودکار ممکن نشد (نرخ به‌ازای واحد ظرفیت)." -> 250/MW (min 25,000) — تبدیل خودکار ممکن نشد (نرخ به‌ازای واحد ظرفیت).
A25: 5 | B25: 01.1.2 Turbogenerating sets (turbine, generator, cooling system, governor, directly connected auxiliaries) — 125 to 250 MW | C25: 4.95 | D25: 5000 | E25: 250/MW | F25: Rate-SubGroup row 6 | H25: =D25*'Currency-Conversion'!$C$10 -> 1.5319397e+10 | I25: =E25&" — تبدیل خودکار ممکن نشد (نرخ به‌ازای واحد ظرفیت)." -> 250/MW — تبدیل خودکار ممکن نشد (نرخ به‌ازای واحد ظرفیت).
A26: 6 | B26: 01.1.2 Turbogenerating sets (turbine, generator, cooling system, governor, directly connected auxiliaries) — 250 to 450 MW | C26: 5.4 | D26: 7500 | E26: 250/MW | F26: Rate-SubGroup row 7 | H26: =D26*'Currency-Conversion'!$C$10 -> 2.2979096e+10 | I26: =E26&" — تبدیل خودکار ممکن نشد (نرخ به‌ازای واحد ظرفیت)." -> 250/MW — تبدیل خودکار ممکن نشد (نرخ به‌ازای واحد ظرفیت).
A27: 7 | B27: 01.1.3 Water-systems cycle comprising condenser, feed heater piping, pumps etc. | C27: 3.1 | D27: 2500 | E27: 5000 | F27: Rate-SubGroup row 8 | H27: =D27*'Currency-Conversion'!$C$10 -> 7.6596986e+09 | I27: =E27*'Currency-Conversion'!$C$10 -> 1.5319397e+10
A28: 8 | B28: 01.1.4 Electric equipment, control and measuring installations incl. station transformers | C28: 3.3 | D28: 2500 | E28: 5000 | F28: Rate-SubGroup row 9 | H28: =D28*'Currency-Conversion'!$C$10 -> 7.6596986e+09 | I28: =E28*'Currency-Conversion'!$C$10 -> 1.5319397e+10
A29: 9 | B29: 01.1.5 Balance of plant comprising: ash-handling, off-site tanks | C29: 3.1 | D29: 2500 | E29: 5000 | F29: Rate-SubGroup row 10 | H29: =D29*'Currency-Conversion'!$C$10 -> 7.6596986e+09 | I29: =E29*'Currency-Conversion'!$C$10 -> 1.5319397e+10
A30: 10 | B30: 01.2.1 Gas turbine power plants — Gasturbo generating sets (turbine, compressor, generator, starting device, all auxiliaries) — up to 10 MW | C30: 4.2 | D30: 5000 | E30: 10000 | F30: Rate-SubGroup row 11 | H30: =D30*'Currency-Conversion'!$C$10 -> 1.5319397e+10 | I30: =E30*'Currency-Conversion'!$C$10 -> 3.0638794e+10
A31: 11 | B31: 01.2.1 Gasturbo generating sets (turbine, compressor, generator, starting device, all auxiliaries connected to foundation block) — 10 to 20 | C31: 4.7 | D31: 5000 | E31: 750/MW (min 10,000) | F31: Rate-SubGroup row 12 | H31: =D31*'Currency-Conversion'!$C$10 -> 1.5319397e+10 | I31: =E31&" — تبدیل خودکار ممکن نشد (نرخ به‌ازای واحد ظرفیت)." -> 750/MW (min 10,000) — تبدیل خودکار ممکن نشد (نرخ به‌ازای واحد ظرفیت).
A32: 12 | B32: 01.2.1 Gasturbo generating sets (turbine, compressor, generator, starting device, all auxiliaries connected to foundation block) — 20 to 40 | C32: 5.5 | D32: 5000 | E32: 750/MW | F32: Rate-SubGroup row 13 | H32: =D32*'Currency-Conversion'!$C$10 -> 1.5319397e+10 | I32: =E32&" — تبدیل خودکار ممکن نشد (نرخ به‌ازای واحد ظرفیت)." -> 750/MW — تبدیل خودکار ممکن نشد (نرخ به‌ازای واحد ظرفیت).
A33: 13 | B33: 01.2.2 Electrical equipment control/measuring: air inlet/outlet, filters, piping, pumps incl. station transformers | C33: 3.3 | D33: 1000 | E33: 2000 | F33: Rate-SubGroup row 14 | H33: =D33*'Currency-Conversion'!$C$10 -> 3.0638794e+09 | I33: =E33*'Currency-Conversion'!$C$10 -> 6.1277589e+09
A34: 14 | B34: 01.2.3 Balance of plant off-site installations: tanks, gas receiving and/or pressure reducing plant etc. | C34: 3.1 | D34: 1000 | E34: 2000 | F34: Rate-SubGroup row 15 | H34: =D34*'Currency-Conversion'!$C$10 -> 3.0638794e+09 | I34: =E34*'Currency-Conversion'!$C$10 -> 6.1277589e+09
A35: 15 | B35: 01.3.1 Diesel generator sets — diesel engine, starting device, generator and all auxiliaries attached — engines with speed above 500 rpm | C35: 4.95 | D35: 2000 | E35: 1000/MW (min 5,000) | F35: Rate-SubGroup row 16 | H35: =D35*'Currency-Conversion'!$C$10 -> 6.1277589e+09 | I35: =E35&" — تبدیل خودکار ممکن نشد (نرخ به‌ازای واحد ظرفیت)." -> 1000/MW (min 5,000) — تبدیل خودکار ممکن نشد (نرخ به‌ازای واحد ظرفیت).
A36: 16 | B36: 01.3.1 Diesel Generator sets (diesel engine, starting device, generator, all attached auxiliaries) - engines with speed above 500 rpm — engi | C36: 4.2 | D36: 2000 | E36: 1000/MW | F36: Rate-SubGroup row 17 | H36: =D36*'Currency-Conversion'!$C$10 -> 6.1277589e+09 | I36: =E36&" — تبدیل خودکار ممکن نشد (نرخ به‌ازای واحد ظرفیت)." -> 1000/MW — تبدیل خودکار ممکن نشد (نرخ به‌ازای واحد ظرفیت).
A37: 17 | B37: 01.3.2 Electrical equipment control/measuring; air inlet/outlet, filters, piping, pumps | C37: 3.4 | D37: 1000 | E37: 2000 | F37: Rate-SubGroup row 18 | H37: =D37*'Currency-Conversion'!$C$10 -> 3.0638794e+09 | I37: =E37*'Currency-Conversion'!$C$10 -> 6.1277589e+09
A38: 18 | B38: 01.3.3 Balance of plant comprising off-site installations, tanks, etc. | C38: 3 | D38: 1000 | E38: 2000 | F38: Rate-SubGroup row 19 | H38: =D38*'Currency-Conversion'!$C$10 -> 3.0638794e+09 | I38: =E38*'Currency-Conversion'!$C$10 -> 6.1277589e+09
A39: 19 | B39: 01.4.1 Turbinehouse installations - Pelton turbine, up to 100 MW | C39: 2.95 | D39: 2500 | E39: 10000 | F39: Rate-SubGroup row 20 | H39: =D39*'Currency-Conversion'!$C$10 -> 7.6596986e+09 | I39: =E39*'Currency-Conversion'!$C$10 -> 3.0638794e+10
A40: 20 | B40: 01.4.1 Turbinehouse installations - Pelton turbine — Pelton, 100 to 200 MW | C40: 3.3 | D40: 2500 | E40: 100/MW | F40: Rate-SubGroup row 21 | H40: =D40*'Currency-Conversion'!$C$10 -> 7.6596986e+09 | I40: =E40&" — تبدیل خودکار ممکن نشد (نرخ به‌ازای واحد ظرفیت)." -> 100/MW — تبدیل خودکار ممکن نشد (نرخ به‌ازای واحد ظرفیت).
A41: 21 | B41: 01.4.1 Turbinehouse installations - Pelton turbine — Francis turbine, up to 100 MW | C41: 3.3 | D41: 2500 | E41: 10000 | F41: Rate-SubGroup row 22 | H41: =D41*'Currency-Conversion'!$C$10 -> 7.6596986e+09 | I41: =E41*'Currency-Conversion'!$C$10 -> 3.0638794e+10
A42: 22 | B42: 01.4.1 Turbinehouse installations - Pelton turbine — Francis, 100 to 200 MW | C42: 3.6 | D42: 2500 | E42: 100/MW | F42: Rate-SubGroup row 23 | H42: =D42*'Currency-Conversion'!$C$10 -> 7.6596986e+09 | I42: =E42&" — تبدیل خودکار ممکن نشد (نرخ به‌ازای واحد ظرفیت)." -> 100/MW — تبدیل خودکار ممکن نشد (نرخ به‌ازای واحد ظرفیت).
A43: 23 | B43: 01.4.1 Turbinehouse installations - Pelton turbine — Kaplan turbine, up to 100 MW | C43: 3.3 | D43: 2500 | E43: 10000 | F43: Rate-SubGroup row 24 | H43: =D43*'Currency-Conversion'!$C$10 -> 7.6596986e+09 | I43: =E43*'Currency-Conversion'!$C$10 -> 3.0638794e+10
A44: 24 | B44: 01.4.1 Turbinehouse installations - Pelton turbine — Kaplan, 100 to 200 MW | C44: 3.65 | D44: 2500 | E44: 100/MW | F44: Rate-SubGroup row 25 | H44: =D44*'Currency-Conversion'!$C$10 -> 7.6596986e+09 | I44: =E44&" — تبدیل خودکار ممکن نشد (نرخ به‌ازای واحد ظرفیت)." -> 100/MW — تبدیل خودکار ممکن نشد (نرخ به‌ازای واحد ظرفیت).
A45: 25 | B45: 01.4.1 Turbinehouse installations - Pelton turbine — Other types (tubular/axial flow reaction turbines), up to 25 MW | C45: 3.3 | D45: 2500 | E45: 5000 | F45: Rate-SubGroup row 26 | H45: =D45*'Currency-Conversion'!$C$10 -> 7.6596986e+09 | I45: =E45*'Currency-Conversion'!$C$10 -> 1.5319397e+10
A46: 26 | B46: 01.4.1 Turbinehouse installations - Pelton turbine — Other types, 25 to 50 MW | C46: 3.75 | D46: 2500 | E46: 100/MW | F46: Rate-SubGroup row 27 | H46: =D46*'Currency-Conversion'!$C$10 -> 7.6596986e+09 | I46: =E46&" — تبدیل خودکار ممکن نشد (نرخ به‌ازای واحد ظرفیت)." -> 100/MW — تبدیل خودکار ممکن نشد (نرخ به‌ازای واحد ظرفیت).
A47: 27 | B47: 01.4.2 Pumping house installations - Horizontal pumping sets, up to 25 MW | C47: 3.6 | D47: 2500 | E47: 5000 | F47: Rate-SubGroup row 28 | H47: =D47*'Currency-Conversion'!$C$10 -> 7.6596986e+09 | I47: =E47*'Currency-Conversion'!$C$10 -> 1.5319397e+10
A48: 28 | B48: 01.4.2 Pumping house installations - Horizontal pumping sets — Horizontal, 25 to 50 MW | C48: 4.1 | D48: 2500 | E48: 10000 | F48: Rate-SubGroup row 29 | H48: =D48*'Currency-Conversion'!$C$10 -> 7.6596986e+09 | I48: =E48*'Currency-Conversion'!$C$10 -> 3.0638794e+10
A49: 29 | B49: 01.4.2 Pumping house installations - Horizontal pumping sets — Vertical pumping sets, up to 25 MW | C49: 3.85 | D49: 2500 | E49: 5000 | F49: Rate-SubGroup row 30 | H49: =D49*'Currency-Conversion'!$C$10 -> 7.6596986e+09 | I49: =E49*'Currency-Conversion'!$C$10 -> 1.5319397e+10
A50: 30 | B50: 01.4.2 Pumping house installations - Horizontal pumping sets — Vertical, 25 to 50 MW | C50: 4.25 | D50: 2500 | E50: 10000 | F50: Rate-SubGroup row 31 | H50: =D50*'Currency-Conversion'!$C$10 -> 7.6596986e+09 | I50: =E50*'Currency-Conversion'!$C$10 -> 3.0638794e+10
A51: 31 | B51: 01.4.3 Electrical equipment and measuring installations, station transformers, pressurised air control systems, etc. | C51: 3.3 | D51: 2500 | E51: 5000 | F51: Rate-SubGroup row 32 | H51: =D51*'Currency-Conversion'!$C$10 -> 7.6596986e+09 | I51: =E51*'Currency-Conversion'!$C$10 -> 1.5319397e+10
A52: 32 | B52: 01.4.4 Water intake and off-site installations: penstocks, gates, trash racks, weir installations and the like | C52: 3.3 | D52: 2500 | E52: 5000 | F52: Rate-SubGroup row 33 | H52: =D52*'Currency-Conversion'!$C$10 -> 7.6596986e+09 | I52: =E52*'Currency-Conversion'!$C$10 -> 1.5319397e+10
A53: 33 | B53: 01.5.1 Transformer stations — power transformer, phase compensators, cooling control, capacitors, rectifier banks — 30 to 150 MVA | C53: 3.15 | D53: 2500 | E53: 5000 | F53: Rate-SubGroup row 34 | H53: =D53*'Currency-Conversion'!$C$10 -> 7.6596986e+09 | I53: =E53*'Currency-Conversion'!$C$10 -> 1.5319397e+10
A54: 34 | B54: 01.5.1 Transformer stations — power transformer, phase compensators, cooling control, capacitors, rectifier banks — 150 to 300 MVA | C54: 3.4 | D54: 2500 | E54: 5000 | F54: Rate-SubGroup row 35 | H54: =D54*'Currency-Conversion'!$C$10 -> 7.6596986e+09 | I54: =E54*'Currency-Conversion'!$C$10 -> 1.5319397e+10
A55: 35 | B55: 01.5.1 Transformer stations — power transformer, phase compensators, cooling control, capacitors, rectifier banks — above 300 MVA | C55: 3.65 | D55: 5000 | E55: 10000 | F55: Rate-SubGroup row 36 | H55: =D55*'Currency-Conversion'!$C$10 -> 1.5319397e+10 | I55: =E55*'Currency-Conversion'!$C$10 -> 3.0638794e+10
A56: 36 | B56: 01.5.1 Transformer Stations (power transformer, phase compensators, cooling/control/protection auxiliaries, capacitors, rectifier banks) - P | C56: 2.9 | D56: 1000 | E56: 2500 | F56: Rate-SubGroup row 37 | H56: =D56*'Currency-Conversion'!$C$10 -> 3.0638794e+09 | I56: =E56*'Currency-Conversion'!$C$10 -> 7.6596986e+09
A57: 37 | B57: 01.5.2 Switchgear installations (circuit breakers, control/protection equipment, line feeders) up to 60 kV | C57: 2.7 | D57: 1000 | E57: 2500 | F57: Rate-SubGroup row 38 | H57: =D57*'Currency-Conversion'!$C$10 -> 3.0638794e+09 | I57: =E57*'Currency-Conversion'!$C$10 -> 7.6596986e+09
A58: 38 | B58: 01.5.2 Switchgear installations (circuit breakers, control/protection equipment, line feeders) — 60 kV to 500 kV | C58: 2.85 | D58: 1000 | E58: 2500 | F58: Rate-SubGroup row 39 | H58: =D58*'Currency-Conversion'!$C$10 -> 3.0638794e+09 | I58: =E58*'Currency-Conversion'!$C$10 -> 7.6596986e+09
... A171: 151 | B171: 19.3 Poultry farms (rearing hatcheries) and similar installations | C171: 3.3 | D171: 1000 | E171: 2500 | F171: Rate-SubGroup row 152 | H171: =D171*'Currency-Conversion'!$C$10 -> 3.0638794e+09 | I171: =E171*'Currency-Conversion'!$C$10 -> 7.6596986e+09

Sheet Rate-BINARY
A1: Coverage Item | B1: Option (select in Data sheet) | C1: Rate Loading (‰) | D1: Applicable On | E1: EAR Reference | F1: Notes / Swiss Re Guidance
A2: Hot Testing / Commissioning | B2: Yes — included | C2: from Ref.Rate | D2: Testing rate (col F Hot_test in Rate-SubGroup) | E2: Sec 3.3.2 | F2: Standard 4-week commissioning period included in erection rate
A3: Hot Testing / Commissioning | B3: Not included | C3: 0 | D3: N/A | E3: Sec 3.3.2 | F3: If no commissioning/testing, testing rate excluded
A4: Manufacturer's Risk (Defect Material/Workmanship) | B4: Yes — 1-3 mths | C4: 5% of Ref.Rate | D4: Per month of testing/maint | E4: Sec 6.1.1 | F4: 5% × Ref.Rate added per month; Ref.Rate from Rate-SubGroup col G
A5: Manufacturer's Risk (Defect Material/Workmanship) | B5: Yes — 4-6 mths | C5: 7.5% of Ref.Rate | D5: Per month | E5: Sec 6.1.1
A6: Manufacturer's Risk (Defect Material/Workmanship) | B6: Yes — 7-12 mths | C6: 10% of Ref.Rate | D6: Per month | E6: Sec 6.1.1
A7: Manufacturer's Risk (Defect Material/Workmanship) | B7: Not included | C7: 0 | D7: N/A | E7: Sec 6.1.1 | F7: Without defect coverage: reduce basic rate by 5% × Ref.Rate
A8: Manufacturer's Risk (Defective Design) | B8: Yes — 1-3 mths | C8: 5% of Ref.Rate | D8: Per month | E8: Sec 6.1.2 | F8: Same scale as defective material/workmanship
A9: Manufacturer's Risk (Defective Design) | B9: Yes — 4-6 mths | C9: 7.5% of Ref.Rate | D9: Per month | E9: Sec 6.1.2
A10: Manufacturer's Risk (Defective Design) | B10: Yes — 7-12 mths | C10: 10% of Ref.Rate | D10: Per month | E10: Sec 6.1.2
A11: Manufacturer's Risk (Defective Design) | B11: Not included | C11: 0 | D11: N/A | E11: Sec 6.1.2
A12: Visits Maintenance (6.2.1) | B12: Yes — 12 months | C12: 5-7.5% of Ref.Rate | D12: Total period | E12: Sec 6.2.1 / 9 | F12: 5% light industry; 7.5% power/chemical/heavy industry
A13: Visits Maintenance (6.2.1) | B13: Not included | C13: 0 | D13: N/A | E13: Sec 6.2.1
A14: Extended Maintenance (6.2.2) | B14: Yes — 12 months | C14: 7.5-12.5% of Ref.Rate | D14: Total period | E14: Sec 6.2.2 / 9 | F14: 7.5% light; 12.5% power/chemical/heavy
A15: Extended Maintenance (6.2.2) | B15: Not included | C15: 0 | D15: N/A | E15: Sec 6.2.2
A16: Expediting Costs (5.3) | B16: Yes — with limit | C16: 5-10% of works rate | D16: On total SI | E16: Sec 5.3 p.109 | F16: Limit per event ≈ 20% of expected average claim
A17: Expediting Costs (5.3) | B17: Not included | C17: 0 | D17: N/A | E17: Sec 5.3
A18: Air Freight Costs (5.4) | B18: Yes — <2000 miles | C18: 5 | D18: On aggregate limit | E18: Sec 5.4 p.109 | F18: Max aggregate limit ≈ 1% of SI
A19: Air Freight Costs (5.4) | B19: Yes — >2000 miles | C19: 5-20 | D19: On aggregate limit | E19: Sec 5.4 | F19: Proportional increase above 5‰
A20: Air Freight Costs (5.4) | B20: Not included | C20: 0 | D20: N/A | E20: Sec 5.4
A21: Clearance of Debris (5.2) | B21: Yes — limit ≤100k | C21: 0 | D21: Standard inclusion | E21: Sec 5.2 | F21: Up to 100,000 c-units: nil additional rate
A22: Clearance of Debris (5.2) | B22: Yes — limit >100k | C22: Equal to erection rate | D22: On limit per event | E22: Sec 5.2 | F22: Max 1 million c-units; rate = overall erection/testing rate
A23: Clearance of Debris (5.2) | B23: Not included | C23: 0 | D23: N/A | E23: Sec 5.2
A24: Storage Risk — Pre-Erection (5.5) | B24: Yes — with limit | C24: 0.1 | D24: Per month on value stored | E24: Sec 5.5 p.109 | F24: Minimum 0.1‰/month on value stored; fire/PoN measures may be required
A25: Storage Risk — Pre-Erection (5.5) | B25: Not included | C25: 0 | D25: N/A | E25: Sec 5.5
A26: Inland Transit (6.5) | B26: Yes — with limit | C26: ≥1‰ | D26: On total value transported | E26: Sec 6.5 p.111 | F26: Marine specialist rate; min 1‰; not normally covered under EAR policy
A27: Inland Transit (6.5) | B27: Not included | C27: 0 | D27: N/A | E27: Sec 6.5
A28: Project Period Extension (3.3.5) | B28: Extended | C28: (Overall rate / months) × 1.25 | D28: Per extra month | E28: Sec 9 / 3.3.5 | F28: Fraction of month = full month; applies to erection extension
A29: Project Period Extension (3.3.5) | B29: No extension | C29: 0 | D29: N/A | E29: Sec 3.3.5
A30: Used / Second-Hand Machinery (2.6) | B30: Yes — included | C30: Loading per underwriter | D30: On affected SI | E30: Sec 2.6 | F30: Rates in guide are for new/proven design; loading required for used equipment
A31: Used / Second-Hand Machinery (2.6) | B31: Not applicable | C31: 0 | D31: N/A | E31: Sec 2.6
A32: Cross Liability (6.3) | B32: Yes — included | C32: 35% of total TPL premium | D32: Total TPL prem | E32: Sec 6.3 / B.5 | F32: Min 15% if no plant/equipment/storage exposure; see Rate-TPL B.5
A33: Cross Liability (6.3) | B33: Not included | C33: 0 | D33: N/A | E33: Sec 6.3
A34: Third Party Liability (5.6) | B34: Yes — with limit | C34: See Rate-TPL B.1 | D34: On contract value | E34: Sec 5.6 / Table 20 | F34: Rate per risk category (I/II/III) × surroundings (a/b/c)
A35: Third Party Liability (5.6) | B35: Not included | C35: 0 | D35: N/A | E35: Sec 5.6

Sheet Rate-Region
A1: ⚠ DEPRECATED / غیرفعال — این شیت پیش‌تر هم غیرفعال بود (طبق یادداشت داخلی خودش). اکنون کاملاً جایگزین شده با 'Rate-EQ-SwissRe' که جدول E واقعی سوئیس‌ری را از متن مبدأ بازسازی می‌کند (نه تقریب خطی E/3 که این شیت به‌عنوان فرض موقت اعلام کرده بود).
A3: Province / Region (Iran) | B3: EQ Zone (A-E) | C3: Monthly EQ Rate (‰ / month) | D3: Factor E (E1×E2=3) | E3: Annual EQ Rate (× months) | F3: Notes
A4: Tehran — Northern / fault zones (Rey, Shemiran) | B4: A | C4: 0.064 | D4: 3 | E4: 12-24 mths | F4: Zone A catastrophic; near North Tehran Fault
A5: Tehran — Southern, Alborz, Markazi, Kerman | B5: B | C5: 0.026 | D5: 3 | E5: 12-24 mths | F5: Zone B very heavy
A6: Sistan-Baluchestan (Chabahar area) | B6: B | C6: 0.026 | D6: 3 | E6: 12-24 mths | F6: Zone B per seismic map
A7: Fars, East Azerbaijan | B7: C | C7: 0 | D7: 3 | E7: — | F7: Zone C heavy; E=3 → no loading (threshold E≥6 for Zone C)
A8: Mazandaran, Golestan, Gilan | B8: C | C8: 0 | D8: 3 | E8: — | F8: Zone C; coastal/Alborz — verify site-specific
A9: Hormozgan, Hamadan, Yazd | B9: C | C9: 0 | D9: 3 | E9: — | F9: Zone C
A10: Khorasan Razavi, Qazvin | B10: C | C10: 0 | D10: 3 | E10: — | F10: Zone C
A11: Isfahan, Khuzestan, Markazi | B11: D | C11: 0 | D11: 3 | E11: — | F11: Zone D medium; E=3 → no loading (threshold E≥12.5)
A12: Qom, Semnan, Zanjan, Ardabil | B12: D | C12: 0 | D12: 3 | E12: — | F12: Zone D
A13: Kermanshah, Kurdistan, Ilam | B13: D | C13: 0 | D13: 3 | E13: — | F13: Zone D
A14: Lorestan, Bushehr, Chaharmahal | B14: D | C14: 0 | D14: 3 | E14: — | F14: Zone D
A15: West Azerbaijan, Kohgiluyeh | B15: D | C15: 0 | D15: 3 | E15: — | F15: Zone D
A16: North Khorasan
A17: South Khorasan — central parts | B17: E | C17: 0 | D17: 3 | E17: — | F17: Zone E low; no EQ loading required regardless of E factor
A18: EQ method (as implemented): Loading(permille) = monthly base rate (this table, calibrated at reference E=3) x (E/3) x project months, where E = E1 (plant sensitivity 1-4) x E2 (structure 1-5). Applied only if zone threshold met: A/B always; C if E>=6; D if E>=12.5; E never. NOTE: the full Swiss Re zone x E earthquake table is not present in this workbook, so the (E/3) linear scaling from the E=3 anchor is an explicit ASSUMPTION - verify against the original Swiss Re EQ table before binding. Zones C/D/E currently carry a 0 base rate here, so they yield 0 regardless of E.

Sheet Currency-Conversion
A1: تبدیل C-Unit (دلار ۱۹۹۷) به ریال ۱۴۰۵ — مبنای واحد پولی کل کاربرگ
A3: ۱) نرخ ارز نیمایی (ریال به ازای ۱ دلار آمریکا)
A4: نرخ نیمایی امروز | C4: 1480135 | D4: ⚠ ورودی — هر بار قبل از محاسبه، این عدد را با نرخ نیمایی روز (سامانه نیما / سنا) به‌روزرسانی کنید. عدد فعلی نمونه از تیر ۱۴۰۵ است، نه نرخ لحظه‌ای.
A6: ۲) ضریب تعدیل تورمی دلار آمریکا، ۱۹۹۷ ← ۲۰۲۶
A7: نسبت CPI-U آمریکا (۲۰۲۶ ÷ ۱۹۹۷) | C7: 2.07 | D7: مبنا: CPI-U میانگین ۱۹۹۷≈۱۶۰.۵ و برآورد اوایل ۲۰۲۶≈۳۳۲ (بر اساس روند BLS). تخمین مهندسی معقول، نه رقم رسمی دقیق این ماه؛ برای دقت بالاتر: bls.gov/data/inflation_calculator.htm
A9: ۳) ضریب نهایی تبدیل — هر ۱ c-unit معادل چند ریال ۱۴۰۵
A10: ضریب نهایی (ریال به ازای هر c-unit) | C10: =C4*C7 -> 3063879.4 | D10: نرخ نیمایی × ضریب تورمی. تمام سلول‌های پولی کاربرگ از همین یک سلول تغذیه می‌شوند.
A12: ۴) آستانه‌های عددی سوئیس‌ری که مستقیم در فرمول‌های شیت Data استفاده می‌شوند
A13: شرح آستانه | B13: مقدار اصلی (c-unit) | C13: معادل ریالی (فرمول) | D13: کجا استفاده می‌شود
A14: سقف معافیت رفع نخاله (فعال‌سازی نرخ) | B14: 100000 | C14: =B14*$C$10 -> 306387945000 | D14: Data!E39 — اگر سقف واردشده کمتر باشد، حق‌بیمه صفر است
A15: حداقل فرضی حق‌بیمهٔ MD (پیش‌فرض در نبود ردیف) | B15: 500 | C15: =B15*$C$10 -> 1.5319397e+09 | D15: Data!E69 — کف‌ محافظه‌کارانهٔ آخر، فقط اگر زیرگروه پیدا نشود
A16: سقف پوشش اموال مجاور (فقط مرجع، هنوز در فرمول اعمال نشده) | B16: 5000000 | C16: =B16*$C$10 -> 1.5319397e+13 | D16: Rate-Asset — یادداشت مرجع، آماده برای اعتبارسنجی آینده
A17: سقف پوشش رفع نخاله (فقط مرجع، هنوز در فرمول اعمال نشده) | B17: 1000000 | C17: =B17*$C$10 -> 3.0638794e+12 | D17: یادداشت مرجع، آماده برای اعتبارسنجی آینده
A18: بازهٔ سقف کل TPL — ۰.۵ میلیون c-unit | B18: 500000 | C18: =B18*$C$10 -> 1.5319397e+12 | D18: Data!E46 — آستانهٔ اول جدول ضریب سقف TPL
A19: بازهٔ سقف کل TPL — ۱ میلیون c-unit | B19: 1000000 | C19: =B19*$C$10 -> 3.0638794e+12 | D19: Data!E46
A20: بازهٔ سقف کل TPL — ۲ میلیون c-unit | B20: 2000000 | C20: =B20*$C$10 -> 6.1277589e+12 | D20: Data!E46
A21: بازهٔ سقف کل TPL — ۴ میلیون c-unit | B21: 4000000 | C21: =B21*$C$10 -> 1.2255518e+13 | D21: Data!E46
A22: بازهٔ سقف کل TPL — ۶ میلیون c-unit | B22: نگهداری ساده — مدت (ماه) | C22: =B22*$C$10 -> #VALUE! | D22: Data!E46
A23: بازهٔ سقف کل TPL — ۸ میلیون c-unit | B23: نگهداری گسترده — مدت (ماه) | C23: =B23*$C$10 -> #VALUE! | D23: Data!E46
A24: بازهٔ سقف کل TPL — ۱۰ میلیون c-unit | B24: 10000000 | C24: =B24*$C$10 -> 3.0638794e+13 | D24: Data!E46
D27: سایت ایزوله / حومه / مرکز شهر
C48: 0
C49: 0.1

Sheet Rate-Asset
A1: Existing Property Option | B1: Rate on Limit (‰ per event) | C1: Max Limit (c-units) | D1: Notes / EAR Reference | E1: Max Limit (﷼)
A2: Yes — Existing property, WITH explosion risk | B2: 15 | C2: 5000000 | D2: EAR Sec 5.1 p.109 / p.34. Rate 15‰ on limit per event. Limit ≤ c-units 5,000,000 or in reasonable relation to TCV. | E2: =C2*'Currency-Conversion'!$C$10 -> 1.5319397e+13
A3: Yes — Existing property, WITHOUT explosion risk | B3: 5 | C3: 5000000 | D3: EAR Sec 5.1 p.109 / p.34. Rate 5‰ on limit per event. | E3: =C3*'Currency-Conversion'!$C$10 -> 1.5319397e+13
A4: Not included — existing property not covered | B4: 0 | C4: 0 | D4: No additional premium. Default position. | E4: =C4*'Currency-Conversion'!$C$10 -> 0

Sheet Changelog
A1: تاریخ | B1: تغییر | C1: منبع
A2: 2026-06-28 | B2: افزودن 115 مورد بیمهٔ جدید (دسته‌بندی‌های اندازه/نوع) به شیت Rate-SubGroup زیر ردیف ۳۸ (ردیف‌های 39 تا 153). | C2: Swiss Re EAR Rating Guide (Section 10 white tables) via EAR_Iran_Rating_Database.xlsx
B3: ۳۷ ردیف اصلی بدون تغییر حفظ شد؛ فقط جدول‌های سفید Complete Plant با نرخ واقعی افزوده شد. ماشین‌های منفرد (جدول آبی) و TPL (جدول ۲۰) ساختار نرخ متفاوت دارند و افزوده نشدند.
A4: 2026-06-29 | B4: v3 — Major rebuild: (1) Rate-BINARY, Rate-Region, Rate-Asset fully translated to English with real Swiss Re EAR values and rate loadings. (2) Rate-Clauses new sheet: all 30 EAR endorsements/clauses with rate impacts. (3) Data sheet fully rebuilt in English: Group→Sub-group cascading dropdown (INDIRECT-based), TPL rate calculation (auto from risk category × surroundings × limit), earthquake loading, all extensions in dropdown rows, 8-row multi-clause section (EAR_Clauses named range), deductibles read-only display, and summary/total row. (4) Named ranges fixed after column insert. (5) All 37 original Rate-SubGroup rows renamed to EAR standard English names. | C4: Claude (Anthropic) — EAR Swiss Re Rating Guide
A5: 2026-06-29 | B5: v5 — Bug fixes & completion: (1) C5 dropdown: I5 rebuilt with correct U+2014 em-dash SUBSTITUTE chain; EAR_Groups sorted numerically 01-19; old Persian named ranges removed. (2) E12 hot-test formula uses exact em-dash string match with C12 default. (3) C6 validation: 1-120 months with error message. (4) New section I: validation checks (V1-V4) for duration, EQ exclusion conflict, hot-test consistency, sub-group lookup. (5) New section J: full premium engine — SI input, technical rate, UW adjustment, office rate, min premium check, gross MD premium, TPL premium, brokerage, tax, total premium payable. (6) H section total row relabelled as Indicative Gross Rate. (7) C8 label clarified as Soil/Ground Type. | C5: Claude (Anthropic) v5
A6: 2026-06-29 | B6: v6 - Full repair & rebuild. STRUCTURAL: Rate-SubGroup re-sorted by group/sub-code so the lookup key (col A, cleaned full EAR names) is row-aligned with the rates - fixes the critical defect where 150 of 152 sub-groups returned another sub-group rates; helper key cols replaced by one aligned key + a 19-row group list (col N); all EAR_ named ranges rebuilt as contiguous per-group A-slices; dead Sheet2 removed. FORMULAS: every XLOOKUP replaced with INDEX/MATCH (version-safe; the bare xlookup spelling produced a name error in MS Excel that IFERROR silently turned into zero); Data sheet rebuilt from scratch to remove orphaned merged ranges and broken references. PRICING: TPL is calculated once and wired live to Rate-TPL (base rate, limit factor and minimum premium via INDEX/MATCH, no hardcoded grid) and removed from the MD rate so it is no longer double counted; cross-liability is gated on selection and applied once as 35 percent of the TPL premium; Section-C extensions rebuilt as real calculators (Manufacturers Risk by test/maint months x percent-of-Reference-Rate band; Visits and Extended Maintenance by months x light/heavy percent; Expediting as percent-of-works-rate; Air Freight, Storage, Inland Transit, Debris>100k and Existing Property priced as premiums in c-units on their own limit/value rather than per-mille on the SI); earthquake rebuilt to the Swiss Re E = E1 x E2 method with zone thresholds and an earthquake-exclusion toggle. VALIDATION: checks now detect real failures - V1 verifies the sub-group resolved to a numeric rate rather than merely that a key exists, plus floor, duration, EQ-exclusion, TPL-input and Sum-Insured checks; the advisory-endorsement dropdowns were moved onto the correct columns. PREMIUM: Gross = MD + add-ons + TPL; tax is applied to gross (not to premium net of brokerage); net-to-insurer and total-payable-by-insured are shown separately. ASSUMPTIONS: earthquake (E/3) linear scaling from the E=3 anchor because the full Swiss Re zone x E table is not in the workbook; the indicative minimum premium uses the general-excess value as an order-of-magnitude floor only (not an authoritative Swiss Re minimum); maintenance light vs heavy is a user toggle. | C6: Independent audit & rebuild (Claude)
A7: 2026-07-19 | B7: v7 — Earthquake mechanism replaced with real Swiss Re method (Claude audit). BEFORE: Data!E18 = VLOOKUP(province, 'Rate-Hazard', flat 1.00/1.15 factor, unsourced); Data!E20 = (erection rate + testing rate) x (loading factor - 1), applied once regardless of project duration or equipment/structure sensitivity; EQ1/EQ2/EQ3 (E1, E2, combined E) were hardcoded as 'DEPRECATED - superseded by province factor'. AFTER: Data!C7 now selects a city/town from the Standard 2800 (4th ed., 1393) Appendix 1 classification (489 county-seat-level points, sheet 'Hazard-Cities-2800', each row cited to its source scan page); Data!C15/C16 are live inputs for plant sensitivity (E1, Table E1, 4 classes) and structure resistance (E2, Table E2, 6 classes), both reconstructed from the original EAR Rating Guide OCR text; Data!E17 = E1xE2 (real combined factor, no longer hardcoded); Data!E18 = Zone (A-E) via a user-approved mapping table (خیلی زیاد->B, زیاد->C, متوسط->D, کم->E; Zone A intentionally unused for Iran - confidence: medium, no PGA equivalence found in source for Swiss Re zone letters); Data!G17/G18 (helper cells) round E up to the nearest tabulated value (conservative assumption, not specified in source - flagged for user confirmation) and look up the monthly per-mille rate from the reconstructed Table E (sheet 'Rate-EQ-SwissRe', 13x5 grid, OCR-sourced with high confidence for the numeric progression); Data!E20 = monthly rate x project duration in months (C6) - matches the source text's explicit monthly-accrual method (EAR Rating Guide Sec 4.3.1), instead of a single flat multiplier. RATIONALE: the old 1.00/1.15 factors had no traceable source (the intended source file 'EAR_Iran_Natural_Hazard_LoadingFactor.xlsx' was never uploaded and was later deemed unreliable by the user); the new mechanism is fully traceable to (a) the original Swiss Re EAR Rating Guide OCR text for the E1/E2/Table-E structure, and (b) the official Standard 2800 4th edition (1393) Appendix 1 for city-level classification. OPEN ASSUMPTIONS carried forward for user confirmation: (1) round-UP rule for non-tabulated E values; (2) Zone A left unassigned for all of Iran; (3) 'Rate-Hazard' and 'Rate-Region' sheets kept but marked deprecated rather than deleted, for audit trail - delete on request. | C7: Claude (Anthropic) - earthquake mechanism rebuild, v7
A8: 2026-07-19 | B8: v8 - Province-then-City cascading selector added for earthquake location (user request). BEFORE: Data!C7 was a single flat dropdown of 489 'City - Province' combined strings (Hazard-Cities-2800!B2:B490), hard to navigate. AFTER: Data!C7 = Province dropdown (30 provinces, list from new sheet 'Hazard-Province-Index'); Data!H7 = City/Town dropdown, auto-filtered to the selected province via INDIRECT(I7), where I7 looks up a safe defined-name code (HZP_01..HZP_30) for the chosen province - same INDIRECT-cascading pattern already used for Industry Group (C4) -> Sub-Group (C5) in this workbook. 'Hazard-Cities-2800' was re-sorted by Province then City (was: Persian-alphabetical by city name) so each province's cities form a contiguous block usable as a defined-name range - row order change only, no data change; verified via recalc with zero errors both before and after. Data!E7 (hazard level lookup) now builds its key from BOTH H7 and C7 (=H7&" - "&C7) matched against Hazard-Cities-2800!B, so the 3 duplicate city names across provinces (آستانه, خور, فیروزآباد) resolve to the correct province's row - tested explicitly for both 'خور' instances (اصفهان -> متوسط, یزد -> متوسط; both resolved via the correct row, confirmed by checking the underlying row, not merely matching output value). | C8: Claude (Anthropic) - cascading Province->City selector, v8
A9: 2026-07-19 | B9: v9 - Province and City moved to two separate stacked rows (user request), instead of same-row helper columns. BEFORE: Data row 7 held both Province (C7) and City (H7, same row, off to the side) in one row. AFTER: Data!C7 = Province (unchanged position); a NEW Data row 8 = City/Town, auto-filtered to the Province via INDIRECT($H$8) where H8 looks up the safe defined-name code (HZP_01..HZP_30) for the selected province - same cascading pattern as before, now laid out as two stacked parameter rows like every other input in this sheet. Data!E7 (hazard level) now keys on C8&" - "&C7 instead of the old H7&" - "&C7. STRUCTURAL: inserting this row required shifting every formula and merged header range at old row 8 and below by +1 throughout the Data sheet (rows 8-83 -> 9-84). This was done with a scripted row-reference shift (protecting cross-sheet references), not manual retyping. QA NOTE (transparency): openpyxl's insert_rows() silently dropped the B/D/E/F content of 8 rows during the physical shift - specifically every row that sat directly before a merged section-header row (old rows 13,23,32,39,50,56,63,76, i.e. the last content row of each lettered section, including the MD TECHNICAL RATE formula at what is now row 64). This was caught by a full before/after audit of every row (not assumed clean from a green recalc) and manually restored with correctly re-numbered formulas. Root cause: merged-range metadata was not un-merged before calling insert_rows, so the shifted values landed on cells still flagged as non-top-left merged cells and were discarded. Fully verified afterward: recalc = 0 errors, MD Technical Rate chain (D64 -> E68 -> E70 -> E73 -> E75/E77) manually checked against hand arithmetic, and both known duplicate-city cases (Isfahan/Khur, Yazd/Khur) tested to confirm the Province+City two-key lookup resolves to the correct row in each case. | C9: Claude (Anthropic) - Province/City stacked rows + insert_rows data-loss fix, v9
A10: 2026-07-19 | B10: v10 - Correction batch from full cell-by-cell Swiss Re audit (Claude). All fixes verified against original OCR source text, not the derivative database file. Rate-SubGroup (152->151 rows): (1) FIXED 01.5.4 'Gas filled cables' Code1 1.78->1.70; (2) FIXED 01.6.1 'Waterworks' Min.Rate 3.3->3.00; (3) FIXED 18.2 'Medical/lab equipment' - was showing 18.1's values (1.4/0.1/0.075/0.05/0.55/4) instead of its own (1.7/0.1/0.075/0.05/0.9/5) - merged the two duplicate 18.2 rows into one correct row; (4) REMOVED duplicate rows 06.4.1 and 13.6.1 (exact copies of 06.4/13.6, not present as separate codes in source); (5) ADDED 2 missing rows for 01.5.1 Transformer Stations 150-300 MVA (Ref.Rate 6) and above 300 MVA (Ref.Rate 7) - previously only the two smaller size bands existed. All 19 EAR_xx Group->Sub-Group defined names rebuilt from scratch to match new row boundaries; Data!E10/E11/E12/E14/E69 range references updated from $153 to $152; both changes verified via recalc (0 errors) and live cascading-dropdown tests (new transformer row + last group in table, both compute correctly). Rate-IndividualMachines (87->127 rows): ADDED 41 missing individual-machine rate rows that exist in the Swiss Re source but were absent, replaced by a generic 'use white table X' placeholder that did not match the source's actual guidance for these groups: Group 05 Metal Industry (+9 rows), 07 Timber (+4), 09 Printing (+6), 12 Plastic & Rubber (+5), 13 Food Vegetable (+12, incl. 2-variant 13.0.5), 15 Food Refrigeration (+6). No Data-sheet formula references this sheet, so this addition carries zero downstream risk. Rate-Deductibles D.3: fully regenerated (152->151 rows) from the corrected Rate-SubGroup to stay in sync (this table is a static, non-live snapshot by design - flagged for periodic re-sync if Rate-SubGroup changes again). D.1 and D.2 required no changes (both were already 100% correct against source). Rate-Clauses: (1) FIXED data-entry bug - C6 'Type' column had a stray number (15) instead of text ('Extension'); (2) FIXED Contractors' Plant & Equipment rate 7-10‰/5-7‰ -> 8-10‰/6-7‰ per EAR Rating Guide Sec.9 point 5.7; (3) Riot & Strike erection-period '50%' figure could not be verified in the uploaded source after two independent searches - left as-is but flagged in-cell as unverified/insufficient evidence rather than silently kept or invented a replacement. VERIFICATION: full structural re-scan of both rebuilt sheets confirmed zero gaps/empty rows; live formula tests at both the new transformer row and the last row of the table (group 19) matched hand calculation exactly; earthquake mechanism (v7-v9) and all other sheets confirmed untouched and unaffected. | C10: Claude (Anthropic) - correction batch from full audit, v10
A11: 2026-07-20 | B11: v11 - C-unit (1997 USD) converted to Iranian Rial (1405) as the base currency for all calculations and minimums, per user request. METHODOLOGY (new sheet 'Currency-Conversion'): Step 1 - US CPI-U inflation adjustment 1997->2026, factor ~2.07 (documented, editable, source: BLS trend, 1997 avg CPI-U ~160.5 vs early-2026 estimate ~332 - approximate, recommend re-checking against bls.gov calculator for precision). Step 2 - NIMA USD/IRR exchange rate (editable input cell, user updates each time from sana.ir/NIMA; seeded with ~1,480,135 IRR/USD from mid-Tir 1405 as a placeholder). Combined factor = inflation x FX, computed live in one cell (C10) that everything else references - changing either input auto-recalculates the whole workbook. SCOPE (only genuine currency fields were converted; ‰ rates and % loadings were NOT touched since they are dimensionless): added parallel (﷼) columns next to every existing (c-units) column in Rate-SubGroup (Gen.Excess, AoG/Maint Excess), Rate-IndividualMachines (same), Rate-Deductibles D.3 (same), Rate-TPL (3x3 minimum-premium grid), and Rate-Asset (existing-property cap) - original c-unit columns preserved untouched for audit trail. LIVE FORMULA CHANGES in Data sheet (the only 6 places a currency number was hardcoded or looked up for a real calculation): E39 debris threshold (100,000 c-units -> Rial equivalent via Currency-Conversion!C14); E46 TPL limit-adaptation lookup (hardcoded {0.5,1,2,4,6,8,10} array -> Currency-Conversion!C18:C24 Rial-equivalent range); E49 TPL minimum-premium floor (repointed from Rate-TPL!F4:H6 to new Rial columns I4:K6); E69 indicative minimum premium (repointed from Rate-SubGroup!I to new column K, fallback default 500->Currency-Conversion!C15). All monetary input/output cell labels changed from '(c-units)' to '(﷼)' throughout Data sheet (B23-B77 range). Example default values updated to Rial scale: C66 Sum Insured 10,000,000 c-units -> 30,638,794,500,000 ﷼; C44 TPL Limit 2,000,000 c-units -> 6,127,758,900,000 ﷼ (both at the seed conversion factor - user should overtype with their actual project figures). KNOWN LIMITATION: 13 rows in Rate-SubGroup (and their D.3 mirror) have AoG/Maint excess values expressed per unit of capacity (e.g. '150/MW (min 10,000)') rather than a plain number - these could NOT be auto-converted by formula (text, not numeric) and are flagged in-cell with the conversion factor shown for manual calculation; none of these 13 rows feed a live Data-sheet formula, so this does not affect any automated calculation, only manual underwriter reference. VERIFICATION: full recalc = 0 errors across 898 formulas; manually hand-checked the entire premium chain (E70 Gross MD, E49/E51 TPL, E73 Gross Premium, E75 Net, E77 Total Payable) against the new Rial figures - all reconcile exactly; tested debris threshold crossing with a live value above/below the new Rial threshold; confirmed the per-MW text-preservation fallback displays correctly without breaking recalc. OPEN ITEMS for user: (1) NIMA rate in Currency-Conversion!C4 is a seed value from mid-Tir 1405 - update before relying on any output; (2) CPI factor in C7 is an engineering approximation - refine via bls.gov if higher precision is needed; (3) user chose NIMA (not free-market or official) rate per explicit instruction. | C11: Claude (Anthropic) - C-unit to Rial conversion, v11
A12: 2026-07-20 | B12: v12 - Added Riot & Strike input (was missing entirely) and removed Section H 'Advisory Endorsements' (user judged it non-functional - condition-only checkboxes with no rate impact, cluttering the sheet). ADDED: Data!C33 = Riot and Strike (6.4) Fire Dept/FOC riot-and-strike rate (‰) - user-entered, since Swiss Re does NOT tabulate this rate itself, it must be sourced from the local fire insurance market; Data!C34 = period basis dropdown (Erection period / Testing-Commissioning period); Data!E34 = computed loading (rate x 100% if testing, x 50% if erection - the 50% figure is flagged in-cell as unverified/insufficient evidence per the earlier audit, not silently presented as confirmed). This loading now correctly feeds into the Extension Rate-Loadings subtotal (E35) and the MD Technical Rate (D60), tested end-to-end. REMOVED: Section H 'Advisory Endorsements' (old rows 52-57: 4 condition-only checkboxes - Debris/Silt/Erosion/Landslip, Visits Maintenance, Exclusion of EQ Damage, Exclusion of Damage to Crops - plus its EAR_Clauses-driven dropdown). None of these carried a rate impact or fed any formula, so removal has zero calculation effect. METHOD: given the net structural change (+2 rows for Riot&Strike, -6 rows for Section H, non-uniform), the entire Data sheet was extracted to Python, an explicit old-row-to-new-row mapping was built and applied to every formula (protecting cross-sheet references), then the sheet was fully cleared and rewritten from the corrected dataset - avoiding openpyxl's insert_rows/delete_rows entirely (both have caused silent data loss in this workbook before, see v9 changelog). VERIFICATION: recalc = 0 errors across 899 formulas; full structural re-scan found zero orphaned/empty rows; live formula tests confirmed both Riot & Strike period options compute correctly (erection = rate x 0.5, testing = rate x 1.0) and propagate correctly through E35 -> D59 -> D60 -> downstream premium; confirmed no trace of 'ADVISORY ENDORSEMENTS' text remains anywhere in the sheet; all merged section-header ranges and data validations (including the cascading Group->Sub-Group and Province->City dropdowns) re-verified intact at their new row positions. | C12: Claude (Anthropic) - Riot & Strike input added, Section H removed, v12
A13: 2026-07-20 | B13: v13 - New user-friendly front-end sheet 'محاسبه-ساده' (Simple-Calc) added, per user request for a much simpler entry point for new/non-expert staff. ARCHITECTURE: the Data sheet's calculation engine (all 899+ formulas) was NOT modified - zero risk to accuracy. Instead, the Simple sheet became the true data-entry surface: all 33 cells in Data that previously held static user-typed values (C4,C5,C6,C7,C8,C12,C16,C17,C20,C23,D23,C27,C28,C29,C30,C31,C32,C33,C34,C38,D38,C39,D39,C40,C41,C44,C45,C46,C50,C62,C63,C70,C72) were converted to one-line formulas pointing at the corresponding Simple-sheet cell (e.g. Data!C4 = ='محاسبه-ساده'!C9). All dropdown validations were moved from Data to the Simple sheet's input cells (including the cascading Group->SubGroup and Province->City INDIRECT dropdowns, which still work correctly since they reference Data!J5 / Data!H8, and those helper cells still compute correctly off Data!C4/C7, which now just happen to be formulas instead of literals). LAYOUT: title bar; a live result box pinned at the top (validation status traffic-light, final MD rate ‰, final total premium ﷼ - both update immediately on any input change, addressing the user's 'see the rate change quickly' requirement); 5 colour-coded sections covering every single input cell that requires a user decision (project specs, amounts, common options, supplementary options - all visible, none collapsed per explicit user instruction, financial settings). Pure computed/intermediate cells (rate build-up steps, EQ factors, TPL sub-calculations, validation detail) were deliberately NOT duplicated here - they remain only in Data, since the user asked to keep only items requiring a decision and drop everything else. VERIFICATION: recalc = 0 errors across 936 formulas; live test changing Province/City to Tehran and EQ sensitivity to max on the Simple sheet correctly propagated through Data (C7 updated, EQ Zone recalculated B, rate rose 4.1->5.675, premium rose accordingly) with the result box updating instantly; status indicator correctly shows green when all 5 validation checks (Data!E75-E80) pass. | C13: Claude (Anthropic) - Simple-Calc front-end sheet, v13
A14: 2026-07-21 | B14: v14–15 — (1) Added TPL master include/exclude toggle: محاسبه-ساده!C18 (پوشش مسئولیت شخص ثالث TPL اصلاً وجود دارد؟, Yes/No, default Yes). Data!I44 links to it; Data!E51 (TPL Premium) returns 0 outright when the toggle = No; Data!E79 (V5) reports "OK (TPL excluded)" instead of flagging category/surroundings. Cross-liability (E52) auto-zeroes since it is 35% of E51. (2) Removed ALL minimum-PREMIUM floors, per explicit user instruction — minimum-RATE floors (E11/E13, and the Rate-TPL ‰ table itself) were NOT touched. BEFORE: Data!E66 = MAX(ROUND(C62*E64/1000,0), E65) — E65 ("Indicative Minimum Premium") was traced to Rate-SubGroup column K, which is actually General Excess (a deductible) converted to Rial, not a real minimum premium — mislabeled floor. AFTER: Data!E66 = ROUND(C62*E64/1000,0), pure SI × office-rate. E65 kept on the sheet as an informational/audit-trail value only — no longer feeds any live calculation. BEFORE: Data!E51 = MAX(ROUND($C$62*E49/1000,0), TPL minimum-premium grid Rate-TPL!I4:K6) — this grid IS an authoritative Swiss Re per-category/surroundings minimum premium (500–4000 c-units, verified against the source PDF B.1 rating table), removed only from the live formula per user instruction; the figures themselves are unchanged on Rate-TPL. AFTER: Data!E51 = ROUND($C$62*E49/1000,0), pure SI × TPL-rate. VERIFIED (LibreOffice recalc, reference scenario: Metal/Paint-factories, 15 months, Qom, SI 20,000,000,000 ﷼, TPL Cat I-a isolated site, no cross-liability, TPL Included=Yes): E66 3,063,879,450 → 82,000,000 ﷼; E51/E53 1,531,939,725 → 4,000,000 ﷼; E73 (Total Payable) 5,055,401,092 → 94,600,000 ﷼. Rate floor E13 confirmed still active at 3.65‰ (unchanged), proving rate-floor logic was not disturbed. IMPORTANT PROCESS NOTE: this revision was rebuilt directly from raw OOXML (not via openpyxl round-trip) because the prior two saves (v14, v15 originally) had silently dropped the three x14-extension list dropdowns on محاسبه-ساده (C10 Project Sub-Group, C12 Province, C13 City/Town) — openpyxl does not round-trip the x14:dataValidations extLst block. All three dropdowns are restored and verified intact in this file. | C14: Claude (Anthropic) - TPL exclusion toggle + minimum-premium floor removal (rebuilt via raw XML to preserve dropdowns), v14–v15
A15: 2026-07-21 | B15: v17 — Added the Entire Project / Individual Machines rating-basis switch (Swiss Re Rating Guide 2.5 + 10.1, blue tables). FINDING THAT PROMPTED THIS: the 'Rate-IndividualMachines' sheet held 108 complete blue-table rate rows but NO formula anywhere in the workbook referenced it — an orphaned sheet, never wired in. Verified by full-text search of every formula in both EAR_Rating.xlsx and EAR_Rating_v13_Simple.xlsx; neither ever contained a rating-basis input. Severity Major, category D (present but never implemented). NEW INPUTS (محاسبه-ساده, new section 6, rows 51-56 — appended after row 49 so NO existing row number shifts): C52 rating basis (Entire Project / Individual Machines, default Entire Project); C53 machine picker (dropdown over the new EAR_Machines defined name, 108 entries); C54 erection months (default 3); C55 testing months (default 1); C56 nature-perils loading for the machine (default No). NEW HELPER DATA: Rate-IndividualMachines columns K:O rows 2-109 hold a contiguous, de-duplicated picker list (label, basic rate, add. erection, add. testing, ref. rate) compacted from the scattered source rows; columns A:J untouched. NEW CALC BLOCK: Data rows 85-93. I86 is the mode flag (M = machine, P = project) derived via SEARCH so no fragile Persian string comparison is used. E91 = blue rate = Basic + MAX(0,MIN(erect,9)-3)*Add.Erect + MAX(0,MIN(test,3)-1)*Add.Test. E92 = blue reference rate. E93 = new validation V7 for the period caps. SWITCH POINTS — exactly five formulas changed, all downstream logic untouched: E12 hot-testing rate -> IF(I86="M",0,<original>) because the blue basic rate already includes 1 month testing (double-count guard); E13 effective erection rate -> IF(I86="M",E91,<original>); E14 reference rate -> IF(I86="M",E92,<original>); D58 earthquake loading -> IF(AND(I86="M",C90="No"),0,E21) per 2.5 'no additional rates for perils of nature unless return period under 10 years' — exposed as a user toggle rather than hard-coded, since much of Iran plausibly meets that exception; E76 validation V2 -> reports OK in machine mode because for individual machines the basic rate IS the minimum rate (2.5), so the white-table floor E11 does not apply. BACKWARD COMPATIBILITY: default C52 = Entire Project => I86 = P => all five formulas evaluate to their original expressions, so existing quotes are bit-identical. Verified by LibreOffice UNO calculateAll() on the reference scenario. NOT IMPLEMENTED — INSUFFICIENT EVIDENCE: the separate large-sum-insured rebate table for individual machines (factors 0.95/0.925/0.90) is present in the source but its c-unit thresholds are garbled in the OCR text; deliberately omitted rather than guessed. ALSO NOT ADDRESSED: per 2.5 the blue basic rate already includes defective material/workmanship cover, so the Manufacturer's-Risk extension (E26/E27 path) would double-count if used in machine mode — left active pending user decision. Built by direct OOXML editing (never openpyxl round-trip) to preserve the x14 extension dropdowns; calcChain.xml omitted and fullCalcOnLoad retained. | C15: Claude (Anthropic) — Entire Project / Individual Machines rating-basis switch, v17
A16: 2026-07-28 | B16: v18 — Restructured the محاسبه-ساده input sheet so the Entire Project / Individual Machines fields follow the same layout as BLOCK 1 of the Data sheet in the updated EAR_Rating.xlsx (v7 5-Block engine). VISUAL/STRUCTURAL CHANGE ONLY — the calculation logic remains the Swiss Re Rating Guide logic implemented in v17, not the template's. NEW SECTION 1 ORDER (mirrors Block 1 fields 1.1-1.8): C9 Project Scope; C10 Industry Group; C11 Project Sub-Group (Entire Project only); C12 Individual Machine (Individual Machines only); C13 Total Project Duration (Entire Project only); C14 Erection Months (machine); C15 Testing Months (machine); C16 Province; C17 City. Labels carry ⟨scope⟩ markers exactly as Block 1 does. The nature-perils toggle, which has no Block 1 equivalent, stays in a slim section 6 at C56. ROW SHIFT: four rows inserted into section 1, so every row from the old 14 onward moved +4. All 39 cross-sheet references in the Data sheet were remapped in a single atomic pass; the 5 merged section headers, the 18 standard data validations and all 3 x14-extension dropdowns (sub-group C11, province C16, city C17) were re-pointed to their new rows and verified intact. New whole-number validations cap C14 at 0-9 and C15 at 0-3. DELIBERATE DIVERGENCES FROM THE TEMPLATE, on Swiss Re grounds — the template's Block 2 rate build-up was NOT copied: (1) The template matches machines on 'Rate-IndividualMachines'!$B$3:$B$87, i.e. bare descriptions. That range contains 8 rows all named 'Other individual machines, not specified elsewhere'. MATCH returns the first hit, so choosing that entry for any of the 7 later industries silently returns the Utilities rate. This workbook keeps matching on the EAR code + description key (unique across all 108 rows) built in v17. (2) The template applies MAX(0,months-3) and MAX(0,months-1) with no upper bound. Swiss Re 2.5 caps erection at 3+6=9 months and testing at 1+2=3 months, so this workbook keeps MIN(...,9) and MIN(...,3) plus validation V7. (3) The template's table covers 66 rated machines (rows 3:87); this workbook's covers all 108. (4) The template comments that individual machines have no minimum-rate floor. Swiss Re 2.5 states the basic rate IS simultaneously the minimum rate; effect is equivalent, wording corrected in V2. BACKWARD COMPATIBILITY: default scope remains Entire Project, and the reference scenario still returns the identical premium. Built by direct OOXML editing, never an openpyxl round-trip. | C16: Claude (Anthropic) — محاسبه-ساده restructured to Block-1 layout; Swiss Re logic retained, v18

Sheet Rate-Hazard
A1: ⚠ DEPRECATED / غیرفعال — این شیت دیگر توسط فرمول‌های شیت Data استفاده نمی‌شود. جایگزین: 'Hazard-Cities-2800' (سطح شهرستان، استاندارد ۲۸۰۰) + 'Rate-EQ-SwissRe' (نگاشت Zone). دلیل کنارگذاری: ضرایب ۱٫۰۰/۱٫۱۵ این شیت منبع مستندی نداشتند (فایل واسطه هرگز آپلود نشد) و روش آن (ضریب ضربی یک‌باره) با روش واقعی سوئیس‌ری (نرخ ماهانه × مدت) ناسازگار بود.
A3: # | B3: Province (Iran) | C3: Recommended Loading Factor | D3: Composite Hazard Score | E3: Technical Justification — Main Driver
A4: 1 | B4: تهران | C4: 1.15 | D4: 3.83 | E4: گسل‌های فعال متعدد (گسل شمال تهران) + فرونشست شدید (تا ۳۱cm/سال در جنوب‌غرب)
A5: 2 | B5: البرز | C5: 1 | D5: 2.83 | E5: مجاورت با کمربند لرزه‌ای تهران + فرونشست بسیار شدید (نظرآباد ۲۷-۲۸cm/سال)
A6: 3 | B6: قم | C6: 1 | D6: 2.78 | E6: زلزله‌خیزی متوسط + عدم پوشش رسمی فرونشست/زمین‌لغزش
A7: 4 | B7: مرکزی | C7: 1 | D7: 2.88 | E7: فرونشست خیلی زیاد (>17cm/سال) در کنار زلزله‌خیزی متوسط
A8: 5 | B8: قزوین | C8: 1 | D8: 2.78 | E8: زلزله‌خیزی متوسط (برون‌یابی) - نیازمند مطالعهٔ اختصاصی استاندارد ۲۸۰۰
A9: 6 | B9: گیلان | C9: 1 | D9: 3.23 | E9: زلزله‌خیزی زیاد + مخاطرهٔ سیل/بارش سنگین شمال کشور
A10: 7 | B10: اردبیل | C10: 1 | D10: 3.33 | E10: زلزله‌خیزی زیاد + فرونشست دشت ویلکیج (وضعیت بحرانی)
A11: 8 | B11: زنجان | C11: 1 | D11: 3.33 | E11: زلزله‌خیزی زیاد + فرونشست دشت‌های استان
A12: 9 | B12: آذربایجان شرقی | C12: 1.15 | D12: 3.88 | E12: زلزله‌خیزی خیلی زیاد (تبریز) + بالاترین نرخ فرونشست کشور (مرند ۱۸.۹cm/سال)
A13: 10 | B13: آذربایجان غربی | C13: 1 | D13: 3.28 | E13: زلزله‌خیزی زیاد (ارومیه، طبق ویرایش ۴ از متوسط به زیاد ارتقا یافت)
A14: 11 | B14: کردستان | C14: 1 | D14: 2.83 | E14: فرونشست زیاد + زلزله‌خیزی متوسط (برون‌یابی)
A15: 12 | B15: همدان | C15: 1 | D15: 2.83 | E15: فرونشست زیاد (دشت کبودراهنگ/فامنین) + زلزله‌خیزی متوسط
... A34: 31 | B34: خراسان جنوبی | C34: 1 | D34: 3.35 | E34: ⚠ تناقض ۱۹۹۷ در برابر امروز: استاندارد۲۸۰۰ زلزله‌خیزی «زیاد» می‌دهد، نقشهٔ سوییس‌ری۱۹۹۷ «Zone E-کم» — نیازمند بازنگری فوری
A35: Source: EAR_Iran_Natural_Hazard_LoadingFactor.xlsx / Hazard_Table, imported 2026-07-08. Replaces the Zone A-E system in 'Rate-Region' (left in place, no longer referenced).

Sheet Hazard-Cities-2800
A1: ردیف | B1: کلید یکتا (برای دراپ‌داون Data!C7) | C1: شهرستان/نقطه جمعیتی | D1: استان | E1: خطر نسبی زلزله (۲۸۰۰) | F1: Zone سوئیس‌ری معادل (مصوب کاربر) | G1: صفحه منبع اسکن | H1: یادداشت
A2: 1 | B2: آذرشهر — آذربایجان شرقی | C2: آذرشهر | D2: آذربایجان شرقی | E2: زیاد | F2: C | G2: ص 3
A3: 2 | B3: اهر — آذربایجان شرقی | C3: اهر | D3: آذربایجان شرقی | E3: متوسط | F3: D | G3: ص 7
A4: 3 | B4: بستان آباد — آذربایجان شرقی | C4: بستان آباد | D4: آذربایجان شرقی | E4: خیلی زیاد | F4: B | G4: ص 9
A5: 4 | B5: بناب — آذربایجان شرقی | C5: بناب | D5: آذربایجان شرقی | E5: متوسط | F5: D | G5: ص 12
A6: 5 | B6: تبریز — آذربایجان شرقی | C6: تبریز | D6: آذربایجان شرقی | E6: خیلی زیاد | F6: B | G6: ص 15
A7: 6 | B7: تسوج — آذربایجان شرقی | C7: تسوج | D7: آذربایجان شرقی | E7: خیلی زیاد | F7: B | G7: ص 15
A8: 7 | B8: جلفا — آذربایجان شرقی | C8: جلفا | D8: آذربایجان شرقی | E8: زیاد | F8: C | G8: ص 16
A9: 8 | B9: زنوز — آذربایجان شرقی | C9: زنوز | D9: آذربایجان شرقی | E9: زیاد | F9: C | G9: ص 27
A10: 9 | B10: سراب — آذربایجان شرقی | C10: سراب | D10: آذربایجان شرقی | E10: زیاد | F10: C | G10: ص 27
A11: 10 | B11: شبستر — آذربایجان شرقی | C11: شبستر | D11: آذربایجان شرقی | E11: خیلی زیاد | F11: B | G11: ص 33
A12: 11 | B12: شرفخانه — آذربایجان شرقی | C12: شرفخانه | D12: آذربایجان شرقی | E12: خیلی زیاد | F12: B | G12: ص 33
A13: 12 | B13: صوفیان — آذربایجان شرقی | C13: صوفیان | D13: آذربایجان شرقی | E13: خیلی زیاد | F13: B | G13: ص 33
... A20: 19 | B20: هشترود — آذربایجان شرقی | C20: هشترود | D20: آذربایجان شرقی | E20: زیاد | F20: C | G20: ص 52
A21: 20 | B21: ورزقان — آذربایجان شرقی | C21: ورزقان | D21: آذربایجان شرقی | E21: زیاد | F21: C | G21: ص 51 | H21: ⚠ شمارهٔ ردیف منبع دوپهلو بود؛ نام/سطح خطر مطمئن است.
A22: 21 | B22: کلیبر — آذربایجان شرقی | C22: کلیبر | D22: آذربایجان شرقی | E22: متوسط | F22: D | G22: ص 39
A23: 22 | B23: ارومیه — آذربایجان غربی | C23: ارومیه | D23: آذربایجان غربی | E23: متوسط | F23: D | G23: ص 6
A24: 23 | B24: اشنویه — آذربایجان غربی | C24: اشنویه | D24: آذربایجان غربی | E24: زیاد | F24: C | G24: ص 6
A25: 24 | B25: بوکان — آذربایجان غربی | C25: بوکان | D25: آذربایجان غربی | E25: متوسط | F25: D | G25: ص 12
A26: 25 | B26: تکاب — آذربایجان غربی | C26: تکاب | D26: آذربایجان غربی | E26: کم | F26: E | G26: ص 15
A27: 26 | B27: خوی — آذربایجان غربی | C27: خوی | D27: آذربایجان غربی | E27: زیاد | F27: C | G27: ص 21
A28: 27 | B28: سردشت — آذربایجان غربی | C28: سردشت | D28: آذربایجان غربی | E28: زیاد | F28: C | G28: ص 28
A29: 28 | B29: سرو — آذربایجان غربی | C29: سرو | D29: آذربایجان غربی | E29: متوسط | F29: D | G29: ص 30
A30: 29 | B30: سلماس — آذربایجان غربی | C30: سلماس | D30: آذربایجان غربی | E30: خیلی زیاد | F30: B | G30: ص 30
A31: 30 | B31: سیه چشمه — آذربایجان غربی | C31: سیه چشمه | D31: آذربایجان غربی | E31: زیاد | F31: C | G31: ص 30
A32: 31 | B32: شاهین دژ — آذربایجان غربی | C32: شاهین دژ | D32: آذربایجان غربی | E32: متوسط | F32: D | G32: ص 31
A33: 32 | B33: قره ضیاءالدین — آذربایجان غربی | C33: قره ضیاءالدین | D33: آذربایجان غربی | E33: زیاد | F33: C | G33: ص 37
... A94: 93 | B94: دهلران — ایلام | C94: دهلران | D94: ایلام | E94: متوسط | F94: D | G94: ص 22
A95: 94 | B95: مهران — ایلام | C95: مهران | D95: ایلام | E95: متوسط | F95: D | G95: ص 48 | H95: ⚠ شمارهٔ ردیف منبع دوپهلو بود؛ نام/سطح خطر مطمئن است.
A96: 95 | B96: موسیان — ایلام | C96: موسیان | D96: ایلام | E96: متوسط | F96: D | G96: ص 48
A97: 96 | B97: اهرم — بوشهر | C97: اهرم | D97: بوشهر | E97: کم | F97: E | G97: ص 7
A98: 97 | B98: برازجان — بوشهر | C98: برازجان | D98: بوشهر | E98: زیاد | F98: C | G98: ص 9
A99: 98 | B99: بندر دیر — بوشهر | C99: بندر دیر | D99: بوشهر | E99: زیاد | F99: C | G99: ص 12
A100: 99 | B100: بندر دیلم — بوشهر | C100: بندر دیلم | D100: بوشهر | E100: متوسط | F100: D | G100: ص 12
A101: 100 | B101: بندر طاهری — بوشهر | C101: بندر طاهری | D101: بوشهر | E101: زیاد | F101: C | G101: ص 12
A102: 101 | B102: بندر عسلویه — بوشهر | C102: بندر عسلویه | D102: بوشهر | E102: زیاد | F102: C | G102: ص 12
A103: 102 | B103: بندر مقام — بوشهر | C103: بندر مقام | D103: بوشهر | E103: زیاد | F103: C | G103: ص 12
A104: 103 | B104: بندر گناوه — بوشهر | C104: بندر گناوه | D104: بوشهر | E104: متوسط | F104: D | G104: ص 12
A105: 104 | B105: بوشهر — بوشهر | C105: بوشهر | D105: بوشهر | E105: متوسط | F105: D | G105: ص 12
A106: 105 | B106: جم — بوشهر | C106: جم | D106: بوشهر | E106: زیاد | F106: C | G106: ص 16
A107: 106 | B107: خارک — بوشهر | C107: خارک | D107: بوشهر | E107: متوسط | F107: D | G107: ص 18
... A353: 352 | B353: خنداب — مرکزی | C353: خنداب | D353: مرکزی | E353: متوسط | F353: D | G353: ص 21
A354: 353 | B354: دلیجان — مرکزی | C354: دلیجان | D354: مرکزی | E354: متوسط | F354: D | G354: ص 21 | H354: ⚠ شمارهٔ ردیف منبع دوپهلو بود؛ نام/سطح خطر مطمئن است.
A355: 354 | B355: ساوه — مرکزی | C355: ساوه | D355: مرکزی | E355: زیاد | F355: C | G355: ص 27
A356: 355 | B356: شازند — مرکزی | C356: شازند | D356: مرکزی | E356: زیاد | F356: C | G356: ص 31
A357: 356 | B357: فرمهین — مرکزی | C357: فرمهین | D357: مرکزی | E357: متوسط | F357: D | G357: ص 36
A358: 357 | B358: محلات — مرکزی | C358: محلات | D358: مرکزی | E358: متوسط | F358: D | G358: ص 45
A359: 358 | B359: نوبران — مرکزی | C359: نوبران | D359: مرکزی | E359: زیاد | F359: C | G359: ص 51
A360: 359 | B360: کمیجان — مرکزی | C360: کمیجان | D360: مرکزی | E360: متوسط | F360: D | G360: ص 40
A361: 360 | B361: بستک — هرمزگان | C361: بستک | D361: هرمزگان | E361: زیاد | F361: C | G361: ص 9
A362: 361 | B362: بندر خمیر — هرمزگان | C362: بندر خمیر | D362: هرمزگان | E362: زیاد | F362: C | G362: ص 12
A363: 362 | B363: بندر عباس — هرمزگان | C363: بندر عباس | D363: هرمزگان | E363: زیاد | F363: C | G363: ص 12
A364: 363 | B364: بندر لنگه — هرمزگان | C364: بندر لنگه | D364: هرمزگان | E364: زیاد | F364: C | G364: ص 12
A365: 364 | B365: جاسک — هرمزگان | C365: جاسک | D365: هرمزگان | E365: زیاد | F365: C | G365: ص 15
A366: 365 | B366: حاجی آباد — هرمزگان | C366: حاجی آباد | D366: هرمزگان | E366: زیاد | F366: C | G366: ص 18
... A478: 477 | B478: خور — یزد | C478: خور | D478: یزد | E478: متوسط | F478: D | G478: ص 21
A479: 478 | B479: دهشیر — یزد | C479: دهشیر | D479: یزد | E479: متوسط | F479: D | G479: ص 22 | H479: ⚠ شمارهٔ ردیف منبع دوپهلو بود؛ نام/سطح خطر مطمئن است.
A480: 479 | B480: دیهوک — یزد | C480: دیهوک | D480: یزد | E480: خیلی زیاد | F480: B | G480: ص 24
A481: 480 | B481: رباط پشت بادام — یزد | C481: رباط پشت بادام | D481: یزد | E481: زیاد | F481: C | G481: ص 24
A482: 481 | B482: ساغند — یزد | C482: ساغند | D482: یزد | E482: زیاد | F482: C | G482: ص 27
A483: 482 | B483: طبس — یزد | C483: طبس | D483: یزد | E483: خیلی زیاد | F483: B | G483: ص 33
A484: 483 | B484: عقداء — یزد | C484: عقداء | D484: یزد | E484: خیلی زیاد | F484: B | G484: ص 36
A485: 484 | B485: مروست — یزد | C485: مروست | D485: یزد | E485: زیاد | F485: C | G485: ص 48
A486: 485 | B486: مهریز — یزد | C486: مهریز | D486: یزد | E486: متوسط | F486: D | G486: ص 48
A487: 486 | B487: میبد — یزد | C487: میبد | D487: یزد | E487: متوسط | F487: D | G487: ص 48
A488: 487 | B488: نایین — یزد | C488: نایین | D488: یزد | E488: خیلی زیاد | F488: B | G488: ص 51
A489: 488 | B489: هرات — یزد | C489: هرات | D489: یزد | E489: زیاد | F489: C | G489: ص 51
A490: 489 | B490: یزد — یزد | C490: یزد | D490: یزد | E490: متوسط | F490: D | G490: ص 52

Sheet Rate-EQ-SwissRe
A1: روش نرخ‌گذاری زلزلهٔ سوئیس‌ری (E = E1 × E2 × Zone) — بازسازی‌شده از متن اصلی EAR Rating Guide، بخش ۴.۳.۱ و بخش ۹
A3: جدول E1 — حساسیت ذاتی تجهیزات نسبت به زلزله (منبع: EAR Rating Guide, TABLE E1)
A4: کلاس (ورودی Data!C15) | B4: توصیف | C4: مثال تجهیزات | D4: ضریب E1
A5: 1 | B5: اقلام غیرحساس | C5: توربین‌های هیدرولیکی، پرس‌های سنگین، کوره‌های آهنگری، خطوط لوله | D5: 1
A6: 2 | B6: حساسیت کم تا متوسط | C6: موتورهای دیزل، کمپرسورهای پیستونی/سانتریفیوژ، توربوژنراتور بخار/گاز، ظروف تحت فشار | D6: 2
A7: 3 | B7: حساس | C7: نوار نقاله، جرثقیل پلی، دیگ‌های بخار، کوره‌های سیمان، مخازن بزرگ سطح زمین | D7: 3
A8: 4 | B8: بسیار حساس | C8: کامپیوتر، ترانسفورماتور، تجهیزات پست برق، تأسیسات دارویی، راکتورها | D8: 4
A10: جدول E2 — مقاومت سازهٔ ساختمان دربرگیرندهٔ تجهیزات (منبع: EAR Rating Guide, TABLE E2)
A11: کلاس (ورودی Data!C16) | B11: سازهٔ نگهدارنده | C11: دیوار/جداکننده | D11: ضریب E2
A12: 1 | B12: اسکلت فولادی | C12: دیوار پوششی فلزی/پلاستیکی سبک یا فضای باز | D12: 1
A13: 2 | B13: اسکلت فولادی | C13: آزبست موج‌دار | D13: 1.5
A14: 3 | B14: اسکلت بتن مسلح | C14: دیوار پوششی سبک، فلز/پلاستیک/شیشه | D14: 2
A15: 4 | B15: فولاد یا بتن مسلح | C15: دیوار برشی داخلی سخت + پوشش سبک | D15: 2.5
A16: 5 | B16: بتن مسلح | C16: فقط ستون‌ها سخت، بدون هستهٔ سخت؛ دیوار آجر/بلوک | D16: 3
A17: 6 | B17: بنایی آجری | C17: ساختمان‌های آجری/پیش‌ساختهٔ معمولی | D17: 5
A19: نگاشت سطح خطر استاندارد ۲۸۰۰ به Zone سوئیس‌ری — مصوب کاربر در گفتگوی ممیزی (سطح اطمینان: متوسط؛ قابل بازنگری)
A20: سطح خطر ۲۸۰۰ | B20: Zone سوئیس‌ری | C20: نسبت شتاب A متناظر (۲۸۰۰) | D20: یادداشت
A21: خیلی زیاد | B21: B | C21: 0.35 | D21: معادل «خیلی‌سنگین». در متن رسمی استاندارد ۲۸۰۰ این رده «بسیار زیاد» نامیده می‌شود (مترادف با «خیلی زیاد» در سند اسکن‌شدهٔ منبع طبقه‌بندی شهرها). Zone A (فاجعه‌بار) عمداً برای هیچ نقطه‌ای در ایران استفاده نشد.
A22: زیاد | B22: C | C22: 0.3 | D22: معادل «سنگین»
A23: متوسط | B23: D | C23: 0.25 | D23: معادل «متوسط»
A24: کم | B24: E | C24: 0.2 | D24: معادل «کم» — طبق منبع اصلی، Zone E همواره بارگذاری صفر دارد
A25: Zone A (فاجعه‌بار) — رزرو، بدون تخصیص در ایران
A27: جدول E — نرخ ماهانهٔ زلزله (‰) بر حسب Zone و فاکتور ترکیبی E=E1×E2 (منبع: EAR Rating Guide, Section 9, TABLE E)
A28: فاکتور E | B28: Zone A (فاجعه‌بار) | C28: Zone B (خیلی‌سنگین) | D28: Zone C (سنگین) | E28: Zone D (متوسط) | F28: Zone E (کم)
A29: 1 | B29: 0.022 | C29: 0 | D29: 0 | E29: 0 | F29: 0
A30: 1.5 | B30: 0.035 | C30: 0 | D30: 0 | E30: 0 | F30: 0
A31: 2 | B31: 0.042 | C31: 0 | D31: 0 | E31: 0 | F31: 0
A32: 2.5 | B32: 0.052 | C32: 0.021 | D32: 0 | E32: 0 | F32: 0
A33: 3 | B33: 0.064 | C33: 0.026 | D33: 0 | E33: 0 | F33: 0
A34: 4 | B34: 0.085 | C34: 0.034 | D34: 0 | E34: 0 | F34: 0
A35: 5 | B35: 0.11 | C35: 0.042 | D35: 0 | E35: 0 | F35: 0
A36: 6 | B36: 0.13 | C36: 0.051 | D36: 0.022 | E36: 0 | F36: 0
A37: 8 | B37: 0.17 | C37: 0.067 | D37: 0.029 | E37: 0 | F37: 0
A38: 10 | B38: 0.21 | C38: 0.085 | D38: 0.036 | E38: 0 | F38: 0
A39: 12.5 | B39: 0.27 | C39: 0.105 | D39: 0.045 | E39: 0.021 | F39: 0
A40: 15 | B40: 0.32 | C40: 0.125 | D40: 0.055 | E40: 0.026 | F40: 0
A41: 20 | B41: 0.42 | C41: 0.165 | D41: 0.073 | E41: 0.034 | F41: 0
A43: یادداشت‌های روش‌شناختی: ۱) نرخ‌های این جدول به هزار (‰) در ماه هستند. حق‌بیمهٔ زلزله = نرخ ماهانه × مدت پروژه (ماه) — نه یک ضریب یک‌بارمصرف. ۲) اگر E محاسبه‌شده بین دو مقدار جدول باشد، به‌صورت محافظه‌کارانه به بالاترین مقدار جدول گرد می‌شود (فرض مهندسی، تأیید نشده از متن مبدأ — قابل تغییر به میان‌یابی خطی در صورت درخواست). ۳) Zone A هرگز در ایران انتخاب نمی‌شود چون بالاترین ردهٔ استاندارد ۲۸۰۰ (بسیار زیاد، A=۰.۳۵) به Zone B نگاشت شده — تصمیم کاربر، سطح اطمینان متوسط. ۴) صحت پیشروی عددی جدول E با یادداشت‌های داخلی نسخهٔ قبلی Rate-Region (آستانه‌های E≥۶ برای C، E≥۱۲.۵ برای D) مطابقت کامل دارد. ۵) OCR متن مبدأ در برخی نویسه‌ها مخدوش بود؛ ارقام جدول با الگوی پیوستهٔ ستون‌ها بازسازی شدند، نه با حدس — پیش از استناد رسمی با نسخهٔ چاپی مقابله شود.

Sheet Hazard-Province-Index
A1: # | B1: استان | C1: کد ایمن (Defined Name) | D1: ردیف شروع | E1: ردیف پایان | F1: تعداد شهر
A2: 1 | B2: آذربایجان شرقی | C2: HZP_01 | D2: 2 | E2: 22 | F2: 21
A3: 2 | B3: آذربایجان غربی | C3: HZP_02 | D3: 23 | E3: 41 | F3: 19
A4: 3 | B4: اردبیل | C4: HZP_03 | D4: 42 | E4: 56 | F4: 15
A5: 4 | B5: اصفهان | C5: HZP_04 | D5: 57 | E5: 88 | F5: 32
A6: 5 | B6: ایلام | C6: HZP_05 | D6: 89 | E6: 96 | F6: 8
A7: 6 | B7: بوشهر | C7: HZP_06 | D7: 97 | E7: 116 | F7: 20
A8: 7 | B8: تهران | C8: HZP_07 | D8: 117 | E8: 142 | F8: 26
A9: 8 | B9: خراسان جنوبی | C9: HZP_08 | D9: 143 | E9: 155 | F9: 13
A10: 9 | B10: خراسان رضوی | C10: HZP_09 | D10: 156 | E10: 181 | F10: 26
A11: 10 | B11: خراسان شمالی | C11: HZP_10 | D11: 182 | E11: 191 | F11: 10
A12: 11 | B12: خوزستان | C12: HZP_11 | D12: 192 | E12: 221 | F12: 30
A13: 12 | B13: زنجان | C13: HZP_12 | D13: 222 | E13: 231 | F13: 10
... A31: 30 | B31: یزد | C31: HZP_30 | D31: 473 | E31: 490 | F31: 18
A33: این شیت زیرساخت دراپ‌داون آبشاری «استان → شهرستان» در Data!C7/H7 است. هر ردیف یک Defined Name (کد ایمن HZP_xx) دارد که به بازهٔ ردیف‌های همان استان در ستون C شیت 'Hazard-Cities-2800' اشاره می‌کند. Data!I7 نام استان انتخابی را به کد ایمن ترجمه می‌کند و Data!H7 (دراپ‌داون شهرستان) با INDIRECT(کد ایمن) فقط شهرهای همان استان را نشان می‌دهد — دقیقاً همان الگوی 'گروه صنعتی → زیرگروه' که در C4/C5 همین شیت از قبل وجود دارد.
